Workbook
Name _Toc74834714: DropDown!$O$1
Name AuswahlX: [1]DropDown!$H$2:$H$3
Name AuswahlX: [1]DropDown!$H$2:$H$3
Name AuswahlX: DropDown!$H$2:$H$3
Name Fehlerart: [1]DropDown!$A$2:$A$12
Name Fehlerart: [1]DropDown!$A$2:$A$12
Name Fehlerart: DropDown!$A$4:$A$13
Name KSK_No.: 'D1-D2-D3'!$D$14
Name Product: DropDown!$N$2:$N$3
Name Product: DropDown!$N$2:$N$3
Name sortingaction: 'D1-D2-D3'!$AD$93
Name Sprachen: [1]DropDown!$C$2:$C$15
Name Sprachen: [1]DropDown!$C$2:$C$15
Name Sprachen: DropDown!$C$2:$C$15
Name Syst: #REF!
Name Syst: #REF!
Name Syst: #REF!
Name X: #REF!
Name X: #REF!
Name X: #REF!
Name X: #REF!
Name X: #REF!
Name X: #REF!
Name YesNo: #REF!
Name YesNo: #REF!
Name YesNo: #REF!
Name YesNo: #REF!
Name YesNo: #REF!
Name YesNo: #REF!
Name YN: #REF!
Name YN: #REF!
Name YN: #REF!
Name YN: #REF!
Name YN: #REF!
Name YN: #REF!

Sheet D1-D2-D3
R2: =INDIRECT($J$4&"!C2")&" "&INDIRECT($J$4&"!C7") -> PROBLEM SOLVING SHEET Basic Data-Team-Problem Description-Immediate Action(s) | BN2: =INDIRECT($J$4&"!C3") -> PSS No. | BW2: =AI4 -> 0 | CG2: 4.15.03.00 | CY2: =INDIRECT($J$4&"!C4") -> Page 1: D0-D1-D2-D3
C4: =INDIRECT($J$4&"!C5") -> Language | J4: ENGLISH | AA4: =INDIRECT($J$4&"!C3") -> PSS No. | AZ4: =INDIRECT($J$4&"!C6") -> Fault type
C7: =INDIRECT($J$4&"!C8") -> Kroschu plant | AF7: =INDIRECT($J$4&"!C9") -> Opening date | BU7: Report version | DU7: 1 | DV7: =IF(DW7="","",MAX($DV$6:DV6)+1) -> 1 | DW7: =IF($D14=DropDown!$N$8,DropDown!N5,"") -> Int. KSK-No. | DX7: =VLOOKUP(DU7,$DV$7:$DW$9,2,FALSE) -> Int. KSK-No.
C8: =INDIRECT($J$4&"!C10") -> Customer | AF8: =INDIRECT($J$4&"!C11") -> Project | BU8: =INDIRECT($J$4&"!C12") -> Customer complaint No. | DU8: 2 | DV8: =IF(DW8="","",MAX($DV$6:DV7)+1) | DW8: =IF($D14=DropDown!$N$9,DropDown!N6,"")
DU9: 3 | DV9: =IF(DW9="","",MAX($DV$6:DV8)+1) | DW9: =IF($D14=DropDown!$N$10,DropDown!N7,"")
B11: =INDIRECT($J$4&"!C13") -> Basic Data
D14: KSK | AM14: =DX7 -> Int. KSK-No. | CC14: =INDIRECT($J$4&"!C21") -> Production date/time
DU15: 1 | DV15: =IF(DW15="","",MAX(DV14:DV14)+1) -> 1 | DW15: =IF($CC16=DropDown!$L$15,DropDown!L18,"") -> PSC | DX15: =VLOOKUP(DU15,DV15:DW16,2,FALSE) -> PSC
D16: =INDIRECT($J$4&"!C17") -> Index | AM16: =INDIRECT($J$4&"!C16") -> Lfd./Serial | CC16: Safety-relevant characterisitc | DU16: 2 | DV16: =IF(DW16="","",MAX($DV$14:DV15)+1) | DW16: =IF($CC16=DropDown!$L$16,DropDown!L19,"")
DU17: 3
B18: =INDIRECT($J$4&"!C22") -> D1 - Team
D20: =INDIRECT($J$4&"!C23") -> Coordinator (/Champion) | BL20: =INDIRECT($J$4&"!C26") -> Sponsor
D21: =INDIRECT($J$4&"!C24") -> Name, prename | T21: =INDIRECT($J$4&"!C25") -> Department/function Contact data | BK21: =INDIRECT($J$4&"!C24") -> Name, prename | CD21: =INDIRECT($J$4&"!C25") -> Department/function Contact data
D24: =INDIRECT($J$4&"!C27") -> Members
B33: =INDIRECT($J$4&"!C28") -> D2 - Problem description
D36: =INDIRECT($J$4&"!C29") -> NOK PART | BL36: =INDIRECT($J$4&"!C30") -> OK PART
D46: =INDIRECT($J$4&"!C65") -> Symptom description | AU46: =INDIRECT($J$4&"!C43") -> IS | CG46: =INDIRECT($J$4&"!C44") -> IS NOT
AR47: =INDIRECT($J$4&"!C45") -> What | AU47: =INDIRECT($J$4&"!C49") -> Which product/process does the problem concern ? | CG47: =INDIRECT($J$4&"!C57") -> Are there comparable products/processes where the problem did not occur ?
D48: =INDIRECT($J$4&"!C66") -> Problem description
AU49: =INDIRECT($J$4&"!C50") -> What is the deviation ? | CG49: =INDIRECT($J$4&"!C58") -> Are additional deviations of the affected product/process expected ?
D51: =INDIRECT($J$4&"!C31")&" & "&INDIRECT($J$4&"!C32") -> Fault code & Fault description | AR51: =INDIRECT($J$4&"!C46") -> Where | AU51: =INDIRECT($J$4&"!C51") -> Where was the product/process when the deviation first occurred ? | CG51: =INDIRECT($J$4&"!C59") -> Where else could the deviation occur ?
D52: =VLOOKUP(AH51,'Fault catalogue'!A2:C574,3,0) -> #N/A
AU53: =INDIRECT($J$4&"!C52") -> Where in the product/process did the deviation occur ? | CG53: =INDIRECT($J$4&"!C60") -> What are the names of the neighbouring products/processes and which of them are not affected by the deviation ?
D54: =INDIRECT($J$4&"!C33") -> Fault location
AR55: =INDIRECT($J$4&"!C47") -> When | AU55: =INDIRECT($J$4&"!C53") -> When was the deviation first detected ? (Date of occurrence & life cycle) | CG55: =INDIRECT($J$4&"!C61") -> Can the problem have occurred in an earlier phase/time ?
D56: =INDIRECT($J$4&"!C34") -> Workplace
D57: =INDIRECT($J$4&"!C35") -> Qualification | AU57: =INDIRECT($J$4&"!C54") -> Is there a recognisable systematic of failures ? (single failure, continuous increase/fall, random or cyclical) ? | CG57: =INDIRECT($J$4&"!C62") -> Can additional failures be expected since the discovery ?
D58: =INDIRECT($J$4&"!C36") -> Line
D59: =INDIRECT($J$4&"!C37") -> Team | AR59: =INDIRECT($J$4&"!C48") -> How many | AU59: =INDIRECT($J$4&"!C55") -> How many failures ? (number & PPM's) | CG59: =INDIRECT($J$4&"!C63") -> How many more can be expected in the future ?
D60: =INDIRECT($J$4&"!C38") -> Equipment
D61: =INDIRECT($J$4&"!C39")&":" -> Repetitive fault: | R61: =INDIRECT($J$4&"!C40")&":" -> If yes, PSS No./ 8D No.: | AU61: =INDIRECT($J$4&"!C56") -> Which persons are affected ? What costs have been incurred so far ? Will these rise, fall or remain stable ? | CG61: =INDIRECT($J$4&"!C64") -> What can lead to worse/better circumstances ?
B65: =INDIRECT($J$4&"!C67") -> D3 - Immediate action(s)
BR66: =INDIRECT($J$4&"!C68")&":" -> Status: | CZ66: =INDIRECT($J$4&"!C69") -> Date
D69: =INDIRECT($J$4&"!C70") -> Were the relevant emloyees informed ? | AR69: =INDIRECT($J$4&"!C69") -> Date | BW69: =INDIRECT($J$4&"!C83") -> Responsible
D71: =INDIRECT($J$4&"!C71") -> Limitation of affected products
D73: =INDIRECT($J$4&"!C72") -> Is it possible to do a limitation of the affected products ? | BA73: Yes
T75: =INDIRECT($J$4&"!C73") -> delivered to the customer | AZ75: =INDIRECT($J$4&"!C74") -> on transit | BX75: =INDIRECT($J$4&"!C75") -> at Kroschu
AU77: → | BB77: =SUM(AR75,BP75,CN75) -> 0 | BL77: =INDIRECT($J$4&"!C76") -> total amount of affected products
D79: =INDIRECT($J$4&"!C80") -> Action | CC79: =INDIRECT($J$4&"!C81") -> Effectiveness verification
AZ80: =INDIRECT($J$4&"!C262") -> Start date | BG80: =INDIRECT($J$4&"!C263") -> Closing date | BN80: =INDIRECT($J$4&"!C83") -> Responsible | BX80: =INDIRECT($J$4&"!C82") -> Method | CW80: =INDIRECT($J$4&"!C69") -> Date | DD80: =INDIRECT($J$4&"!C83") -> Responsible | DM80: =INDIRECT($J$4&"!C264") -> Result
D81: =INDIRECT($J$4&"!C77") -> Measures for continuing secure production at customer
D84: =INDIRECT($J$4&"!C78") -> Measures for continuing delivery
D87: =INDIRECT($J$4&"!C79") -> Measures for continuing Kroschu-production
H91: =INDIRECT($J$4&"!C73") -> delivered to the customer | AU91: =INDIRECT($J$4&"!C74") -> on transit | CH91: =INDIRECT($J$4&"!C75") -> at Kroschu
D93: =INDIRECT($J$4&"!C85") -> Sorting actions | H93: =INDIRECT($J$4&"!C85") -> Sorting actions | AU93: =INDIRECT($J$4&"!C85") -> Sorting actions | CH93: =INDIRECT($J$4&"!C85") -> Sorting actions
H95: =INDIRECT($J$4&"!C86") -> Quantity sorted | AU95: =INDIRECT($J$4&"!C86") -> Quantity sorted | CH95: =INDIRECT($J$4&"!C86") -> Quantity sorted
H98: =INDIRECT($J$4&"!C87") -> No. NOK parts found | AU98: =INDIRECT($J$4&"!C87") -> No. NOK parts found | CH98: =INDIRECT($J$4&"!C87") -> No. NOK parts found
H101: =INDIRECT($J$4&"!C88") -> Identification OK Parts | AU101: =INDIRECT($J$4&"!C88") -> Identification OK Parts | CH101: =INDIRECT($J$4&"!C88") -> Identification OK Parts
CH103: =INDIRECT($J$4&"!C89") -> clean point
L106: =SUM(AD95,BQ95,DD95) -> 0 | R106: =INDIRECT($J$4&"!C90") -> total amount of sorted parts | AR106: =SUM(AD98,BQ98,DD98) -> 0 | AX106: =INDIRECT($J$4&"!C91") -> total amount of NOK parts found | CB106: =L106-AR106 -> 0 | CH106: =INDIRECT($J$4&"!C92") -> total amount of OK parts identified
D109: =INDIRECT($J$4&"!C93") -> Comments
B113: =INDIRECT($J$4&"!C104") -> Other information

Sheet Risk assesment (for D3 & D5)
P2: =INDIRECT('D1-D2-D3'!$J$4&"!C2")&"/ "&'8D-Report (with link)'!R2 -> PROBLEM SOLVING SHEET/ 8D-report | AI2: =INDIRECT('D1-D2-D3'!$J$4&"!C3") -> PSS No. | AO2: ='D1-D2-D3'!AI4 -> 0 | AU2: 4.15.03.00 | BC2: =INDIRECT('D1-D2-D3'!$J$4&"!C233") -> Risk assessment
D6: =INDIRECT('D1-D2-D3'!$J$4&"!C234") -> Probability | S6: =INDIRECT('D1-D2-D3'!$J$4&"!C235") -> Effect | AG6: =INDIRECT('D1-D2-D3'!$J$4&"!C246") -> Level | BD6: Matrix
D8: 1 | E8: =INDIRECT('D1-D2-D3'!$J$4&"!C236") -> Remote - Chance for this event is almost 0 | S8: 1 | T8: =INDIRECT('D1-D2-D3'!$J$4&"!C241") -> ignorable - ignorable damages without impact | BB8: =INDIRECT('D1-D2-D3'!$J$4&"!C234") -> Probability | BD8: 5 | BG8: 10 | BJ8: 15 | BM8: 20 | BP8: 25
D9: 2 | E9: =INDIRECT('D1-D2-D3'!$J$4&"!C237") -> Unlikely - Eventaulity exists but is not going to happen | S9: 2 | T9: =INDIRECT('D1-D2-D3'!$J$4&"!C242") -> low - slightly damages outside visible are | AG9: high | AI9: =INDIRECT('D1-D2-D3'!$J$4&"!C247") -> 12 or higher | AM9: =INDIRECT('D1-D2-D3'!$J$4&"!C251") -> measures to be discussed with customer | BD9: 4 | BG9: 8 | BJ9: 12 | BM9: 16 | BP9: 20
D10: 3 | E10: =INDIRECT('D1-D2-D3'!$J$4&"!C238") -> Possible - Event can occurre sometime | S10: 3 | T10: =INDIRECT('D1-D2-D3'!$J$4&"!C243") -> mid - noticable damages in visible area | AG10: mid | AI10: =INDIRECT('D1-D2-D3'!$J$4&"!C248") -> 7 till 11 | AM10: =INDIRECT('D1-D2-D3'!$J$4&"!C252") -> measures upon request of customer | BD10: 3 | BG10: 6 | BJ10: 9 | BM10: 12 | BP10: 15
D11: 4 | E11: =INDIRECT('D1-D2-D3'!$J$4&"!C239") -> Probable - Event will happen sometimes and can be expected | S11: 4 | T11: =INDIRECT('D1-D2-D3'!$J$4&"!C244") -> high - damage with functional impact | AG11: ALARP | AI11: =INDIRECT('D1-D2-D3'!$J$4&"!C249") -> 5 till 6 | AM11: =INDIRECT('D1-D2-D3'!$J$4&"!C253") -> as low as reasonable practicable | BD11: 2 | BG11: 4 | BJ11: 6 | BM11: 8 | BP11: 10
D12: 5 | E12: =INDIRECT('D1-D2-D3'!$J$4&"!C240") -> Almost certain - Event happens often and is expected | S12: 5 | T12: =INDIRECT('D1-D2-D3'!$J$4&"!C245") -> catastrophic - catastrophic damage with consequences | AG12: low | AI12: =INDIRECT('D1-D2-D3'!$J$4&"!C250") -> 1 till 4 | AM12: =INDIRECT('D1-D2-D3'!$J$4&"!C254") -> no further action needed | BD12: 1 | BG12: 2 | BJ12: 3 | BM12: 4 | BP12: 5
BD13: =INDIRECT('D1-D2-D3'!$J$4&"!C235") -> Effect
D17: ='D1-D2-D3'!B65 -> D3 - Immediate action(s) | AE17: =INDIRECT('D1-D2-D3'!$J$4&"!C258") -> Initial evaluation | BE17: =INDIRECT('D1-D2-D3'!$J$4&"!C260") -> New evaluation
U18: =INDIRECT('D1-D2-D3'!$J$4&"!C256") -> Hazard/ Risk | AE18: =INDIRECT('D1-D2-D3'!$J$4&"!C234")&" P" -> Probability P | AI18: =INDIRECT('D1-D2-D3'!$J$4&"!C235")&" E" -> Effect E | AL18: =INDIRECT('D1-D2-D3'!$J$4&"!C257")&" PxE" -> Risk height PxE | AO18: =INDIRECT('D1-D2-D3'!$J$4&"!C246") -> Level | AS18: =INDIRECT('D1-D2-D3'!$J$4&"!C259") -> Measures | BE18: =INDIRECT('D1-D2-D3'!$J$4&"!C234")&" P" -> Probability P | BI18: =INDIRECT('D1-D2-D3'!$J$4&"!C235")&" E" -> Effect E | BL18: =INDIRECT('D1-D2-D3'!$J$4&"!C257")&" PxE" -> Risk height PxE | BO18: =INDIRECT('D1-D2-D3'!$J$4&"!C246") -> Level | BY18: Level 1 | CC18: Level 2
D19: ='D1-D2-D3'!D81 -> Measures for continuing secure production at customer | H19: =IF('D1-D2-D3'!L81="","",'D1-D2-D3'!L81) | K19: =IF('D1-D2-D3'!T81="","",'D1-D2-D3'!T81) | AL19: =BX19 | AO19: =IF(BW19>11,"high",IF(BW19>6,"mid",IF(BW19>4,"ALARP",IF(BW19=0,"",IF(BW19>=1,"low"))))) | BL19: =CB19 | BO19: =CC19 | BW19: =AE19*AI19 -> 0 | BX19: =IF(BW19=0,"",IF(BW19>=1,BW19)) | BY19: =IF(BW19>11,"high",IF(BW19>6,"mid",IF(BW19>4,"ALARP",IF(BW19=0,"",IF(BW19>=1,"low"))))) | CA19: =BE19*BI19 -> 0 | CB19: =IF(CA19=0,"",IF(CA19>=1,CA19)) | CC19: =IF(CA19>11,"high",IF(CA19>6,"mid",IF(CA19>4,"ALARP",IF(CA19=0,"",IF(CA19>=1,"low")))))
H20: =IF('D1-D2-D3'!L82="","",'D1-D2-D3'!L82) | K20: =IF('D1-D2-D3'!T82="","",'D1-D2-D3'!T82) | AL20: =BX20 | AO20: =IF(BW20>11,"high",IF(BW20>6,"mid",IF(BW20>4,"ALARP",IF(BW20=0,"",IF(BW20>=1,"low"))))) | BL20: =CB20 | BO20: =CC20 | BW20: =AE20*AI20 -> 0 | BX20: =IF(BW20=0,"",IF(BW20>=1,BW20)) | BY20: =IF(BW20>11,"high",IF(BW20>6,"mid",IF(BW20>4,"ALARP",IF(BW20=0,"",IF(BW20>=1,"low"))))) | CA20: =BE20*BI20 -> 0 | CB20: =IF(CA20=0,"",IF(CA20>=1,CA20)) | CC20: =IF(CA20>11,"high",IF(CA20>6,"mid",IF(CA20>4,"ALARP",IF(CA20=0,"",IF(CA20>=1,"low")))))
H21: =IF('D1-D2-D3'!L83="","",'D1-D2-D3'!L83) | K21: =IF('D1-D2-D3'!T83="","",'D1-D2-D3'!T83) | AL21: =BX21 | AO21: =IF(BW21>11,"high",IF(BW21>6,"mid",IF(BW21>4,"ALARP",IF(BW21=0,"",IF(BW21>=1,"low"))))) | BL21: =CB21 | BO21: =CC21 | BW21: =AE21*AI21 -> 0 | BX21: =IF(BW21=0,"",IF(BW21>=1,BW21)) | BY21: =IF(BW21>11,"high",IF(BW21>6,"mid",IF(BW21>4,"ALARP",IF(BW21=0,"",IF(BW21>=1,"low"))))) | CA21: =BE21*BI21 -> 0 | CB21: =IF(CA21=0,"",IF(CA21>=1,CA21)) | CC21: =IF(CA21>11,"high",IF(CA21>6,"mid",IF(CA21>4,"ALARP",IF(CA21=0,"",IF(CA21>=1,"low")))))
D22: ='D1-D2-D3'!D84 -> Measures for continuing delivery | H22: =IF('D1-D2-D3'!L84="","",'D1-D2-D3'!L84) | K22: =IF('D1-D2-D3'!T84="","",'D1-D2-D3'!T84) | AL22: =BX22 | AO22: =IF(BW22>11,"high",IF(BW22>6,"mid",IF(BW22>4,"ALARP",IF(BW22=0,"",IF(BW22>=1,"low"))))) | BL22: =CB22 | BO22: =CC22 | BW22: =AE22*AI22 -> 0 | BX22: =IF(BW22=0,"",IF(BW22>=1,BW22)) | BY22: =IF(BW22>11,"high",IF(BW22>6,"mid",IF(BW22>4,"ALARP",IF(BW22=0,"",IF(BW22>=1,"low"))))) | CA22: =BE22*BI22 -> 0 | CB22: =IF(CA22=0,"",IF(CA22>=1,CA22)) | CC22: =IF(CA22>11,"high",IF(CA22>6,"mid",IF(CA22>4,"ALARP",IF(CA22=0,"",IF(CA22>=1,"low")))))
H23: =IF('D1-D2-D3'!L85="","",'D1-D2-D3'!L85) | K23: =IF('D1-D2-D3'!T85="","",'D1-D2-D3'!T85) | AL23: =BX23 | AO23: =IF(BW23>11,"high",IF(BW23>6,"mid",IF(BW23>4,"ALARP",IF(BW23=0,"",IF(BW23>=1,"low"))))) | BL23: =CB23 | BO23: =CC23 | BW23: =AE23*AI23 -> 0 | BX23: =IF(BW23=0,"",IF(BW23>=1,BW23)) | BY23: =IF(BW23>11,"high",IF(BW23>6,"mid",IF(BW23>4,"ALARP",IF(BW23=0,"",IF(BW23>=1,"low"))))) | CA23: =BE23*BI23 -> 0 | CB23: =IF(CA23=0,"",IF(CA23>=1,CA23)) | CC23: =IF(CA23>11,"high",IF(CA23>6,"mid",IF(CA23>4,"ALARP",IF(CA23=0,"",IF(CA23>=1,"low")))))
H24: =IF('D1-D2-D3'!L86="","",'D1-D2-D3'!L86) | K24: =IF('D1-D2-D3'!T86="","",'D1-D2-D3'!T86) | AL24: =BX24 | AO24: =IF(BW24>11,"high",IF(BW24>6,"mid",IF(BW24>4,"ALARP",IF(BW24=0,"",IF(BW24>=1,"low"))))) | BL24: =CB24 | BO24: =CC24 | BW24: =AE24*AI24 -> 0 | BX24: =IF(BW24=0,"",IF(BW24>=1,BW24)) | BY24: =IF(BW24>11,"high",IF(BW24>6,"mid",IF(BW24>4,"ALARP",IF(BW24=0,"",IF(BW24>=1,"low"))))) | CA24: =BE24*BI24 -> 0 | CB24: =IF(CA24=0,"",IF(CA24>=1,CA24)) | CC24: =IF(CA24>11,"high",IF(CA24>6,"mid",IF(CA24>4,"ALARP",IF(CA24=0,"",IF(CA24>=1,"low")))))
D25: ='D1-D2-D3'!D87 -> Measures for continuing Kroschu-production | H25: =IF('D1-D2-D3'!L87="","",'D1-D2-D3'!L87) | K25: =IF('D1-D2-D3'!T87="","",'D1-D2-D3'!T87) | AL25: =BX25 | AO25: =IF(BW25>11,"high",IF(BW25>6,"mid",IF(BW25>4,"ALARP",IF(BW25=0,"",IF(BW25>=1,"low"))))) | BL25: =CB25 | BO25: =CC25 | BW25: =AE25*AI25 -> 0 | BX25: =IF(BW25=0,"",IF(BW25>=1,BW25)) | BY25: =IF(BW25>11,"high",IF(BW25>6,"mid",IF(BW25>4,"ALARP",IF(BW25=0,"",IF(BW25>=1,"low"))))) | CA25: =BE25*BI25 -> 0 | CB25: =IF(CA25=0,"",IF(CA25>=1,CA25)) | CC25: =IF(CA25>11,"high",IF(CA25>6,"mid",IF(CA25>4,"ALARP",IF(CA25=0,"",IF(CA25>=1,"low")))))
H26: =IF('D1-D2-D3'!L88="","",'D1-D2-D3'!L88) | K26: =IF('D1-D2-D3'!T88="","",'D1-D2-D3'!T88) | AL26: =BX26 | AO26: =IF(BW26>11,"high",IF(BW26>6,"mid",IF(BW26>4,"ALARP",IF(BW26=0,"",IF(BW26>=1,"low"))))) | BL26: =CB26 | BO26: =CC26 | BW26: =AE26*AI26 -> 0 | BX26: =IF(BW26=0,"",IF(BW26>=1,BW26)) | BY26: =IF(BW26>11,"high",IF(BW26>6,"mid",IF(BW26>4,"ALARP",IF(BW26=0,"",IF(BW26>=1,"low"))))) | CA26: =BE26*BI26 -> 0 | CB26: =IF(CA26=0,"",IF(CA26>=1,CA26)) | CC26: =IF(CA26>11,"high",IF(CA26>6,"mid",IF(CA26>4,"ALARP",IF(CA26=0,"",IF(CA26>=1,"low")))))
H27: =IF('D1-D2-D3'!L89="","",'D1-D2-D3'!L89) | K27: =IF('D1-D2-D3'!T89="","",'D1-D2-D3'!T89) | AL27: =BX27 | AO27: =IF(BW27>11,"high",IF(BW27>6,"mid",IF(BW27>4,"ALARP",IF(BW27=0,"",IF(BW27>=1,"low"))))) | BL27: =CB27 | BO27: =CC27 | BW27: =AE27*AI27 -> 0 | BX27: =IF(BW27=0,"",IF(BW27>=1,BW27)) | BY27: =IF(BW27>11,"high",IF(BW27>6,"mid",IF(BW27>4,"ALARP",IF(BW27=0,"",IF(BW27>=1,"low"))))) | CA27: =BE27*BI27 -> 0 | CB27: =IF(CA27=0,"",IF(CA27>=1,CA27)) | CC27: =IF(CA27>11,"high",IF(CA27>6,"mid",IF(CA27>4,"ALARP",IF(CA27=0,"",IF(CA27>=1,"low")))))
D29: ='D4.5Why''s-D5-D6'!AB6 -> D5 - Corrective Action(s)
BW30: P*C | BX30: Result ohne 0 | BY30: LEVEL | CA30: new evaluat | CC30: L | CF30: Risk | CG30: Level | CH30: Measures
D31: =INDIRECT('D1-D2-D3'!$J$4&"!C137") -> Technical consideration | E31: =IF(ISNA('D4.5Why''s-D5-D6'!BY19),"",'D4.5Why''s-D5-D6'!BY19) | AL31: =BX31 | AO31: =IF(BW31>11,"high",IF(BW31>6,"mid",IF(BW31>4,"ALARP",IF(BW31=0,"",IF(BW31>=1,"low"))))) | BL31: =CB31 | BO31: =CC31 | BW31: =AE31*AI31 -> 0 | BX31: =IF(BW31=0,"",IF(BW31>=1,BW31)) | BY31: =IF(BW31>11,"high",IF(BW31>6,"mid",IF(BW31>4,"ALARP",IF(BW31=0,"",IF(BW31>=1,"low"))))) | CA31: =BE31*BI31 -> 0 | CB31: =IF(CA31=0,"",IF(CA31>=1,CA31)) | CC31: =IF(CA31>11,"high",IF(CA31>6,"mid",IF(CA31>4,"ALARP",IF(CA31=0,"",IF(CA31>=1,"low"))))) | CF31: =IF(U31=0,"",IF(ISNA(U31),"",IF(E31<>"",U31,""))) | CG31: =IF(AO31=0,"",IF(ISNA(AO31),"",IF(E31<>"",AO31,""))) | CH31: =IF(AS31=0,"",IF(ISNA(AS31),"",IF(E31<>"",AS31,"")))
E32: =IF(ISNA('D4.5Why''s-D5-D6'!BY20),"",'D4.5Why''s-D5-D6'!BY20) | AL32: =BX32 | AO32: =IF(BW32>11,"high",IF(BW32>6,"mid",IF(BW32>4,"ALARP",IF(BW32=0,"",IF(BW32>=1,"low"))))) | BL32: =CB32 | BO32: =CC32 | BW32: =AE32*AI32 -> 0 | BX32: =IF(BW32=0,"",IF(BW32>=1,BW32)) | BY32: =IF(BW32>11,"high",IF(BW32>6,"mid",IF(BW32>4,"ALARP",IF(BW32=0,"",IF(BW32>=1,"low"))))) | CA32: =BE32*BI32 -> 0 | CB32: =IF(CA32=0,"",IF(CA32>=1,CA32)) | CC32: =IF(CA32>11,"high",IF(CA32>6,"mid",IF(CA32>4,"ALARP",IF(CA32=0,"",IF(CA32>=1,"low"))))) | CF32: =IF(U32=0,"",IF(ISNA(U32),"",IF(E32<>"",U32,""))) | CG32: =IF(AO32=0,"",IF(ISNA(AO32),"",IF(E32<>"",AO32,""))) | CH32: =IF(AS32=0,"",IF(ISNA(AS32),"",IF(E32<>"",AS32,"")))
E33: =IF(ISNA('D4.5Why''s-D5-D6'!BY21),"",'D4.5Why''s-D5-D6'!BY21) | AL33: =BX33 | AO33: =IF(BW33>11,"high",IF(BW33>6,"mid",IF(BW33>4,"ALARP",IF(BW33=0,"",IF(BW33>=1,"low"))))) | BL33: =CB33 | BO33: =CC33 | BW33: =AE33*AI33 -> 0 | BX33: =IF(BW33=0,"",IF(BW33>=1,BW33)) | BY33: =IF(BW33>11,"high",IF(BW33>6,"mid",IF(BW33>4,"ALARP",IF(BW33=0,"",IF(BW33>=1,"low"))))) | CA33: =BE33*BI33 -> 0 | CB33: =IF(CA33=0,"",IF(CA33>=1,CA33)) | CC33: =IF(CA33>11,"high",IF(CA33>6,"mid",IF(CA33>4,"ALARP",IF(CA33=0,"",IF(CA33>=1,"low"))))) | CF33: =IF(U33=0,"",IF(ISNA(U33),"",IF(E33<>"",U33,""))) | CG33: =IF(AO33=0,"",IF(ISNA(AO33),"",IF(E33<>"",AO33,""))) | CH33: =IF(AS33=0,"",IF(ISNA(AS33),"",IF(E33<>"",AS33,"")))
E34: =IF(ISNA('D4.5Why''s-D5-D6'!BY22),"",'D4.5Why''s-D5-D6'!BY22) | AL34: =BX34 | AO34: =IF(BW34>11,"high",IF(BW34>6,"mid",IF(BW34>4,"ALARP",IF(BW34=0,"",IF(BW34>=1,"low"))))) | BL34: =CB34 | BO34: =CC34 | BW34: =AE34*AI34 -> 0 | BX34: =IF(BW34=0,"",IF(BW34>=1,BW34)) | BY34: =IF(BW34>11,"high",IF(BW34>6,"mid",IF(BW34>4,"ALARP",IF(BW34=0,"",IF(BW34>=1,"low"))))) | CA34: =BE34*BI34 -> 0 | CB34: =IF(CA34=0,"",IF(CA34>=1,CA34)) | CC34: =IF(CA34>11,"high",IF(CA34>6,"mid",IF(CA34>4,"ALARP",IF(CA34=0,"",IF(CA34>=1,"low"))))) | CF34: =IF(U34=0,"",IF(ISNA(U34),"",IF(E34<>"",U34,""))) | CG34: =IF(AO34=0,"",IF(ISNA(AO34),"",IF(E34<>"",AO34,""))) | CH34: =IF(AS34=0,"",IF(ISNA(AS34),"",IF(E34<>"",AS34,"")))
E35: =IF(ISNA('D4.5Why''s-D5-D6'!BY23),"",'D4.5Why''s-D5-D6'!BY23) | AL35: =BX35 | AO35: =IF(BW35>11,"high",IF(BW35>6,"mid",IF(BW35>4,"ALARP",IF(BW35=0,"",IF(BW35>=1,"low"))))) | BL35: =CB35 | BO35: =CC35 | BW35: =AE35*AI35 -> 0 | BX35: =IF(BW35=0,"",IF(BW35>=1,BW35)) | BY35: =IF(BW35>11,"high",IF(BW35>6,"mid",IF(BW35>4,"ALARP",IF(BW35=0,"",IF(BW35>=1,"low"))))) | CA35: =BE35*BI35 -> 0 | CB35: =IF(CA35=0,"",IF(CA35>=1,CA35)) | CC35: =IF(CA35>11,"high",IF(CA35>6,"mid",IF(CA35>4,"ALARP",IF(CA35=0,"",IF(CA35>=1,"low"))))) | CF35: =IF(U35=0,"",IF(ISNA(U35),"",IF(E35<>"",U35,""))) | CG35: =IF(AO35=0,"",IF(ISNA(AO35),"",IF(E35<>"",AO35,""))) | CH35: =IF(AS35=0,"",IF(ISNA(AS35),"",IF(E35<>"",AS35,"")))
E36: =IF(ISNA('D4.5Why''s-D5-D6'!BY24),"",'D4.5Why''s-D5-D6'!BY24) | AL36: =BX36 | AO36: =IF(BW36>11,"high",IF(BW36>6,"mid",IF(BW36>4,"ALARP",IF(BW36=0,"",IF(BW36>=1,"low"))))) | BL36: =CB36 | BO36: =CC36 | BW36: =AE36*AI36 -> 0 | BX36: =IF(BW36=0,"",IF(BW36>=1,BW36)) | BY36: =IF(BW36>11,"high",IF(BW36>6,"mid",IF(BW36>4,"ALARP",IF(BW36=0,"",IF(BW36>=1,"low"))))) | CA36: =BE36*BI36 -> 0 | CB36: =IF(CA36=0,"",IF(CA36>=1,CA36)) | CC36: =IF(CA36>11,"high",IF(CA36>6,"mid",IF(CA36>4,"ALARP",IF(CA36=0,"",IF(CA36>=1,"low"))))) | CF36: =IF(U36=0,"",IF(ISNA(U36),"",IF(E36<>"",U36,""))) | CG36: =IF(AO36=0,"",IF(ISNA(AO36),"",IF(E36<>"",AO36,""))) | CH36: =IF(AS36=0,"",IF(ISNA(AS36),"",IF(E36<>"",AS36,"")))
E37: =IF(ISNA('D4.5Why''s-D5-D6'!BY25),"",'D4.5Why''s-D5-D6'!BY25) | AL37: =BX37 | AO37: =IF(BW37>11,"high",IF(BW37>6,"mid",IF(BW37>4,"ALARP",IF(BW37=0,"",IF(BW37>=1,"low"))))) | BL37: =CB37 | BO37: =CC37 | BW37: =AE37*AI37 -> 0 | BX37: =IF(BW37=0,"",IF(BW37>=1,BW37)) | BY37: =IF(BW37>11,"high",IF(BW37>6,"mid",IF(BW37>4,"ALARP",IF(BW37=0,"",IF(BW37>=1,"low"))))) | CA37: =BE37*BI37 -> 0 | CB37: =IF(CA37=0,"",IF(CA37>=1,CA37)) | CC37: =IF(CA37>11,"high",IF(CA37>6,"mid",IF(CA37>4,"ALARP",IF(CA37=0,"",IF(CA37>=1,"low"))))) | CF37: =IF(U37=0,"",IF(ISNA(U37),"",IF(E37<>"",U37,""))) | CG37: =IF(AO37=0,"",IF(ISNA(AO37),"",IF(E37<>"",AO37,""))) | CH37: =IF(AS37=0,"",IF(ISNA(AS37),"",IF(E37<>"",AS37,"")))
E38: =IF(ISNA('D4.5Why''s-D5-D6'!BY26),"",'D4.5Why''s-D5-D6'!BY26) | AL38: =BX38 | AO38: =IF(BW38>11,"high",IF(BW38>6,"mid",IF(BW38>4,"ALARP",IF(BW38=0,"",IF(BW38>=1,"low"))))) | BL38: =CB38 | BO38: =CC38 | BW38: =AE38*AI38 -> 0 | BX38: =IF(BW38=0,"",IF(BW38>=1,BW38)) | BY38: =IF(BW38>11,"high",IF(BW38>6,"mid",IF(BW38>4,"ALARP",IF(BW38=0,"",IF(BW38>=1,"low"))))) | CA38: =BE38*BI38 -> 0 | CB38: =IF(CA38=0,"",IF(CA38>=1,CA38)) | CC38: =IF(CA38>11,"high",IF(CA38>6,"mid",IF(CA38>4,"ALARP",IF(CA38=0,"",IF(CA38>=1,"low"))))) | CF38: =IF(U38=0,"",IF(ISNA(U38),"",IF(E38<>"",U38,""))) | CG38: =IF(AO38=0,"",IF(ISNA(AO38),"",IF(E38<>"",AO38,""))) | CH38: =IF(AS38=0,"",IF(ISNA(AS38),"",IF(E38<>"",AS38,"")))
E39: =IF(ISNA('D4.5Why''s-D5-D6'!BY27),"",'D4.5Why''s-D5-D6'!BY27) | AL39: =BX39 | AO39: =IF(BW39>11,"high",IF(BW39>6,"mid",IF(BW39>4,"ALARP",IF(BW39=0,"",IF(BW39>=1,"low"))))) | BL39: =CB39 | BO39: =CC39 | BW39: =AE39*AI39 -> 0 | BX39: =IF(BW39=0,"",IF(BW39>=1,BW39)) | BY39: =IF(BW39>11,"high",IF(BW39>6,"mid",IF(BW39>4,"ALARP",IF(BW39=0,"",IF(BW39>=1,"low"))))) | CA39: =BE39*BI39 -> 0 | CB39: =IF(CA39=0,"",IF(CA39>=1,CA39)) | CC39: =IF(CA39>11,"high",IF(CA39>6,"mid",IF(CA39>4,"ALARP",IF(CA39=0,"",IF(CA39>=1,"low"))))) | CF39: =IF(U39=0,"",IF(ISNA(U39),"",IF(E39<>"",U39,""))) | CG39: =IF(AO39=0,"",IF(ISNA(AO39),"",IF(E39<>"",AO39,""))) | CH39: =IF(AS39=0,"",IF(ISNA(AS39),"",IF(E39<>"",AS39,"")))
E40: =IF(ISNA('D4.5Why''s-D5-D6'!BY28),"",'D4.5Why''s-D5-D6'!BY28) | AL40: =BX40 | AO40: =IF(BW40>11,"high",IF(BW40>6,"mid",IF(BW40>4,"ALARP",IF(BW40=0,"",IF(BW40>=1,"low"))))) | BL40: =CB40 | BO40: =CC40 | BW40: =AE40*AI40 -> 0 | BX40: =IF(BW40=0,"",IF(BW40>=1,BW40)) | BY40: =IF(BW40>11,"high",IF(BW40>6,"mid",IF(BW40>4,"ALARP",IF(BW40=0,"",IF(BW40>=1,"low"))))) | CA40: =BE40*BI40 -> 0 | CB40: =IF(CA40=0,"",IF(CA40>=1,CA40)) | CC40: =IF(CA40>11,"high",IF(CA40>6,"mid",IF(CA40>4,"ALARP",IF(CA40=0,"",IF(CA40>=1,"low"))))) | CF40: =IF(U40=0,"",IF(ISNA(U40),"",IF(E40<>"",U40,""))) | CG40: =IF(AO40=0,"",IF(ISNA(AO40),"",IF(E40<>"",AO40,""))) | CH40: =IF(AS40=0,"",IF(ISNA(AS40),"",IF(E40<>"",AS40,"")))
D42: =INDIRECT('D1-D2-D3'!$J$4&"!C138") -> Systemic consideration | E42: =IF(ISNA('D4.5Why''s-D5-D6'!BY44),"",'D4.5Why''s-D5-D6'!BY44) | AL42: =BX42 | AO42: =IF(BW42>11,"high",IF(BW42>6,"mid",IF(BW42>4,"ALARP",IF(BW42=0,"",IF(BW42>=1,"low"))))) | BL42: =CB42 | BO42: =CC42 | BW42: =AE42*AI42 -> 0 | BX42: =IF(BW42=0,"",IF(BW42>=1,BW42)) | BY42: =IF(BW42>11,"high",IF(BW42>6,"mid",IF(BW42>4,"ALARP",IF(BW42=0,"",IF(BW42>=1,"low"))))) | CA42: =BE42*BI42 -> 0 | CB42: =IF(CA42=0,"",IF(CA42>=1,CA42)) | CC42: =IF(CA42>11,"high",IF(CA42>6,"mid",IF(CA42>4,"ALARP",IF(CA42=0,"",IF(CA42>=1,"low"))))) | CF42: =IF(U42=0,"",IF(ISNA(U42),"",IF(E42<>"",U42,""))) | CG42: =IF(AO42=0,"",IF(ISNA(AO42),"",IF(E42<>"",AO42,""))) | CH42: =IF(AS42=0,"",IF(ISNA(AS42),"",IF(E42<>"",AS42,"")))
E43: =IF(ISNA('D4.5Why''s-D5-D6'!BY45),"",'D4.5Why''s-D5-D6'!BY45) | AL43: =BX43 | AO43: =IF(BW43>11,"high",IF(BW43>6,"mid",IF(BW43>4,"ALARP",IF(BW43=0,"",IF(BW43>=1,"low"))))) | BL43: =CB43 | BO43: =CC43 | BW43: =AE43*AI43 -> 0 | BX43: =IF(BW43=0,"",IF(BW43>=1,BW43)) | BY43: =IF(BW43>11,"high",IF(BW43>6,"mid",IF(BW43>4,"ALARP",IF(BW43=0,"",IF(BW43>=1,"low"))))) | CA43: =BE43*BI43 -> 0 | CB43: =IF(CA43=0,"",IF(CA43>=1,CA43)) | CC43: =IF(CA43>11,"high",IF(CA43>6,"mid",IF(CA43>4,"ALARP",IF(CA43=0,"",IF(CA43>=1,"low"))))) | CF43: =IF(U43=0,"",IF(ISNA(U43),"",IF(E43<>"",U43,""))) | CG43: =IF(AO43=0,"",IF(ISNA(AO43),"",IF(E43<>"",AO43,""))) | CH43: =IF(AS43=0,"",IF(ISNA(AS43),"",IF(E43<>"",AS43,"")))
E44: =IF(ISNA('D4.5Why''s-D5-D6'!BY46),"",'D4.5Why''s-D5-D6'!BY46) | AL44: =BX44 | AO44: =IF(BW44>11,"high",IF(BW44>6,"mid",IF(BW44>4,"ALARP",IF(BW44=0,"",IF(BW44>=1,"low"))))) | BL44: =CB44 | BO44: =CC44 | BW44: =AE44*AI44 -> 0 | BX44: =IF(BW44=0,"",IF(BW44>=1,BW44)) | BY44: =IF(BW44>11,"high",IF(BW44>6,"mid",IF(BW44>4,"ALARP",IF(BW44=0,"",IF(BW44>=1,"low"))))) | CA44: =BE44*BI44 -> 0 | CB44: =IF(CA44=0,"",IF(CA44>=1,CA44)) | CC44: =IF(CA44>11,"high",IF(CA44>6,"mid",IF(CA44>4,"ALARP",IF(CA44=0,"",IF(CA44>=1,"low"))))) | CF44: =IF(U44=0,"",IF(ISNA(U44),"",IF(E44<>"",U44,""))) | CG44: =IF(AO44=0,"",IF(ISNA(AO44),"",IF(E44<>"",AO44,""))) | CH44: =IF(AS44=0,"",IF(ISNA(AS44),"",IF(E44<>"",AS44,"")))
E45: =IF(ISNA('D4.5Why''s-D5-D6'!BY47),"",'D4.5Why''s-D5-D6'!BY47) | AL45: =BX45 | AO45: =IF(BW45>11,"high",IF(BW45>6,"mid",IF(BW45>4,"ALARP",IF(BW45=0,"",IF(BW45>=1,"low"))))) | BL45: =CB45 | BO45: =CC45 | BW45: =AE45*AI45 -> 0 | BX45: =IF(BW45=0,"",IF(BW45>=1,BW45)) | BY45: =IF(BW45>11,"high",IF(BW45>6,"mid",IF(BW45>4,"ALARP",IF(BW45=0,"",IF(BW45>=1,"low"))))) | CA45: =BE45*BI45 -> 0 | CB45: =IF(CA45=0,"",IF(CA45>=1,CA45)) | CC45: =IF(CA45>11,"high",IF(CA45>6,"mid",IF(CA45>4,"ALARP",IF(CA45=0,"",IF(CA45>=1,"low"))))) | CF45: =IF(U45=0,"",IF(ISNA(U45),"",IF(E45<>"",U45,""))) | CG45: =IF(AO45=0,"",IF(ISNA(AO45),"",IF(E45<>"",AO45,""))) | CH45: =IF(AS45=0,"",IF(ISNA(AS45),"",IF(E45<>"",AS45,"")))
E46: =IF(ISNA('D4.5Why''s-D5-D6'!BY48),"",'D4.5Why''s-D5-D6'!BY48) | AL46: =BX46 | AO46: =IF(BW46>11,"high",IF(BW46>6,"mid",IF(BW46>4,"ALARP",IF(BW46=0,"",IF(BW46>=1,"low"))))) | BL46: =CB46 | BO46: =CC46 | BW46: =AE46*AI46 -> 0 | BX46: =IF(BW46=0,"",IF(BW46>=1,BW46)) | BY46: =IF(BW46>11,"high",IF(BW46>6,"mid",IF(BW46>4,"ALARP",IF(BW46=0,"",IF(BW46>=1,"low"))))) | CA46: =BE46*BI46 -> 0 | CB46: =IF(CA46=0,"",IF(CA46>=1,CA46)) | CC46: =IF(CA46>11,"high",IF(CA46>6,"mid",IF(CA46>4,"ALARP",IF(CA46=0,"",IF(CA46>=1,"low"))))) | CF46: =IF(U46=0,"",IF(ISNA(U46),"",IF(E46<>"",U46,""))) | CG46: =IF(AO46=0,"",IF(ISNA(AO46),"",IF(E46<>"",AO46,""))) | CH46: =IF(AS46=0,"",IF(ISNA(AS46),"",IF(E46<>"",AS46,"")))
E47: =IF(ISNA('D4.5Why''s-D5-D6'!BY49),"",'D4.5Why''s-D5-D6'!BY49) | AL47: =BX47 | AO47: =IF(BW47>11,"high",IF(BW47>6,"mid",IF(BW47>4,"ALARP",IF(BW47=0,"",IF(BW47>=1,"low"))))) | BL47: =CB47 | BO47: =CC47 | BW47: =AE47*AI47 -> 0 | BX47: =IF(BW47=0,"",IF(BW47>=1,BW47)) | BY47: =IF(BW47>11,"high",IF(BW47>6,"mid",IF(BW47>4,"ALARP",IF(BW47=0,"",IF(BW47>=1,"low"))))) | CA47: =BE47*BI47 -> 0 | CB47: =IF(CA47=0,"",IF(CA47>=1,CA47)) | CC47: =IF(CA47>11,"high",IF(CA47>6,"mid",IF(CA47>4,"ALARP",IF(CA47=0,"",IF(CA47>=1,"low"))))) | CF47: =IF(U47=0,"",IF(ISNA(U47),"",IF(E47<>"",U47,""))) | CG47: =IF(AO47=0,"",IF(ISNA(AO47),"",IF(E47<>"",AO47,""))) | CH47: =IF(AS47=0,"",IF(ISNA(AS47),"",IF(E47<>"",AS47,"")))
E48: =IF(ISNA('D4.5Why''s-D5-D6'!BY50),"",'D4.5Why''s-D5-D6'!BY50) | AL48: =BX48 | AO48: =IF(BW48>11,"high",IF(BW48>6,"mid",IF(BW48>4,"ALARP",IF(BW48=0,"",IF(BW48>=1,"low"))))) | BL48: =CB48 | BO48: =CC48 | BW48: =AE48*AI48 -> 0 | BX48: =IF(BW48=0,"",IF(BW48>=1,BW48)) | BY48: =IF(BW48>11,"high",IF(BW48>6,"mid",IF(BW48>4,"ALARP",IF(BW48=0,"",IF(BW48>=1,"low"))))) | CA48: =BE48*BI48 -> 0 | CB48: =IF(CA48=0,"",IF(CA48>=1,CA48)) | CC48: =IF(CA48>11,"high",IF(CA48>6,"mid",IF(CA48>4,"ALARP",IF(CA48=0,"",IF(CA48>=1,"low"))))) | CF48: =IF(U48=0,"",IF(ISNA(U48),"",IF(E48<>"",U48,""))) | CG48: =IF(AO48=0,"",IF(ISNA(AO48),"",IF(E48<>"",AO48,""))) | CH48: =IF(AS48=0,"",IF(ISNA(AS48),"",IF(E48<>"",AS48,"")))
E49: =IF(ISNA('D4.5Why''s-D5-D6'!BY51),"",'D4.5Why''s-D5-D6'!BY51) | AL49: =BX49 | AO49: =IF(BW49>11,"high",IF(BW49>6,"mid",IF(BW49>4,"ALARP",IF(BW49=0,"",IF(BW49>=1,"low"))))) | BL49: =CB49 | BO49: =CC49 | BW49: =AE49*AI49 -> 0 | BX49: =IF(BW49=0,"",IF(BW49>=1,BW49)) | BY49: =IF(BW49>11,"high",IF(BW49>6,"mid",IF(BW49>4,"ALARP",IF(BW49=0,"",IF(BW49>=1,"low"))))) | CA49: =BE49*BI49 -> 0 | CB49: =IF(CA49=0,"",IF(CA49>=1,CA49)) | CC49: =IF(CA49>11,"high",IF(CA49>6,"mid",IF(CA49>4,"ALARP",IF(CA49=0,"",IF(CA49>=1,"low"))))) | CF49: =IF(U49=0,"",IF(ISNA(U49),"",IF(E49<>"",U49,""))) | CG49: =IF(AO49=0,"",IF(ISNA(AO49),"",IF(E49<>"",AO49,""))) | CH49: =IF(AS49=0,"",IF(ISNA(AS49),"",IF(E49<>"",AS49,"")))
E50: =IF(ISNA('D4.5Why''s-D5-D6'!BY52),"",'D4.5Why''s-D5-D6'!BY52) | AL50: =BX50 | AO50: =IF(BW50>11,"high",IF(BW50>6,"mid",IF(BW50>4,"ALARP",IF(BW50=0,"",IF(BW50>=1,"low"))))) | BL50: =CB50 | BO50: =CC50 | BW50: =AE50*AI50 -> 0 | BX50: =IF(BW50=0,"",IF(BW50>=1,BW50)) | BY50: =IF(BW50>11,"high",IF(BW50>6,"mid",IF(BW50>4,"ALARP",IF(BW50=0,"",IF(BW50>=1,"low"))))) | CA50: =BE50*BI50 -> 0 | CB50: =IF(CA50=0,"",IF(CA50>=1,CA50)) | CC50: =IF(CA50>11,"high",IF(CA50>6,"mid",IF(CA50>4,"ALARP",IF(CA50=0,"",IF(CA50>=1,"low"))))) | CF50: =IF(U50=0,"",IF(ISNA(U50),"",IF(E50<>"",U50,""))) | CG50: =IF(AO50=0,"",IF(ISNA(AO50),"",IF(E50<>"",AO50,""))) | CH50: =IF(AS50=0,"",IF(ISNA(AS50),"",IF(E50<>"",AS50,"")))
E51: =IF(ISNA('D4.5Why''s-D5-D6'!BY53),"",'D4.5Why''s-D5-D6'!BY53) | AL51: =BX51 | AO51: =IF(BW51>11,"high",IF(BW51>6,"mid",IF(BW51>4,"ALARP",IF(BW51=0,"",IF(BW51>=1,"low"))))) | BL51: =CB51 | BO51: =CC51 | BW51: =AE51*AI51 -> 0 | BX51: =IF(BW51=0,"",IF(BW51>=1,BW51)) | BY51: =IF(BW51>11,"high",IF(BW51>6,"mid",IF(BW51>4,"ALARP",IF(BW51=0,"",IF(BW51>=1,"low"))))) | CA51: =BE51*BI51 -> 0 | CB51: =IF(CA51=0,"",IF(CA51>=1,CA51)) | CC51: =IF(CA51>11,"high",IF(CA51>6,"mid",IF(CA51>4,"ALARP",IF(CA51=0,"",IF(CA51>=1,"low"))))) | CF51: =IF(U51=0,"",IF(ISNA(U51),"",IF(E51<>"",U51,""))) | CG51: =IF(AO51=0,"",IF(ISNA(AO51),"",IF(E51<>"",AO51,""))) | CH51: =IF(AS51=0,"",IF(ISNA(AS51),"",IF(E51<>"",AS51,"")))

Sheet D4. Data-Facts-Numbers
K2: =INDIRECT('D1-D2-D3'!$J$4&"!C2")&" "&INDIRECT('D1-D2-D3'!$J$4&"!C97") -> PROBLEM SOLVING SHEET Data/Facts/Numbers | AD2: =INDIRECT('D1-D2-D3'!$J$4&"!C3") -> PSS No. | AJ2: ='D1-D2-D3'!$AI$4 -> 0 | AP2: 4.15.03.00 | AX2: =INDIRECT('D1-D2-D3'!$J$4&"!C96") -> Page 2: D4
D6: =INDIRECT('D1-D2-D3'!$J$4&"!C98") -> Rework
D7: =INDIRECT('D1-D2-D3'!$J$4&"!C102") -> Detailed information about rework
D14: =INDIRECT('D1-D2-D3'!$J$4&"!C103") -> Information about fault in QIS
D28: =INDIRECT('D1-D2-D3'!$J$4&"!C104") -> Other information
B62: =INDIRECT('D1-D2-D3'!$J$4&"!C105") -> For a comprehensible root cause analysis, draw the process flow and mark the critical process steps:

Sheet D4. Ishikawa-chart
B2: =INDIRECT('D1-D2-D3'!$J$4&"!C107") -> Guiding questions for an efficient root cause analysis
B3: =INDIRECT('D1-D2-D3'!$J$4&"!C108") -> Man | L3: =INDIRECT('D1-D2-D3'!$J$4&"!C115") -> Machine | V3: =INDIRECT('D1-D2-D3'!$J$4&"!C122") -> Material | AE3: =INDIRECT('D1-D2-D3'!$J$4&"!C128") -> Method
B4: =INDIRECT('D1-D2-D3'!$J$4&"!C109") -> Is there any risk during manipulations ? | L4: =INDIRECT('D1-D2-D3'!$J$4&"!C116") -> Are tools/machines functioning properly ? | V4: =INDIRECT('D1-D2-D3'!$J$4&"!C123") -> Are parts within defined standards ? Are standards suitable ? | AE4: =INDIRECT('D1-D2-D3'!$J$4&"!C129") -> Are work instructions posted at workstations ?
B5: =INDIRECT('D1-D2-D3'!$J$4&"!C110") -> Are workers abilited to the job ? (check concerned prod.period) | L5: =INDIRECT('D1-D2-D3'!$J$4&"!C117") -> Has preventive maintenance been performed ? | V5: =INDIRECT('D1-D2-D3'!$J$4&"!C124") -> Are used components/materials within specifications ? | AE5: =INDIRECT('D1-D2-D3'!$J$4&"!C130") -> Are work instructions updated ?
B6: =INDIRECT('D1-D2-D3'!$J$4&"!C111") -> Did workers received necessary training ? | L6: =INDIRECT('D1-D2-D3'!$J$4&"!C118") -> Did any specific event occure ? (Power shutdown,…) | V6: =INDIRECT('D1-D2-D3'!$J$4&"!C125") -> Were there any changes/modifications on components/materials ? | AE6: =INDIRECT('D1-D2-D3'!$J$4&"!C131") -> Have correct tools/fixtures been used ?
B7: =INDIRECT('D1-D2-D3'!$J$4&"!C112") -> Is training adapted to the needs ? | L7: =INDIRECT('D1-D2-D3'!$J$4&"!C119") -> Do error proofing systems work properly ? (Poka yoke, Control station,…) | V7: =INDIRECT('D1-D2-D3'!$J$4&"!C126") -> Are all components/materials approved ? | AE7: =INDIRECT('D1-D2-D3'!$J$4&"!C132") -> Is the job done the same way in all shifts ?
B8: =INDIRECT('D1-D2-D3'!$J$4&"!C113") -> Do workers perfectly understand applicable work instructions ? | L8: =INDIRECT('D1-D2-D3'!$J$4&"!C120") -> Have machine/process parameters been properly set up ? | V8: =INDIRECT('D1-D2-D3'!$J$4&"!C127") -> Are correct components/materials used ? | AE8: =INDIRECT('D1-D2-D3'!$J$4&"!C133") -> Is preventive maintenance defined ? Is it sufficient ?
B9: =INDIRECT('D1-D2-D3'!$J$4&"!C114") -> Were all work instructions properly followed and applied ? | L9: =INDIRECT('D1-D2-D3'!$J$4&"!C121") -> Are machine/process parameters properly defined ?
I12: =INDIRECT('D1-D2-D3'!$J$4&"!C2")&" "&INDIRECT('D1-D2-D3'!$J$4&"!C136") -> PROBLEM SOLVING SHEET Ishikawa-Chart | W12: =INDIRECT('D1-D2-D3'!$J$4&"!C3") -> PSS No. | Y12: ='D1-D2-D3'!$AI$4 -> 0 | AB12: 4.15.03.00 | AF12: =INDIRECT('D1-D2-D3'!$J$4&"!C106") -> Page 3: D4
C14: =INDIRECT('D1-D2-D3'!$J$4&"!C136") -> Ishikawa-Chart
F16: =INDIRECT('D1-D2-D3'!$J$4&"!C139") -> Occurrence | W16: =INDIRECT('D1-D2-D3'!$J$4&"!C140") -> Non-detection | AS16: YES - Occurence | AY16: YES - Non det | BG16: CAUSE FOR D4. 5WHYs - together
F18: =INDIRECT('D1-D2-D3'!$J$4&"!C108") -> Man | L18: =INDIRECT('D1-D2-D3'!$J$4&"!C115") -> Machine | R18: =INDIRECT('D1-D2-D3'!$J$4&"!C122") -> Material | X18: =INDIRECT('D1-D2-D3'!$J$4&"!C108") -> Man | AD18: =INDIRECT('D1-D2-D3'!$J$4&"!C115") -> Machine | AJ18: =INDIRECT('D1-D2-D3'!$J$4&"!C122") -> Material | AS18: 0 | AZ18: 0 | BG18: 0
AR19: 1 | AS19: =IF($AT19<>"",AS18+1,"") | AT19: =IF($J19=DropDown!$N$11,F19,"") | AV19: 1 | AW19: =VLOOKUP($AV19,$AS$19:$AT$48,2,FALSE) -> #N/A | AX19: =IF(ISNA(AW19),"",AW19) | AY19: 1 | AZ19: =IF($BA19<>"",AZ18+1,"") | BA19: =IF($AB19=DropDown!$N$11,X19,"") | BC19: 1 | BD19: =VLOOKUP($BC19,$AZ$19:$BA$48,2,FALSE) -> #N/A | BE19: =IF(ISNA(BD19),"",BD19) | BG19: =IF($BH19<>"",BG18+1,"") | BH19: =IF(AX19="","",AX19) | BI19: 1 | BJ19: =VLOOKUP($BI19,$BG$19:$BH$48,2,FALSE) -> #N/A | BK19: =IF(ISNA(BJ19),"",BJ19)
AS20: =IF($AT20<>"",MAX(AS$18:AS19)+1,"") | AT20: =IF($J20=DropDown!$N$11,F20,"") | AV20: 2 | AW20: =VLOOKUP($AV20,$AS$19:$AT$48,2,FALSE) -> #N/A | AX20: =IF(ISNA(AW20),"",AW20) | AZ20: =IF($BA20<>"",MAX(AZ$18:AZ19)+1,"") | BA20: =IF($AB20=DropDown!$N$11,X20,"") | BC20: 2 | BD20: =VLOOKUP($BC20,$AZ$19:$BA$48,2,FALSE) -> #N/A | BE20: =IF(ISNA(BD20),"",BD20) | BG20: =IF($BH20<>"",MAX(BG$18:BG19)+1,"") | BH20: =IF(AX20="","",AX20) | BI20: 2 | BJ20: =VLOOKUP($BI20,$BG$19:$BH$48,2,FALSE) -> #N/A | BK20: =IF(ISNA(BJ20),"",BJ20)
AS21: =IF($AT21<>"",MAX(AS$18:AS20)+1,"") | AT21: =IF($J21=DropDown!$N$11,F21,"") | AV21: 3 | AW21: =VLOOKUP($AV21,$AS$19:$AT$48,2,FALSE) -> #N/A | AX21: =IF(ISNA(AW21),"",AW21) | AZ21: =IF($BA21<>"",MAX(AZ$18:AZ20)+1,"") | BA21: =IF($AB21=DropDown!$N$11,X21,"") | BC21: 3 | BD21: =VLOOKUP($BC21,$AZ$19:$BA$48,2,FALSE) -> #N/A | BE21: =IF(ISNA(BD21),"",BD21) | BG21: =IF($BH21<>"",MAX(BG$18:BG20)+1,"") | BH21: =IF(AX21="","",AX21) | BI21: 3 | BJ21: =VLOOKUP($BI21,$BG$19:$BH$48,2,FALSE) -> #N/A | BK21: =IF(ISNA(BJ21),"",BJ21)
AS22: =IF($AT22<>"",MAX(AS$18:AS21)+1,"") | AT22: =IF($J22=DropDown!$N$11,F22,"") | AV22: 4 | AW22: =VLOOKUP($AV22,$AS$19:$AT$48,2,FALSE) -> #N/A | AX22: =IF(ISNA(AW22),"",AW22) | AZ22: =IF($BA22<>"",MAX(AZ$18:AZ21)+1,"") | BA22: =IF($AB22=DropDown!$N$11,X22,"") | BC22: 4 | BD22: =VLOOKUP($BC22,$AZ$19:$BA$48,2,FALSE) -> #N/A | BE22: =IF(ISNA(BD22),"",BD22) | BG22: =IF($BH22<>"",MAX(BG$18:BG21)+1,"") | BH22: =IF(AX22="","",AX22) | BI22: 4 | BJ22: =VLOOKUP($BI22,$BG$19:$BH$48,2,FALSE) -> #N/A | BK22: =IF(ISNA(BJ22),"",BJ22)
AS23: =IF($AT23<>"",MAX(AS$18:AS22)+1,"") | AT23: =IF($J23=DropDown!$N$11,F23,"") | AV23: 5 | AW23: =VLOOKUP($AV23,$AS$19:$AT$48,2,FALSE) -> #N/A | AX23: =IF(ISNA(AW23),"",AW23) | AZ23: =IF($BA23<>"",MAX(AZ$18:AZ22)+1,"") | BA23: =IF($AB23=DropDown!$N$11,X23,"") | BC23: 5 | BD23: =VLOOKUP($BC23,$AZ$19:$BA$48,2,FALSE) -> #N/A | BE23: =IF(ISNA(BD23),"",BD23) | BG23: =IF($BH23<>"",MAX(BG$18:BG22)+1,"") | BH23: =IF(AX23="","",AX23) | BI23: 5 | BJ23: =VLOOKUP($BI23,$BG$19:$BH$48,2,FALSE) -> #N/A | BK23: =IF(ISNA(BJ23),"",BJ23)
AR24: 2 | AS24: =IF($AT24<>"",MAX(AS$18:AS23)+1,"") | AT24: =IF($P19=DropDown!$N$11,L19,"") | AV24: 6 | AW24: =VLOOKUP($AV24,$AS$19:$AT$48,2,FALSE) -> #N/A | AX24: =IF(ISNA(AW24),"",AW24) | AY24: 2 | AZ24: =IF($BA24<>"",MAX(AZ$18:AZ23)+1,"") | BA24: =IF($AH19=DropDown!$N$11,AD19,"") | BC24: 6 | BD24: =VLOOKUP($BC24,$AZ$19:$BA$48,2,FALSE) -> #N/A | BE24: =IF(ISNA(BD24),"",BD24) | BG24: =IF($BH24<>"",MAX(BG$18:BG23)+1,"") | BH24: =IF(AX24="","",AX24) | BI24: 6 | BJ24: =VLOOKUP($BI24,$BG$19:$BH$48,2,FALSE) -> #N/A | BK24: =IF(ISNA(BJ24),"",BJ24)
AS25: =IF($AT25<>"",MAX(AS$18:AS24)+1,"") | AT25: =IF($P20=DropDown!$N$11,L20,"") | AV25: 7 | AW25: =VLOOKUP($AV25,$AS$19:$AT$48,2,FALSE) -> #N/A | AX25: =IF(ISNA(AW25),"",AW25) | AZ25: =IF($BA25<>"",MAX(AZ$18:AZ24)+1,"") | BA25: =IF($AH20=DropDown!$N$11,AD20,"") | BC25: 7 | BD25: =VLOOKUP($BC25,$AZ$19:$BA$48,2,FALSE) -> #N/A | BE25: =IF(ISNA(BD25),"",BD25) | BG25: =IF($BH25<>"",MAX(BG$18:BG24)+1,"") | BH25: =IF(AX25="","",AX25) | BI25: 7 | BJ25: =VLOOKUP($BI25,$BG$19:$BH$48,2,FALSE) -> #N/A | BK25: =IF(ISNA(BJ25),"",BJ25)
AS26: =IF($AT26<>"",MAX(AS$18:AS25)+1,"") | AT26: =IF($P21=DropDown!$N$11,L21,"") | AV26: 8 | AW26: =VLOOKUP($AV26,$AS$19:$AT$48,2,FALSE) -> #N/A | AX26: =IF(ISNA(AW26),"",AW26) | AZ26: =IF($BA26<>"",MAX(AZ$18:AZ25)+1,"") | BA26: =IF($AH21=DropDown!$N$11,AD21,"") | BC26: 8 | BD26: =VLOOKUP($BC26,$AZ$19:$BA$48,2,FALSE) -> #N/A | BE26: =IF(ISNA(BD26),"",BD26) | BG26: =IF($BH26<>"",MAX(BG$18:BG25)+1,"") | BH26: =IF(AX26="","",AX26) | BI26: 8 | BJ26: =VLOOKUP($BI26,$BG$19:$BH$48,2,FALSE) -> #N/A | BK26: =IF(ISNA(BJ26),"",BJ26)
AS27: =IF($AT27<>"",MAX(AS$18:AS26)+1,"") | AT27: =IF($P22=DropDown!$N$11,L22,"") | AV27: 9 | AW27: =VLOOKUP($AV27,$AS$19:$AT$48,2,FALSE) -> #N/A | AX27: =IF(ISNA(AW27),"",AW27) | AZ27: =IF($BA27<>"",MAX(AZ$18:AZ26)+1,"") | BA27: =IF($AH22=DropDown!$N$11,AD22,"") | BC27: 9 | BD27: =VLOOKUP($BC27,$AZ$19:$BA$48,2,FALSE) -> #N/A | BE27: =IF(ISNA(BD27),"",BD27) | BG27: =IF($BH27<>"",MAX(BG$18:BG26)+1,"") | BH27: =IF(AX27="","",AX27) | BI27: 9 | BJ27: =VLOOKUP($BI27,$BG$19:$BH$48,2,FALSE) -> #N/A | BK27: =IF(ISNA(BJ27),"",BJ27)
AS28: =IF($AT28<>"",MAX(AS$18:AS27)+1,"") | AT28: =IF($P23=DropDown!$N$11,L23,"") | AV28: 10 | AW28: =VLOOKUP($AV28,$AS$19:$AT$48,2,FALSE) -> #N/A | AX28: =IF(ISNA(AW28),"",AW28) | AZ28: =IF($BA28<>"",MAX(AZ$18:AZ27)+1,"") | BA28: =IF($AH23=DropDown!$N$11,AD23,"") | BC28: 10 | BD28: =VLOOKUP($BC28,$AZ$19:$BA$48,2,FALSE) -> #N/A | BE28: =IF(ISNA(BD28),"",BD28) | BG28: =IF($BH28<>"",MAX(BG$18:BG27)+1,"") | BH28: =IF(AX28="","",AX28) | BI28: 10 | BJ28: =VLOOKUP($BI28,$BG$19:$BH$48,2,FALSE) -> #N/A | BK28: =IF(ISNA(BJ28),"",BJ28)
AR29: 3 | AS29: =IF($AT29<>"",MAX(AS$18:AS28)+1,"") | AT29: =IF($U19=DropDown!$N$11,R19,"") | AV29: 11 | AW29: =VLOOKUP($AV29,$AS$19:$AT$48,2,FALSE) -> #N/A | AX29: =IF(ISNA(AW29),"",AW29) | AY29: 3 | AZ29: =IF($BA29<>"",MAX(AZ$18:AZ28)+1,"") | BA29: =IF($AM19=DropDown!$N$11,AJ19,"") | BC29: 11 | BD29: =VLOOKUP($BC29,$AZ$19:$BA$48,2,FALSE) -> #N/A | BE29: =IF(ISNA(BD29),"",BD29) | BG29: =IF($BH29<>"",MAX(BG$18:BG28)+1,"") | BH29: =IF(AX29="","",AX29) | BI29: 11 | BJ29: =VLOOKUP($BI29,$BG$19:$BH$48,2,FALSE) -> #N/A | BK29: =IF(ISNA(BJ29),"",BJ29)
AS30: =IF($AT30<>"",MAX(AS$18:AS29)+1,"") | AT30: =IF($U20=DropDown!$N$11,R20,"") | AV30: 12 | AW30: =VLOOKUP($AV30,$AS$19:$AT$48,2,FALSE) -> #N/A | AX30: =IF(ISNA(AW30),"",AW30) | AZ30: =IF($BA30<>"",MAX(AZ$18:AZ29)+1,"") | BA30: =IF($AM20=DropDown!$N$11,AJ20,"") | BC30: 12 | BD30: =VLOOKUP($BC30,$AZ$19:$BA$48,2,FALSE) -> #N/A | BE30: =IF(ISNA(BD30),"",BD30) | BG30: =IF($BH30<>"",MAX(BG$18:BG29)+1,"") | BH30: =IF(AX30="","",AX30) | BI30: 12 | BJ30: =VLOOKUP($BI30,$BG$19:$BH$48,2,FALSE) -> #N/A | BK30: =IF(ISNA(BJ30),"",BJ30)
AS31: =IF($AT31<>"",MAX(AS$18:AS30)+1,"") | AT31: =IF($U21=DropDown!$N$11,R21,"") | AV31: 13 | AW31: =VLOOKUP($AV31,$AS$19:$AT$48,2,FALSE) -> #N/A | AX31: =IF(ISNA(AW31),"",AW31) | AZ31: =IF($BA31<>"",MAX(AZ$18:AZ30)+1,"") | BA31: =IF($AM21=DropDown!$N$11,AJ21,"") | BC31: 13 | BD31: =VLOOKUP($BC31,$AZ$19:$BA$48,2,FALSE) -> #N/A | BE31: =IF(ISNA(BD31),"",BD31) | BG31: =IF($BH31<>"",MAX(BG$18:BG30)+1,"") | BH31: =IF(AX31="","",AX31) | BI31: 13 | BJ31: =VLOOKUP($BI31,$BG$19:$BH$48,2,FALSE) -> #N/A | BK31: =IF(ISNA(BJ31),"",BJ31)
F32: =INDIRECT('D1-D2-D3'!$J$4&"!C128") -> Method | L32: =INDIRECT('D1-D2-D3'!$J$4&"!C134") -> Environment | R32: Others | X32: =INDIRECT('D1-D2-D3'!$J$4&"!C128") -> Method | AB32: =INDIRECT('D1-D2-D3'!$J$4&"!C128") -> Method | AD32: =INDIRECT('D1-D2-D3'!$J$4&"!C134") -> Environment | AH32: =INDIRECT('D1-D2-D3'!$J$4&"!C134") -> Environment | AJ32: Others | AM32: Others | AS32: =IF($AT32<>"",MAX(AS$18:AS31)+1,"") | AT32: =IF($U22=DropDown!$N$11,R22,"") | AV32: 14 | AW32: =VLOOKUP($AV32,$AS$19:$AT$48,2,FALSE) -> #N/A | AX32: =IF(ISNA(AW32),"",AW32) | AZ32: =IF($BA32<>"",MAX(AZ$18:AZ31)+1,"") | BA32: =IF($AM22=DropDown!$N$11,AJ22,"") | BC32: 14 | BD32: =VLOOKUP($BC32,$AZ$19:$BA$48,2,FALSE) -> #N/A | BE32: =IF(ISNA(BD32),"",BD32) | BG32: =IF($BH32<>"",MAX(BG$18:BG31)+1,"") | BH32: =IF(AX32="","",AX32) | BI32: 14 | BJ32: =VLOOKUP($BI32,$BG$19:$BH$48,2,FALSE) -> #N/A | BK32: =IF(ISNA(BJ32),"",BJ32)
AS33: =IF($AT33<>"",MAX(AS$18:AS32)+1,"") | AT33: =IF($U23=DropDown!$N$11,R23,"") | AV33: 15 | AW33: =VLOOKUP($AV33,$AS$19:$AT$48,2,FALSE) -> #N/A | AX33: =IF(ISNA(AW33),"",AW33) | AZ33: =IF($BA33<>"",MAX(AZ$18:AZ32)+1,"") | BA33: =IF($AM23=DropDown!$N$11,AJ23,"") | BC33: 15 | BD33: =VLOOKUP($BC33,$AZ$19:$BA$48,2,FALSE) -> #N/A | BE33: =IF(ISNA(BD33),"",BD33) | BG33: =IF($BH33<>"",MAX(BG$18:BG32)+1,"") | BH33: =IF(BE19="","",BE19) | BI33: 15 | BJ33: =VLOOKUP($BI33,$BG$19:$BH$48,2,FALSE) -> #N/A | BK33: =IF(ISNA(BJ33),"",BJ33)
AR34: 4 | AS34: =IF($AT34<>"",MAX(AS$18:AS33)+1,"") | AT34: =IF($J33=DropDown!$N$11,F33,"") | AV34: 16 | AW34: =VLOOKUP($AV34,$AS$19:$AT$48,2,FALSE) -> #N/A | AX34: =IF(ISNA(AW34),"",AW34) | AY34: 4 | AZ34: =IF($BA34<>"",MAX(AZ$18:AZ33)+1,"") | BA34: =IF($AB33=DropDown!$N$11,X33,"") | BC34: 16 | BD34: =VLOOKUP($BC34,$AZ$19:$BA$48,2,FALSE) -> #N/A | BE34: =IF(ISNA(BD34),"",BD34) | BG34: =IF($BH34<>"",MAX(BG$18:BG33)+1,"") | BH34: =IF(BE20="","",BE20) | BI34: 16 | BJ34: =VLOOKUP($BI34,$BG$19:$BH$48,2,FALSE) -> #N/A | BK34: =IF(ISNA(BJ34),"",BJ34)
AS35: =IF($AT35<>"",MAX(AS$18:AS34)+1,"") | AT35: =IF($J34=DropDown!$N$11,F34,"") | AV35: 17 | AW35: =VLOOKUP($AV35,$AS$19:$AT$48,2,FALSE) -> #N/A | AX35: =IF(ISNA(AW35),"",AW35) | AZ35: =IF($BA35<>"",MAX(AZ$18:AZ34)+1,"") | BA35: =IF($AB34=DropDown!$N$11,X34,"") | BC35: 17 | BD35: =VLOOKUP($BC35,$AZ$19:$BA$48,2,FALSE) -> #N/A | BE35: =IF(ISNA(BD35),"",BD35) | BG35: =IF($BH35<>"",MAX(BG$18:BG34)+1,"") | BH35: =IF(BE21="","",BE21) | BI35: 17 | BJ35: =VLOOKUP($BI35,$BG$19:$BH$48,2,FALSE) -> #N/A | BK35: =IF(ISNA(BJ35),"",BJ35)
AS36: =IF($AT36<>"",MAX(AS$18:AS35)+1,"") | AT36: =IF($J35=DropDown!$N$11,F35,"") | AV36: 18 | AW36: =VLOOKUP($AV36,$AS$19:$AT$48,2,FALSE) -> #N/A | AX36: =IF(ISNA(AW36),"",AW36) | AZ36: =IF($BA36<>"",MAX(AZ$18:AZ35)+1,"") | BA36: =IF($AB35=DropDown!$N$11,X35,"") | BC36: 18 | BD36: =VLOOKUP($BC36,$AZ$19:$BA$48,2,FALSE) -> #N/A | BE36: =IF(ISNA(BD36),"",BD36) | BG36: =IF($BH36<>"",MAX(BG$18:BG35)+1,"") | BH36: =IF(BE22="","",BE22) | BI36: 18 | BJ36: =VLOOKUP($BI36,$BG$19:$BH$48,2,FALSE) -> #N/A | BK36: =IF(ISNA(BJ36),"",BJ36)
AS37: =IF($AT37<>"",MAX(AS$18:AS36)+1,"") | AT37: =IF($J36=DropDown!$N$11,F36,"") | AV37: 19 | AW37: =VLOOKUP($AV37,$AS$19:$AT$48,2,FALSE) -> #N/A | AX37: =IF(ISNA(AW37),"",AW37) | AZ37: =IF($BA37<>"",MAX(AZ$18:AZ36)+1,"") | BA37: =IF($AB36=DropDown!$N$11,X36,"") | BC37: 19 | BD37: =VLOOKUP($BC37,$AZ$19:$BA$48,2,FALSE) -> #N/A | BE37: =IF(ISNA(BD37),"",BD37) | BG37: =IF($BH37<>"",MAX(BG$18:BG36)+1,"") | BH37: =IF(BE23="","",BE23) | BI37: 19 | BJ37: =VLOOKUP($BI37,$BG$19:$BH$48,2,FALSE) -> #N/A | BK37: =IF(ISNA(BJ37),"",BJ37)
AS38: =IF($AT38<>"",MAX(AS$18:AS37)+1,"") | AT38: =IF($J37=DropDown!$N$11,F37,"") | AV38: 20 | AW38: =VLOOKUP($AV38,$AS$19:$AT$48,2,FALSE) -> #N/A | AX38: =IF(ISNA(AW38),"",AW38) | AZ38: =IF($BA38<>"",MAX(AZ$18:AZ37)+1,"") | BA38: =IF($AB37=DropDown!$N$11,X37,"") | BC38: 20 | BD38: =VLOOKUP($BC38,$AZ$19:$BA$48,2,FALSE) -> #N/A | BE38: =IF(ISNA(BD38),"",BD38) | BG38: =IF($BH38<>"",MAX(BG$18:BG37)+1,"") | BH38: =IF(BE24="","",BE24) | BI38: 20 | BJ38: =VLOOKUP($BI38,$BG$19:$BH$48,2,FALSE) -> #N/A | BK38: =IF(ISNA(BJ38),"",BJ38)
AR39: 5 | AS39: =IF($AT39<>"",MAX(AS$18:AS38)+1,"") | AT39: =IF($P33=DropDown!$N$11,L33,"") | AV39: 21 | AW39: =VLOOKUP($AV39,$AS$19:$AT$48,2,FALSE) -> #N/A | AX39: =IF(ISNA(AW39),"",AW39) | AY39: 5 | AZ39: =IF($BA39<>"",MAX(AZ$18:AZ38)+1,"") | BA39: =IF($AH33=DropDown!$N$11,AD33,"") | BC39: 21 | BD39: =VLOOKUP($BC39,$AZ$19:$BA$48,2,FALSE) -> #N/A | BE39: =IF(ISNA(BD39),"",BD39) | BG39: =IF($BH39<>"",MAX(BG$18:BG38)+1,"") | BH39: =IF(BE25="","",BE25) | BI39: 21 | BJ39: =VLOOKUP($BI39,$BG$19:$BH$48,2,FALSE) -> #N/A | BK39: =IF(ISNA(BJ39),"",BJ39)
AS40: =IF($AT40<>"",MAX(AS$18:AS39)+1,"") | AT40: =IF($P34=DropDown!$N$11,L34,"") | AV40: 22 | AW40: =VLOOKUP($AV40,$AS$19:$AT$48,2,FALSE) -> #N/A | AX40: =IF(ISNA(AW40),"",AW40) | AZ40: =IF($BA40<>"",MAX(AZ$18:AZ39)+1,"") | BA40: =IF($AH34=DropDown!$N$11,AD34,"") | BC40: 22 | BD40: =VLOOKUP($BC40,$AZ$19:$BA$48,2,FALSE) -> #N/A | BE40: =IF(ISNA(BD40),"",BD40) | BG40: =IF($BH40<>"",MAX(BG$18:BG39)+1,"") | BH40: =IF(BE26="","",BE26) | BI40: 22 | BJ40: =VLOOKUP($BI40,$BG$19:$BH$48,2,FALSE) -> #N/A | BK40: =IF(ISNA(BJ40),"",BJ40)
AS41: =IF($AT41<>"",MAX(AS$18:AS40)+1,"") | AT41: =IF($P35=DropDown!$N$11,L35,"") | AV41: 23 | AW41: =VLOOKUP($AV41,$AS$19:$AT$48,2,FALSE) -> #N/A | AX41: =IF(ISNA(AW41),"",AW41) | AZ41: =IF($BA41<>"",MAX(AZ$18:AZ40)+1,"") | BA41: =IF($AH35=DropDown!$N$11,AD35,"") | BC41: 23 | BD41: =VLOOKUP($BC41,$AZ$19:$BA$48,2,FALSE) -> #N/A | BE41: =IF(ISNA(BD41),"",BD41) | BG41: =IF($BH41<>"",MAX(BG$18:BG40)+1,"") | BH41: =IF(BE27="","",BE27) | BI41: 23 | BJ41: =VLOOKUP($BI41,$BG$19:$BH$48,2,FALSE) -> #N/A | BK41: =IF(ISNA(BJ41),"",BJ41)
AS42: =IF($AT42<>"",MAX(AS$18:AS41)+1,"") | AT42: =IF($P36=DropDown!$N$11,L36,"") | AV42: 24 | AW42: =VLOOKUP($AV42,$AS$19:$AT$48,2,FALSE) -> #N/A | AX42: =IF(ISNA(AW42),"",AW42) | AZ42: =IF($BA42<>"",MAX(AZ$18:AZ41)+1,"") | BA42: =IF($AH36=DropDown!$N$11,AD36,"") | BC42: 24 | BD42: =VLOOKUP($BC42,$AZ$19:$BA$48,2,FALSE) -> #N/A | BE42: =IF(ISNA(BD42),"",BD42) | BG42: =IF($BH42<>"",MAX(BG$18:BG41)+1,"") | BH42: =IF(BE28="","",BE28) | BI42: 24 | BJ42: =VLOOKUP($BI42,$BG$19:$BH$48,2,FALSE) -> #N/A | BK42: =IF(ISNA(BJ42),"",BJ42)
AS43: =IF($AT43<>"",MAX(AS$18:AS42)+1,"") | AT43: =IF($P37=DropDown!$N$11,L37,"") | AV43: 25 | AW43: =VLOOKUP($AV43,$AS$19:$AT$48,2,FALSE) -> #N/A | AX43: =IF(ISNA(AW43),"",AW43) | AZ43: =IF($BA43<>"",MAX(AZ$18:AZ42)+1,"") | BA43: =IF($AH37=DropDown!$N$11,AD37,"") | BC43: 25 | BD43: =VLOOKUP($BC43,$AZ$19:$BA$48,2,FALSE) -> #N/A | BE43: =IF(ISNA(BD43),"",BD43) | BG43: =IF($BH43<>"",MAX(BG$18:BG42)+1,"") | BH43: =IF(BE29="","",BE29) | BI43: 25 | BJ43: =VLOOKUP($BI43,$BG$19:$BH$48,2,FALSE) -> #N/A | BK43: =IF(ISNA(BJ43),"",BJ43)
J44: =INDIRECT('D1-D2-D3'!$J$4&"!C142") -> Why the cause can be excluded (is not a real root cause) ? | AR44: 6 | AS44: =IF($AT44<>"",MAX(AS$18:AS43)+1,"") | AT44: =IF($U33=DropDown!$N$11,R33,"") | AV44: 26 | AW44: =VLOOKUP($AV44,$AS$19:$AT$48,2,FALSE) -> #N/A | AX44: =IF(ISNA(AW44),"",AW44) | AY44: 6 | AZ44: =IF($BA44<>"",MAX(AZ$18:AZ43)+1,"") | BA44: =IF($AM33=DropDown!$N$11,AJ33,"") | BC44: 26 | BD44: =VLOOKUP($BC44,$AZ$19:$BA$48,2,FALSE) -> #N/A | BE44: =IF(ISNA(BD44),"",BD44) | BG44: =IF($BH44<>"",MAX(BG$18:BG43)+1,"") | BH44: =IF(BE30="","",BE30) | BI44: 26 | BJ44: =VLOOKUP($BI44,$BG$19:$BH$48,2,FALSE) -> #N/A | BK44: =IF(ISNA(BJ44),"",BJ44)
AS45: =IF($AT45<>"",MAX(AS$18:AS44)+1,"") | AT45: =IF($U34=DropDown!$N$11,R34,"") | AV45: 27 | AW45: =VLOOKUP($AV45,$AS$19:$AT$48,2,FALSE) -> #N/A | AX45: =IF(ISNA(AW45),"",AW45) | AZ45: =IF($BA45<>"",MAX(AZ$18:AZ44)+1,"") | BA45: =IF($AM34=DropDown!$N$11,AJ34,"") | BC45: 27 | BD45: =VLOOKUP($BC45,$AZ$19:$BA$48,2,FALSE) -> #N/A | BE45: =IF(ISNA(BD45),"",BD45) | BG45: =IF($BH45<>"",MAX(BG$18:BG44)+1,"") | BH45: =IF(BE31="","",BE31) | BI45: 27 | BJ45: =VLOOKUP($BI45,$BG$19:$BH$48,2,FALSE) -> #N/A | BK45: =IF(ISNA(BJ45),"",BJ45)
F46: =INDIRECT('D1-D2-D3'!$J$4&"!C139") -> Occurrence | X46: =INDIRECT('D1-D2-D3'!$J$4&"!C140") -> Non-detection | AS46: =IF($AT46<>"",MAX(AS$18:AS45)+1,"") | AT46: =IF($U35=DropDown!$N$11,R35,"") | AV46: 28 | AW46: =VLOOKUP($AV46,$AS$19:$AT$48,2,FALSE) -> #N/A | AX46: =IF(ISNA(AW46),"",AW46) | AZ46: =IF($BA46<>"",MAX(AZ$18:AZ45)+1,"") | BA46: =IF($AM35=DropDown!$N$11,AJ35,"") | BC46: 28 | BD46: =VLOOKUP($BC46,$AZ$19:$BA$48,2,FALSE) -> #N/A | BE46: =IF(ISNA(BD46),"",BD46) | BG46: =IF($BH46<>"",MAX(BG$18:BG45)+1,"") | BH46: =IF(BE32="","",BE32) | BI46: 28 | BJ46: =VLOOKUP($BI46,$BG$19:$BH$48,2,FALSE) -> #N/A | BK46: =IF(ISNA(BJ46),"",BJ46)
J47: =INDIRECT('D1-D2-D3'!$J$4&"!C141") -> Why it is not a root cause ? | AB47: =INDIRECT('D1-D2-D3'!$J$4&"!C141") -> Why it is not a root cause ? | AS47: =IF($AT47<>"",MAX(AS$18:AS46)+1,"") | AT47: =IF($U36=DropDown!$N$11,R36,"") | AV47: 29 | AW47: =VLOOKUP($AV47,$AS$19:$AT$48,2,FALSE) -> #N/A | AX47: =IF(ISNA(AW47),"",AW47) | AZ47: =IF($BA47<>"",MAX(AZ$18:AZ46)+1,"") | BA47: =IF($AM36=DropDown!$N$11,AJ36,"") | BC47: 29 | BD47: =VLOOKUP($BC47,$AZ$19:$BA$48,2,FALSE) -> #N/A | BE47: =IF(ISNA(BD47),"",BD47) | BG47: =IF($BH47<>"",MAX(BG$18:BG46)+1,"") | BH47: =IF(BE33="","",BE33) | BI47: 29 | BJ47: =VLOOKUP($BI47,$BG$19:$BH$48,2,FALSE) -> #N/A | BK47: =IF(ISNA(BJ47),"",BJ47)
F48: =IF(ISNA(AX51), " ",AX51) | X48: =IF(ISNA(BE51), " ",BE51) | AS48: =IF($AT48<>"",MAX(AS$18:AS47)+1,"") | AT48: =IF($U37=DropDown!$N$11,R37,"") | AV48: 30 | AW48: =VLOOKUP($AV48,$AS$19:$AT$48,2,FALSE) -> #N/A | AX48: =IF(ISNA(AW48),"",AW48) | AZ48: =IF($BA48<>"",MAX(AZ$18:AZ47)+1,"") | BA48: =IF($AM37=DropDown!$N$11,AJ37,"") | BC48: 30 | BD48: =VLOOKUP($BC48,$AZ$19:$BA$48,2,FALSE) -> #N/A | BE48: =IF(ISNA(BD48),"",BD48) | BG48: =IF($BH48<>"",MAX(BG$18:BG47)+1,"") | BH48: =IF(BE34="","",BE34) | BI48: 30 | BJ48: =VLOOKUP($BI48,$BG$19:$BH$48,2,FALSE) -> #N/A | BK48: =IF(ISNA(BJ48),"",BJ48)
F49: =IF(ISNA(AX52), " ",AX52) | X49: =IF(ISNA(BE52), " ",BE52)
F50: =IF(ISNA(AX53), " ",AX53) | X50: =IF(ISNA(BE53), " ",BE53) | AQ50: NO | AS50: 0 | AX50: no-occ | AZ50: 0 | BE50: no - nondet
F51: =IF(ISNA(AX54), " ",AX54) | X51: =IF(ISNA(BE54), " ",BE54) | AR51: 1 | AS51: =IF($AT51<>"",AS50+1,"") | AT51: =IF($J19=DropDown!$N$12,F19,"") | AV51: 1 | AW51: =VLOOKUP($AV51,$AS$51:$AT$80,2,FALSE) -> #N/A | AX51: =IF(ISNA(AW51),"",AW51) | AY51: 1 | AZ51: =IF($BA51<>"",AZ50+1,"") | BA51: =IF($AB19=DropDown!$N$12,X19,"") | BC51: 1 | BD51: =VLOOKUP($BC51,$AZ$51:$BA$80,2,FALSE) -> #N/A | BE51: =IF(ISNA(BD51),"",BD51)
F52: =IF(ISNA(AX55), " ",AX55) | X52: =IF(ISNA(BE55), " ",BE55) | AS52: =IF($AT52<>"",MAX(AS$50:AS51)+1,"") | AT52: =IF($J20=DropDown!$N$12,F20,"") | AV52: 2 | AW52: =VLOOKUP($AV52,$AS$51:$AT$80,2,FALSE) -> #N/A | AX52: =IF(ISNA(AW52),"",AW52) | AZ52: =IF($BA52<>"",MAX(AZ$50:AZ51)+1,"") | BA52: =IF($AB20=DropDown!$N$12,X20,"") | BC52: 2 | BD52: =VLOOKUP($BC52,$AZ$51:$BA$80,2,FALSE) -> #N/A | BE52: =IF(ISNA(BD52),"",BD52)
F53: =IF(ISNA(AX56), " ",AX56) | X53: =IF(ISNA(BE56), " ",BE56) | AS53: =IF($AT53<>"",MAX(AS$50:AS52)+1,"") | AT53: =IF($J21=DropDown!$N$12,F21,"") | AV53: 3 | AW53: =VLOOKUP($AV53,$AS$51:$AT$80,2,FALSE) -> #N/A | AX53: =IF(ISNA(AW53),"",AW53) | AZ53: =IF($BA53<>"",MAX(AZ$50:AZ52)+1,"") | BA53: =IF($AB21=DropDown!$N$12,X21,"") | BC53: 3 | BD53: =VLOOKUP($BC53,$AZ$51:$BA$80,2,FALSE) -> #N/A | BE53: =IF(ISNA(BD53),"",BD53)
F54: =IF(ISNA(AX57), " ",AX57) | X54: =IF(ISNA(BE57), " ",BE57) | AS54: =IF($AT54<>"",MAX(AS$50:AS53)+1,"") | AT54: =IF($J22=DropDown!$N$12,F22,"") | AV54: 4 | AW54: =VLOOKUP($AV54,$AS$51:$AT$80,2,FALSE) -> #N/A | AX54: =IF(ISNA(AW54),"",AW54) | AZ54: =IF($BA54<>"",MAX(AZ$50:AZ53)+1,"") | BA54: =IF($AB22=DropDown!$N$12,X22,"") | BC54: 4 | BD54: =VLOOKUP($BC54,$AZ$51:$BA$80,2,FALSE) -> #N/A | BE54: =IF(ISNA(BD54),"",BD54)
F55: =IF(ISNA(AX58), " ",AX58) | X55: =IF(ISNA(BE58), " ",BE58) | AS55: =IF($AT55<>"",MAX(AS$50:AS54)+1,"") | AT55: =IF($J23=DropDown!$N$12,F23,"") | AV55: 5 | AW55: =VLOOKUP($AV55,$AS$51:$AT$80,2,FALSE) -> #N/A | AX55: =IF(ISNA(AW55),"",AW55) | AZ55: =IF($BA55<>"",MAX(AZ$50:AZ54)+1,"") | BA55: =IF($AB23=DropDown!$N$12,X23,"") | BC55: 5 | BD55: =VLOOKUP($BC55,$AZ$51:$BA$80,2,FALSE) -> #N/A | BE55: =IF(ISNA(BD55),"",BD55)
F56: =IF(ISNA(AX59), " ",AX59) | X56: =IF(ISNA(BE59), " ",BE59) | AR56: 2 | AS56: =IF($AT56<>"",MAX(AS$50:AS55)+1,"") | AT56: =IF($P19=DropDown!$N$12,L19,"") | AV56: 6 | AW56: =VLOOKUP($AV56,$AS$51:$AT$80,2,FALSE) -> #N/A | AX56: =IF(ISNA(AW56),"",AW56) | AY56: 2 | AZ56: =IF($BA56<>"",MAX(AZ$50:AZ55)+1,"") | BA56: =IF($AH19=DropDown!$N$12,AD19,"") | BC56: 6 | BD56: =VLOOKUP($BC56,$AZ$51:$BA$80,2,FALSE) -> #N/A | BE56: =IF(ISNA(BD56),"",BD56)
F57: =IF(ISNA(AX60), " ",AX60) | X57: =IF(ISNA(BE60), " ",BE60) | AS57: =IF($AT57<>"",MAX(AS$50:AS56)+1,"") | AT57: =IF($P20=DropDown!$N$12,L20,"") | AV57: 7 | AW57: =VLOOKUP($AV57,$AS$51:$AT$80,2,FALSE) -> #N/A | AX57: =IF(ISNA(AW57),"",AW57) | AZ57: =IF($BA57<>"",MAX(AZ$50:AZ56)+1,"") | BA57: =IF($AH20=DropDown!$N$12,AD20,"") | BC57: 7 | BD57: =VLOOKUP($BC57,$AZ$51:$BA$80,2,FALSE) -> #N/A | BE57: =IF(ISNA(BD57),"",BD57)
F58: =IF(ISNA(AX61), " ",AX61) | X58: =IF(ISNA(BE61), " ",BE61) | AS58: =IF($AT58<>"",MAX(AS$50:AS57)+1,"") | AT58: =IF($P21=DropDown!$N$12,L21,"") | AV58: 8 | AW58: =VLOOKUP($AV58,$AS$51:$AT$80,2,FALSE) -> #N/A | AX58: =IF(ISNA(AW58),"",AW58) | AZ58: =IF($BA58<>"",MAX(AZ$50:AZ57)+1,"") | BA58: =IF($AH21=DropDown!$N$12,AD21,"") | BC58: 8 | BD58: =VLOOKUP($BC58,$AZ$51:$BA$80,2,FALSE) -> #N/A | BE58: =IF(ISNA(BD58),"",BD58)
F59: =IF(ISNA(AX62), " ",AX62) | X59: =IF(ISNA(BE62), " ",BE62) | AS59: =IF($AT59<>"",MAX(AS$50:AS58)+1,"") | AT59: =IF($P22=DropDown!$N$12,L22,"") | AV59: 9 | AW59: =VLOOKUP($AV59,$AS$51:$AT$80,2,FALSE) -> #N/A | AX59: =IF(ISNA(AW59),"",AW59) | AZ59: =IF($BA59<>"",MAX(AZ$50:AZ58)+1,"") | BA59: =IF($AH22=DropDown!$N$12,AD22,"") | BC59: 9 | BD59: =VLOOKUP($BC59,$AZ$51:$BA$80,2,FALSE) -> #N/A | BE59: =IF(ISNA(BD59),"",BD59)
F60: =IF(ISNA(AX63), " ",AX63) | X60: =IF(ISNA(BE63), " ",BE63) | AS60: =IF($AT60<>"",MAX(AS$50:AS59)+1,"") | AT60: =IF($P23=DropDown!$N$12,L23,"") | AV60: 10 | AW60: =VLOOKUP($AV60,$AS$51:$AT$80,2,FALSE) -> #N/A | AX60: =IF(ISNA(AW60),"",AW60) | AZ60: =IF($BA60<>"",MAX(AZ$50:AZ59)+1,"") | BA60: =IF($AH23=DropDown!$N$12,AD23,"") | BC60: 10 | BD60: =VLOOKUP($BC60,$AZ$51:$BA$80,2,FALSE) -> #N/A | BE60: =IF(ISNA(BD60),"",BD60)
F61: =IF(ISNA(AX64), " ",AX64) | X61: =IF(ISNA(BE64), " ",BE64) | AR61: 3 | AS61: =IF($AT61<>"",MAX(AS$50:AS60)+1,"") | AT61: =IF($U19=DropDown!$N$12,R19,"") | AV61: 11 | AW61: =VLOOKUP($AV61,$AS$51:$AT$80,2,FALSE) -> #N/A | AX61: =IF(ISNA(AW61),"",AW61) | AY61: 3 | AZ61: =IF($BA61<>"",MAX(AZ$50:AZ60)+1,"") | BA61: =IF($AM19=DropDown!$N$12,AJ19,"") | BC61: 11 | BD61: =VLOOKUP($BC61,$AZ$51:$BA$80,2,FALSE) -> #N/A | BE61: =IF(ISNA(BD61),"",BD61)
F62: =IF(ISNA(AX65), " ",AX65) | X62: =IF(ISNA(BE65), " ",BE65) | AS62: =IF($AT62<>"",MAX(AS$50:AS61)+1,"") | AT62: =IF($U20=DropDown!$N$12,R20,"") | AV62: 12 | AW62: =VLOOKUP($AV62,$AS$51:$AT$80,2,FALSE) -> #N/A | AX62: =IF(ISNA(AW62),"",AW62) | AZ62: =IF($BA62<>"",MAX(AZ$50:AZ61)+1,"") | BA62: =IF($AM20=DropDown!$N$12,AJ20,"") | BC62: 12 | BD62: =VLOOKUP($BC62,$AZ$51:$BA$80,2,FALSE) -> #N/A | BE62: =IF(ISNA(BD62),"",BD62)
F63: =IF(ISNA(AX66), " ",AX66) | X63: =IF(ISNA(BE66), " ",BE66) | AS63: =IF($AT63<>"",MAX(AS$50:AS62)+1,"") | AT63: =IF($U21=DropDown!$N$12,R21,"") | AV63: 13 | AW63: =VLOOKUP($AV63,$AS$51:$AT$80,2,FALSE) -> #N/A | AX63: =IF(ISNA(AW63),"",AW63) | AZ63: =IF($BA63<>"",MAX(AZ$50:AZ62)+1,"") | BA63: =IF($AM21=DropDown!$N$12,AJ21,"") | BC63: 13 | BD63: =VLOOKUP($BC63,$AZ$51:$BA$80,2,FALSE) -> #N/A | BE63: =IF(ISNA(BD63),"",BD63)
F64: =IF(ISNA(AX67), " ",AX67) | X64: =IF(ISNA(BE67), " ",BE67) | AS64: =IF($AT64<>"",MAX(AS$50:AS63)+1,"") | AT64: =IF($U22=DropDown!$N$12,R22,"") | AV64: 14 | AW64: =VLOOKUP($AV64,$AS$51:$AT$80,2,FALSE) -> #N/A | AX64: =IF(ISNA(AW64),"",AW64) | AZ64: =IF($BA64<>"",MAX(AZ$50:AZ63)+1,"") | BA64: =IF($AM22=DropDown!$N$12,AJ22,"") | BC64: 14 | BD64: =VLOOKUP($BC64,$AZ$51:$BA$80,2,FALSE) -> #N/A | BE64: =IF(ISNA(BD64),"",BD64)
F65: =IF(ISNA(AX68), " ",AX68) | X65: =IF(ISNA(BE68), " ",BE68) | AS65: =IF($AT65<>"",MAX(AS$50:AS64)+1,"") | AT65: =IF($U23=DropDown!$N$12,R23,"") | AV65: 15 | AW65: =VLOOKUP($AV65,$AS$51:$AT$80,2,FALSE) -> #N/A | AX65: =IF(ISNA(AW65),"",AW65) | AZ65: =IF($BA65<>"",MAX(AZ$50:AZ64)+1,"") | BA65: =IF($AM23=DropDown!$N$12,AJ23,"") | BC65: 15 | BD65: =VLOOKUP($BC65,$AZ$51:$BA$80,2,FALSE) -> #N/A | BE65: =IF(ISNA(BD65),"",BD65)
F66: =IF(ISNA(AX69), " ",AX69) | X66: =IF(ISNA(BE69), " ",BE69) | AR66: 4 | AS66: =IF($AT66<>"",MAX(AS$50:AS65)+1,"") | AT66: =IF($J33=DropDown!$N$12,F33,"") | AV66: 16 | AW66: =VLOOKUP($AV66,$AS$51:$AT$80,2,FALSE) -> #N/A | AX66: =IF(ISNA(AW66),"",AW66) | AY66: 4 | AZ66: =IF($BA66<>"",MAX(AZ$50:AZ65)+1,"") | BA66: =IF($AB33=DropDown!$N$12,X33,"") | BC66: 16 | BD66: =VLOOKUP($BC66,$AZ$51:$BA$80,2,FALSE) -> #N/A | BE66: =IF(ISNA(BD66),"",BD66)
F67: =IF(ISNA(AX70), " ",AX70) | X67: =IF(ISNA(BE70), " ",BE70) | AS67: =IF($AT67<>"",MAX(AS$50:AS66)+1,"") | AT67: =IF($J34=DropDown!$N$12,F34,"") | AV67: 17 | AW67: =VLOOKUP($AV67,$AS$51:$AT$80,2,FALSE) -> #N/A | AX67: =IF(ISNA(AW67),"",AW67) | AZ67: =IF($BA67<>"",MAX(AZ$50:AZ66)+1,"") | BA67: =IF($AB34=DropDown!$N$12,X34,"") | BC67: 17 | BD67: =VLOOKUP($BC67,$AZ$51:$BA$80,2,FALSE) -> #N/A | BE67: =IF(ISNA(BD67),"",BD67)
AS68: =IF($AT68<>"",MAX(AS$50:AS67)+1,"") | AT68: =IF($J35=DropDown!$N$12,F35,"") | AV68: 18 | AW68: =VLOOKUP($AV68,$AS$51:$AT$80,2,FALSE) -> #N/A | AX68: =IF(ISNA(AW68),"",AW68) | AZ68: =IF($BA68<>"",MAX(AZ$50:AZ67)+1,"") | BA68: =IF($AB35=DropDown!$N$12,X35,"") | BC68: 18 | BD68: =VLOOKUP($BC68,$AZ$51:$BA$80,2,FALSE) -> #N/A | BE68: =IF(ISNA(BD68),"",BD68)
AS69: =IF($AT69<>"",MAX(AS$50:AS68)+1,"") | AT69: =IF($J36=DropDown!$N$12,F36,"") | AV69: 19 | AW69: =VLOOKUP($AV69,$AS$51:$AT$80,2,FALSE) -> #N/A | AX69: =IF(ISNA(AW69),"",AW69) | AZ69: =IF($BA69<>"",MAX(AZ$50:AZ68)+1,"") | BA69: =IF($AB36=DropDown!$N$12,X36,"") | BC69: 19 | BD69: =VLOOKUP($BC69,$AZ$51:$BA$80,2,FALSE) -> #N/A | BE69: =IF(ISNA(BD69),"",BD69)
AS70: =IF($AT70<>"",MAX(AS$50:AS69)+1,"") | AT70: =IF($J37=DropDown!$N$12,F37,"") | AV70: 20 | AW70: =VLOOKUP($AV70,$AS$51:$AT$80,2,FALSE) -> #N/A | AX70: =IF(ISNA(AW70),"",AW70) | AZ70: =IF($BA70<>"",MAX(AZ$50:AZ69)+1,"") | BA70: =IF($AB37=DropDown!$N$12,X37,"") | BC70: 20 | BD70: =VLOOKUP($BC70,$AZ$51:$BA$80,2,FALSE) -> #N/A | BE70: =IF(ISNA(BD70),"",BD70)
AR71: 5 | AS71: =IF($AT71<>"",MAX(AS$50:AS70)+1,"") | AT71: =IF($P33=DropDown!$N$12,L33,"") | AV71: 21 | AW71: =VLOOKUP($AV71,$AS$51:$AT$80,2,FALSE) -> #N/A | AX71: =IF(ISNA(AW71),"",AW71) | AY71: 5 | AZ71: =IF($BA71<>"",MAX(AZ$50:AZ70)+1,"") | BA71: =IF($AH33=DropDown!$N$12,AD33,"") | BC71: 21 | BD71: =VLOOKUP($BC71,$AZ$51:$BA$80,2,FALSE) -> #N/A | BE71: =IF(ISNA(BD71),"",BD71)
AS72: =IF($AT72<>"",MAX(AS$50:AS71)+1,"") | AT72: =IF($P34=DropDown!$N$12,L34,"") | AV72: 22 | AW72: =VLOOKUP($AV72,$AS$51:$AT$80,2,FALSE) -> #N/A | AX72: =IF(ISNA(AW72),"",AW72) | AZ72: =IF($BA72<>"",MAX(AZ$50:AZ71)+1,"") | BA72: =IF($AH34=DropDown!$N$12,AD34,"") | BC72: 22 | BD72: =VLOOKUP($BC72,$AZ$51:$BA$80,2,FALSE) -> #N/A | BE72: =IF(ISNA(BD72),"",BD72)
AS73: =IF($AT73<>"",MAX(AS$50:AS72)+1,"") | AT73: =IF($P35=DropDown!$N$12,L35,"") | AV73: 23 | AW73: =VLOOKUP($AV73,$AS$51:$AT$80,2,FALSE) -> #N/A | AX73: =IF(ISNA(AW73),"",AW73) | AZ73: =IF($BA73<>"",MAX(AZ$50:AZ72)+1,"") | BA73: =IF($AH35=DropDown!$N$12,AD35,"") | BC73: 23 | BD73: =VLOOKUP($BC73,$AZ$51:$BA$80,2,FALSE) -> #N/A | BE73: =IF(ISNA(BD73),"",BD73)
AS74: =IF($AT74<>"",MAX(AS$50:AS73)+1,"") | AT74: =IF($P36=DropDown!$N$12,L36,"") | AV74: 24 | AW74: =VLOOKUP($AV74,$AS$51:$AT$80,2,FALSE) -> #N/A | AX74: =IF(ISNA(AW74),"",AW74) | AZ74: =IF($BA74<>"",MAX(AZ$50:AZ73)+1,"") | BA74: =IF($AH36=DropDown!$N$12,AD36,"") | BC74: 24 | BD74: =VLOOKUP($BC74,$AZ$51:$BA$80,2,FALSE) -> #N/A | BE74: =IF(ISNA(BD74),"",BD74)
AS75: =IF($AT75<>"",MAX(AS$50:AS74)+1,"") | AT75: =IF($P37=DropDown!$N$12,L37,"") | AV75: 25 | AW75: =VLOOKUP($AV75,$AS$51:$AT$80,2,FALSE) -> #N/A | AX75: =IF(ISNA(AW75),"",AW75) | AZ75: =IF($BA75<>"",MAX(AZ$50:AZ74)+1,"") | BA75: =IF($AH37=DropDown!$N$12,AD37,"") | BC75: 25 | BD75: =VLOOKUP($BC75,$AZ$51:$BA$80,2,FALSE) -> #N/A | BE75: =IF(ISNA(BD75),"",BD75)
AR76: 6 | AS76: =IF($AT76<>"",MAX(AS$50:AS75)+1,"") | AT76: =IF($U33=DropDown!$N$12,R33,"") | AV76: 26 | AW76: =VLOOKUP($AV76,$AS$51:$AT$80,2,FALSE) -> #N/A | AX76: =IF(ISNA(AW76),"",AW76) | AY76: 6 | AZ76: =IF($BA76<>"",MAX(AZ$50:AZ75)+1,"") | BA76: =IF($AM33=DropDown!$N$12,AJ33,"") | BC76: 26 | BD76: =VLOOKUP($BC76,$AZ$51:$BA$80,2,FALSE) -> #N/A | BE76: =IF(ISNA(BD76),"",BD76)
AS77: =IF($AT77<>"",MAX(AS$50:AS76)+1,"") | AT77: =IF($U34=DropDown!$N$12,R34,"") | AV77: 27 | AW77: =VLOOKUP($AV77,$AS$51:$AT$80,2,FALSE) -> #N/A | AX77: =IF(ISNA(AW77),"",AW77) | AZ77: =IF($BA77<>"",MAX(AZ$50:AZ76)+1,"") | BA77: =IF($AM34=DropDown!$N$12,AJ34,"") | BC77: 27 | BD77: =VLOOKUP($BC77,$AZ$51:$BA$80,2,FALSE) -> #N/A | BE77: =IF(ISNA(BD77),"",BD77)
AS78: =IF($AT78<>"",MAX(AS$50:AS77)+1,"") | AT78: =IF($U35=DropDown!$N$12,R35,"") | AV78: 28 | AW78: =VLOOKUP($AV78,$AS$51:$AT$80,2,FALSE) -> #N/A | AX78: =IF(ISNA(AW78),"",AW78) | AZ78: =IF($BA78<>"",MAX(AZ$50:AZ77)+1,"") | BA78: =IF($AM35=DropDown!$N$12,AJ35,"") | BC78: 28 | BD78: =VLOOKUP($BC78,$AZ$51:$BA$80,2,FALSE) -> #N/A | BE78: =IF(ISNA(BD78),"",BD78)
AS79: =IF($AT79<>"",MAX(AS$50:AS78)+1,"") | AT79: =IF($U36=DropDown!$N$12,R36,"") | AV79: 29 | AW79: =VLOOKUP($AV79,$AS$51:$AT$80,2,FALSE) -> #N/A | AX79: =IF(ISNA(AW79),"",AW79) | AZ79: =IF($BA79<>"",MAX(AZ$50:AZ78)+1,"") | BA79: =IF($AM36=DropDown!$N$12,AJ36,"") | BC79: 29 | BD79: =VLOOKUP($BC79,$AZ$51:$BA$80,2,FALSE) -> #N/A | BE79: =IF(ISNA(BD79),"",BD79)
AS80: =IF($AT80<>"",MAX(AS$50:AS79)+1,"") | AT80: =IF($U37=DropDown!$N$12,R37,"") | AV80: 30 | AW80: =VLOOKUP($AV80,$AS$51:$AT$80,2,FALSE) -> #N/A | AX80: =IF(ISNA(AW80),"",AW80) | AZ80: =IF($BA80<>"",MAX(AZ$50:AZ79)+1,"") | BA80: =IF($AM37=DropDown!$N$12,AJ37,"") | BC80: 30 | BD80: =VLOOKUP($BC80,$AZ$51:$BA$80,2,FALSE) -> #N/A | BE80: =IF(ISNA(BD80),"",BD80)

Sheet D4.5Why's-D5-D6
M1: =INDIRECT('D1-D2-D3'!$J$4&"!C224") -> AP-team leader
I3: =INDIRECT('D1-D2-D3'!$J$4&"!C2")&" "&INDIRECT('D1-D2-D3'!$J$4&"!C145") -> PROBLEM SOLVING SHEET D4 - Root cause analysis | T3: =INDIRECT('D1-D2-D3'!$J$4&"!C3") -> PSS No. | V3: ='D1-D2-D3'!AI4 -> 0 | Y3: 4.15.03.00 | AE3: =INDIRECT('D1-D2-D3'!$J$4&"!C143") -> Page 4: D4-D5-D6
B6: =INDIRECT('D1-D2-D3'!$J$4&"!C145") -> D4 - Root cause analysis | K6: =INDIRECT('D1-D2-D3'!$J$4&"!C68") -> Status | P6: =INDIRECT('D1-D2-D3'!$J$4&"!C69") -> Date | AB6: =INDIRECT('D1-D2-D3'!$J$4&"!C161") -> D5 - Corrective Action(s) | AF6: =INDIRECT('D1-D2-D3'!$J$4&"!C162") -> D6 - Implementation of permanent corrective action(s)
AB9: =INDIRECT('D1-D2-D3'!$J$4&"!C146") -> Were the relevant emloyees trained ? | AI9: =INDIRECT('D1-D2-D3'!$J$4&"!C147") -> Date of training
AB11: =INDIRECT('D1-D2-D3'!$J$4&"!C93") -> Comments | AG11: =INDIRECT('D1-D2-D3'!$J$4&"!C83") -> Responsible
AG13: =INDIRECT('D1-D2-D3'!$J$4&"!C148") -> Date of effectiveness check of training
D16: ='D1-D2-D3'!D48&":" -> Problem description: | J16: =INDIRECT('D1-D2-D3'!$J$4&"!C150") -> 5-Why-Analysis | X16: =INDIRECT('D1-D2-D3'!$J$4&"!C157") -> Fault category | Z16: =INDIRECT('D1-D2-D3'!$J$4&"!C158") -> Verification of the causes | AB16: =INDIRECT('D1-D2-D3'!$J$4&"!C163") -> Action Plan
D17: =IF('D1-D2-D3'!V48="","",'D1-D2-D3'!V48) | J17: =INDIRECT('D1-D2-D3'!$J$4&"!C137") -> Technical consideration | AM17: TECNICAL - ROOT CAUSE AND 5WHYs | AX17: FINAL 5WHYs for 8D | BH17: ACTION PLAN - TECHN: OCC+cause | BP17: ACTION PLAN - TECH: CAUSE + ACTION if Action is available | BW17: FINAL Cause + Corr.actions for 8D | CH17: 5WHY for SYSTEM
D18: =INDIRECT('D1-D2-D3'!$J$4&"!C149") -> Factors identification | I18: =INDIRECT('D1-D2-D3'!$J$4&"!C151") -> Influent factors | J18: =INDIRECT('D1-D2-D3'!$J$4&"!C152") -> Why 1 | L18: =INDIRECT('D1-D2-D3'!$J$4&"!C153") -> Why 2 | O18: =INDIRECT('D1-D2-D3'!$J$4&"!C154") -> Why 3 | Q18: =INDIRECT('D1-D2-D3'!$J$4&"!C155") -> Why 4 | T18: =INDIRECT('D1-D2-D3'!$J$4&"!C156") -> Why 5 | X18: =INDIRECT('D1-D2-D3'!$J$4&"!C159") -> Category | Z18: =INDIRECT('D1-D2-D3'!$J$4&"!C160") -> Method of cause verification | AB18: =INDIRECT('D1-D2-D3'!$J$4&"!C164") -> Corrective Action | AE18: =INDIRECT('D1-D2-D3'!$J$4&"!C165") -> Pic. No. | AF18: =INDIRECT('D1-D2-D3'!$J$4&"!C83") -> Responsible | AH18: =INDIRECT('D1-D2-D3'!$J$4&"!C166") -> Target Date | AJ18: =INDIRECT('D1-D2-D3'!$J$4&"!C84") -> Impl. Date | AM18: 0 | AP18: 1 | AQ18: 2 | AR18: 3 | AS18: 4 | AT18: 5 | AX18: SVERWEIS - 5 Whys | BH18: 0 | BI18: occ | BJ18: fault | BK18: action | BL18: respo | BM18: target | BN18: implem | BO18: 0 | BW18: SVERWEIS | BY18: Act | BZ18: respons | CA18: Target | CB18: impl
D19: =INDIRECT('D1-D2-D3'!$J$4&"!C149")&"/"& INDIRECT('D1-D2-D3'!$J$4&"!C151") -> Factors identification/Influent factors | AM19: =IF($AN19<>"",AM18+1,"") | AN19: =IF(AP19=0,"",IF(ISNA(AP19),"",IF($I19<>"",G19,""))) | AO19: =IF(AP19=0,"",IF(ISNA(AP19),"",IF($I19<>"",I19,""))) | AP19: =IF($I19<>"",J19,"") | AQ19: =IF($I19<>"",L19,"") | AR19: =IF($I19<>"",O19,"") | AS19: =IF($I19<>"",Q19,"") | AT19: =IF($I19<>"",T19,"") | AU19: =IF($I19<>"",X19,"") | AV19: =IF($I19<>"",Z19,"") | AW19: 1 | AX19: =VLOOKUP($AW19,$AM$19:$AV$28,2,FALSE) -> #N/A | AY19: =VLOOKUP($AW19,$AM$19:$AV$28,3,FALSE) -> #N/A | AZ19: =VLOOKUP($AW19,$AM$19:$AV$28,4,FALSE) -> #N/A | BA19: =VLOOKUP($AW19,$AM$19:$AV$28,5,FALSE) -> #N/A | BB19: =VLOOKUP($AW19,$AM$19:$AV$28,6,FALSE) -> #N/A | BC19: =VLOOKUP($AW19,$AM$19:$AV$28,7,FALSE) -> #N/A | BD19: =VLOOKUP($AW19,$AM$19:$AV$28,8,FALSE) -> #N/A | BE19: =VLOOKUP($AW19,$AM$19:$AV$28,9,FALSE) -> #N/A | BF19: =VLOOKUP($AW19,$AM$19:$AV$28,10,FALSE) -> #N/A | BH19: =IF($BI19<>"",BH18+1,"") | BI19: =IF($I19<>"",G19,"") | BJ19: =IF(ISNA($AB19<>""),"",$I19) -> 0 | BK19: =IF(AB19=0,"",IF(ISNA(AB19),"",IF($AB19<>"",AB19,""))) | BL19: =IF(ISNA(AB19),"",IF($AB19<>"",AF19,"")) | BM19: =IF(AH19<>"",AH19,"") | BN19: =IF(AJ19<>"",AJ19,"") | BO19: =IF($BP19<>"",BO18+1,"") | BP19: =IF(BK19<>"", BI19,"") | BQ19: =IF(BL19<>"", BJ19,"") | BR19: =IF(BJ19<>"", BK19,"") | BS19: =IF(BK19<>"", BL19,"") | BT19: =IF(BK19<>"", BM19,"") | BU19: =IF(BK19<>"", BN19,"") | BV19: 1 | BW19: =VLOOKUP($BV19,$BO$19:$BR$28,2,FALSE) -> #N/A | BX19: =VLOOKUP($BV19,$BO$19:$BU$28,3,FALSE) -> #N/A | BY19: =VLOOKUP($BV19,$BO$19:$BU$28,4,FALSE) -> #N/A | BZ19: =VLOOKUP($BV19,$BO$19:$BU$28,5,FALSE) -> #N/A | CA19: =VLOOKUP($BV19,$BO$19:$BU$28,6,FALSE) -> #N/A | CB19: =VLOOKUP($BV19,$BO$19:$BU$28,7,FALSE) -> #N/A | CH19: =IF(ISNA(BD19),"",BD19)
AM20: =IF($AN20<>"",MAX(AM$18:AM19)+1,"") | AN20: =IF(AP20=0,"",IF(ISNA(AP20),"",IF($I20<>"",G20,""))) | AO20: =IF(AP20=0,"",IF(ISNA(AP20),"",IF($I20<>"",I20,""))) | AP20: =IF($I20<>"",J20,"") | AQ20: =IF($I20<>"",L20,"") | AR20: =IF($I20<>"",O20,"") | AS20: =IF($I20<>"",Q20,"") | AT20: =IF($I20<>"",T20,"") | AU20: =IF($I20<>"",X20,"") | AV20: =IF($I20<>"",Z20,"") | AW20: 2 | AX20: =VLOOKUP($AW20,$AM$19:$AV$28,2,FALSE) -> #N/A | AY20: =VLOOKUP($AW20,$AM$19:$AV$28,3,FALSE) -> #N/A | AZ20: =VLOOKUP($AW20,$AM$19:$AV$28,4,FALSE) -> #N/A | BA20: =VLOOKUP($AW20,$AM$19:$AV$28,5,FALSE) -> #N/A | BB20: =VLOOKUP($AW20,$AM$19:$AV$28,6,FALSE) -> #N/A | BC20: =VLOOKUP($AW20,$AM$19:$AV$28,7,FALSE) -> #N/A | BD20: =VLOOKUP($AW20,$AM$19:$AV$28,8,FALSE) -> #N/A | BE20: =VLOOKUP($AW20,$AM$19:$AV$28,9,FALSE) -> #N/A | BF20: =VLOOKUP($AW20,$AM$19:$AV$28,10,FALSE) -> #N/A | BH20: =IF($BI20<>"",MAX(BH$18:BH19)+1,"") | BI20: =IF($I20<>"",G20,"") | BJ20: =IF(ISNA($AB20<>""),"",$I20) -> 0 | BK20: =IF(AB20=0,"",IF(ISNA(AB20),"",IF($AB20<>"",AB20,""))) | BL20: =IF(ISNA(AB20),"",IF($AB20<>"",AF20,"")) | BM20: =IF(AH20<>"",AH20,"") | BN20: =IF(AJ20<>"",AJ20,"") | BO20: =IF($BP20<>"",MAX(BO$18:BO19)+1,"") | BP20: =IF(BK20<>"", BI20,"") | BQ20: =IF(BL20<>"", BJ20,"") | BR20: =IF(BJ20<>"", BK20,"") | BS20: =IF(BK20<>"", BL20,"") | BT20: =IF(BK20<>"", BM20,"") | BU20: =IF(BK20<>"", BN20,"") | BV20: 2 | BW20: =VLOOKUP($BV20,$BO$19:$BR$28,2,FALSE) -> #N/A | BX20: =VLOOKUP($BV20,$BO$19:$BU$28,3,FALSE) -> #N/A | BY20: =VLOOKUP($BV20,$BO$19:$BU$28,4,FALSE) -> #N/A | BZ20: =VLOOKUP($BV20,$BO$19:$BU$28,5,FALSE) -> #N/A | CA20: =VLOOKUP($BV20,$BO$19:$BU$28,6,FALSE) -> #N/A | CB20: =VLOOKUP($BV20,$BO$19:$BU$28,7,FALSE) -> #N/A | CH20: =IF(ISNA(BD20),"",BD20)
AM21: =IF($AN21<>"",MAX(AM$18:AM20)+1,"") | AN21: =IF(AP21=0,"",IF(ISNA(AP21),"",IF($I21<>"",G21,""))) | AO21: =IF(AP21=0,"",IF(ISNA(AP21),"",IF($I21<>"",I21,""))) | AP21: =IF($I21<>"",J21,"") | AQ21: =IF($I21<>"",L21,"") | AR21: =IF($I21<>"",O21,"") | AS21: =IF($I21<>"",Q21,"") | AT21: =IF($I21<>"",T21,"") | AU21: =IF($I21<>"",X21,"") | AV21: =IF($I21<>"",Z21,"") | AW21: 3 | AX21: =VLOOKUP($AW21,$AM$19:$AV$28,2,FALSE) -> #N/A | AY21: =VLOOKUP($AW21,$AM$19:$AV$28,3,FALSE) -> #N/A | AZ21: =VLOOKUP($AW21,$AM$19:$AV$28,4,FALSE) -> #N/A | BA21: =VLOOKUP($AW21,$AM$19:$AV$28,5,FALSE) -> #N/A | BB21: =VLOOKUP($AW21,$AM$19:$AV$28,6,FALSE) -> #N/A | BC21: =VLOOKUP($AW21,$AM$19:$AV$28,7,FALSE) -> #N/A | BD21: =VLOOKUP($AW21,$AM$19:$AV$28,8,FALSE) -> #N/A | BE21: =VLOOKUP($AW21,$AM$19:$AV$28,9,FALSE) -> #N/A | BF21: =VLOOKUP($AW21,$AM$19:$AV$28,10,FALSE) -> #N/A | BH21: =IF($BI21<>"",MAX(BH$18:BH20)+1,"") | BI21: =IF($I21<>"",G21,"") | BJ21: =IF(ISNA($AB21<>""),"",$I21) -> 0 | BK21: =IF(AB21=0,"",IF(ISNA(AB21),"",IF($AB21<>"",AB21,""))) | BL21: =IF(ISNA(AB21),"",IF($AB21<>"",AF21,"")) | BM21: =IF(AH21<>"",AH21,"") | BN21: =IF(AJ21<>"",AJ21,"") | BO21: =IF($BP21<>"",MAX(BO$18:BO20)+1,"") | BP21: =IF(BK21<>"", BI21,"") | BQ21: =IF(BL21<>"", BJ21,"") | BR21: =IF(BJ21<>"", BK21,"") | BS21: =IF(BK21<>"", BL21,"") | BT21: =IF(BK21<>"", BM21,"") | BU21: =IF(BK21<>"", BN21,"") | BV21: 3 | BW21: =VLOOKUP($BV21,$BO$19:$BR$28,2,FALSE) -> #N/A | BX21: =VLOOKUP($BV21,$BO$19:$BU$28,3,FALSE) -> #N/A | BY21: =VLOOKUP($BV21,$BO$19:$BU$28,4,FALSE) -> #N/A | BZ21: =VLOOKUP($BV21,$BO$19:$BU$28,5,FALSE) -> #N/A | CA21: =VLOOKUP($BV21,$BO$19:$BU$28,6,FALSE) -> #N/A | CB21: =VLOOKUP($BV21,$BO$19:$BU$28,7,FALSE) -> #N/A | CH21: =IF(ISNA(BD21),"",BD21)
AM22: =IF($AN22<>"",MAX(AM$18:AM21)+1,"") | AN22: =IF(AP22=0,"",IF(ISNA(AP22),"",IF($I22<>"",G22,""))) | AO22: =IF(AP22=0,"",IF(ISNA(AP22),"",IF($I22<>"",I22,""))) | AP22: =IF($I22<>"",J22,"") | AQ22: =IF($I22<>"",L22,"") | AR22: =IF($I22<>"",O22,"") | AS22: =IF($I22<>"",Q22,"") | AT22: =IF($I22<>"",T22,"") | AU22: =IF($I22<>"",X22,"") | AV22: =IF($I22<>"",Z22,"") | AW22: 4 | AX22: =VLOOKUP($AW22,$AM$19:$AV$28,2,FALSE) -> #N/A | AY22: =VLOOKUP($AW22,$AM$19:$AV$28,3,FALSE) -> #N/A | AZ22: =VLOOKUP($AW22,$AM$19:$AV$28,4,FALSE) -> #N/A | BA22: =VLOOKUP($AW22,$AM$19:$AV$28,5,FALSE) -> #N/A | BB22: =VLOOKUP($AW22,$AM$19:$AV$28,6,FALSE) -> #N/A | BC22: =VLOOKUP($AW22,$AM$19:$AV$28,7,FALSE) -> #N/A | BD22: =VLOOKUP($AW22,$AM$19:$AV$28,8,FALSE) -> #N/A | BE22: =VLOOKUP($AW22,$AM$19:$AV$28,9,FALSE) -> #N/A | BF22: =VLOOKUP($AW22,$AM$19:$AV$28,10,FALSE) -> #N/A | BH22: =IF($BI22<>"",MAX(BH$18:BH21)+1,"") | BI22: =IF($I22<>"",G22,"") | BJ22: =IF(ISNA($AB22<>""),"",$I22) -> 0 | BK22: =IF(AB22=0,"",IF(ISNA(AB22),"",IF($AB22<>"",AB22,""))) | BL22: =IF(ISNA(AB22),"",IF($AB22<>"",AF22,"")) | BM22: =IF(AH22<>"",AH22,"") | BN22: =IF(AJ22<>"",AJ22,"") | BO22: =IF($BP22<>"",MAX(BO$18:BO21)+1,"") | BP22: =IF(BK22<>"", BI22,"") | BQ22: =IF(BL22<>"", BJ22,"") | BR22: =IF(BJ22<>"", BK22,"") | BS22: =IF(BK22<>"", BL22,"") | BT22: =IF(BK22<>"", BM22,"") | BU22: =IF(BK22<>"", BN22,"") | BV22: 4 | BW22: =VLOOKUP($BV22,$BO$19:$BR$28,2,FALSE) -> #N/A | BX22: =VLOOKUP($BV22,$BO$19:$BU$28,3,FALSE) -> #N/A | BY22: =VLOOKUP($BV22,$BO$19:$BU$28,4,FALSE) -> #N/A | BZ22: =VLOOKUP($BV22,$BO$19:$BU$28,5,FALSE) -> #N/A | CA22: =VLOOKUP($BV22,$BO$19:$BU$28,6,FALSE) -> #N/A | CB22: =VLOOKUP($BV22,$BO$19:$BU$28,7,FALSE) -> #N/A | CH22: =IF(ISNA(BD22),"",BD22)
AM23: =IF($AN23<>"",MAX(AM$18:AM22)+1,"") | AN23: =IF(AP23=0,"",IF(ISNA(AP23),"",IF($I23<>"",G23,""))) | AO23: =IF(AP23=0,"",IF(ISNA(AP23),"",IF($I23<>"",I23,""))) | AP23: =IF($I23<>"",J23,"") | AQ23: =IF($I23<>"",L23,"") | AR23: =IF($I23<>"",O23,"") | AS23: =IF($I23<>"",Q23,"") | AT23: =IF($I23<>"",T23,"") | AU23: =IF($I23<>"",X23,"") | AV23: =IF($I23<>"",Z23,"") | AW23: 5 | AX23: =VLOOKUP($AW23,$AM$19:$AV$28,2,FALSE) -> #N/A | AY23: =VLOOKUP($AW23,$AM$19:$AV$28,3,FALSE) -> #N/A | AZ23: =VLOOKUP($AW23,$AM$19:$AV$28,4,FALSE) -> #N/A | BA23: =VLOOKUP($AW23,$AM$19:$AV$28,5,FALSE) -> #N/A | BB23: =VLOOKUP($AW23,$AM$19:$AV$28,6,FALSE) -> #N/A | BC23: =VLOOKUP($AW23,$AM$19:$AV$28,7,FALSE) -> #N/A | BD23: =VLOOKUP($AW23,$AM$19:$AV$28,8,FALSE) -> #N/A | BE23: =VLOOKUP($AW23,$AM$19:$AV$28,9,FALSE) -> #N/A | BF23: =VLOOKUP($AW23,$AM$19:$AV$28,10,FALSE) -> #N/A | BH23: =IF($BI23<>"",MAX(BH$18:BH22)+1,"") | BI23: =IF($I23<>"",G23,"") | BJ23: =IF(ISNA($AB23<>""),"",$I23) -> 0 | BK23: =IF(AB23=0,"",IF(ISNA(AB23),"",IF($AB23<>"",AB23,""))) | BL23: =IF(ISNA(AB23),"",IF($AB23<>"",AF23,"")) | BM23: =IF(AH23<>"",AH23,"") | BN23: =IF(AJ23<>"",AJ23,"") | BO23: =IF($BP23<>"",MAX(BO$18:BO22)+1,"") | BP23: =IF(BK23<>"", BI23,"") | BQ23: =IF(BL23<>"", BJ23,"") | BR23: =IF(BJ23<>"", BK23,"") | BS23: =IF(BK23<>"", BL23,"") | BT23: =IF(BK23<>"", BM23,"") | BU23: =IF(BK23<>"", BN23,"") | BV23: 5 | BW23: =VLOOKUP($BV23,$BO$19:$BR$28,2,FALSE) -> #N/A | BX23: =VLOOKUP($BV23,$BO$19:$BU$28,3,FALSE) -> #N/A | BY23: =VLOOKUP($BV23,$BO$19:$BU$28,4,FALSE) -> #N/A | BZ23: =VLOOKUP($BV23,$BO$19:$BU$28,5,FALSE) -> #N/A | CA23: =VLOOKUP($BV23,$BO$19:$BU$28,6,FALSE) -> #N/A | CB23: =VLOOKUP($BV23,$BO$19:$BU$28,7,FALSE) -> #N/A | CH23: =IF(ISNA(BD23),"",BD23)
AM24: =IF($AN24<>"",MAX(AM$18:AM23)+1,"") | AN24: =IF(AP24=0,"",IF(ISNA(AP24),"",IF($I24<>"",G24,""))) | AO24: =IF(AP24=0,"",IF(ISNA(AP24),"",IF($I24<>"",I24,""))) | AP24: =IF($I24<>"",J24,"") | AQ24: =IF($I24<>"",L24,"") | AR24: =IF($I24<>"",O24,"") | AS24: =IF($I24<>"",Q24,"") | AT24: =IF($I24<>"",T24,"") | AU24: =IF($I24<>"",X24,"") | AV24: =IF($I24<>"",Z24,"") | AW24: 6 | AX24: =VLOOKUP($AW24,$AM$19:$AV$28,2,FALSE) -> #N/A | AY24: =VLOOKUP($AW24,$AM$19:$AV$28,3,FALSE) -> #N/A | AZ24: =VLOOKUP($AW24,$AM$19:$AV$28,4,FALSE) -> #N/A | BA24: =VLOOKUP($AW24,$AM$19:$AV$28,5,FALSE) -> #N/A | BB24: =VLOOKUP($AW24,$AM$19:$AV$28,6,FALSE) -> #N/A | BC24: =VLOOKUP($AW24,$AM$19:$AV$28,7,FALSE) -> #N/A | BD24: =VLOOKUP($AW24,$AM$19:$AV$28,8,FALSE) -> #N/A | BE24: =VLOOKUP($AW24,$AM$19:$AV$28,9,FALSE) -> #N/A | BF24: =VLOOKUP($AW24,$AM$19:$AV$28,10,FALSE) -> #N/A | BH24: =IF($BI24<>"",MAX(BH$18:BH23)+1,"") | BI24: =IF($I24<>"",G24,"") | BJ24: =IF(ISNA($AB24<>""),"",$I24) -> 0 | BK24: =IF(AB24=0,"",IF(ISNA(AB24),"",IF($AB24<>"",AB24,""))) | BL24: =IF(ISNA(AB24),"",IF($AB24<>"",AF24,"")) | BM24: =IF(AH24<>"",AH24,"") | BN24: =IF(AJ24<>"",AJ24,"") | BO24: =IF($BP24<>"",MAX(BO$18:BO23)+1,"") | BP24: =IF(BK24<>"", BI24,"") | BQ24: =IF(BL24<>"", BJ24,"") | BR24: =IF(BJ24<>"", BK24,"") | BS24: =IF(BK24<>"", BL24,"") | BT24: =IF(BK24<>"", BM24,"") | BU24: =IF(BK24<>"", BN24,"") | BV24: 6 | BW24: =VLOOKUP($BV24,$BO$19:$BR$28,2,FALSE) -> #N/A | BX24: =VLOOKUP($BV24,$BO$19:$BU$28,3,FALSE) -> #N/A | BY24: =VLOOKUP($BV24,$BO$19:$BU$28,4,FALSE) -> #N/A | BZ24: =VLOOKUP($BV24,$BO$19:$BU$28,5,FALSE) -> #N/A | CA24: =VLOOKUP($BV24,$BO$19:$BU$28,6,FALSE) -> #N/A | CB24: =VLOOKUP($BV24,$BO$19:$BU$28,7,FALSE) -> #N/A | CH24: =IF(ISNA(BD24),"",BD24)
AM25: =IF($AN25<>"",MAX(AM$18:AM24)+1,"") | AN25: =IF(AP25=0,"",IF(ISNA(AP25),"",IF($I25<>"",G25,""))) | AO25: =IF(AP25=0,"",IF(ISNA(AP25),"",IF($I25<>"",I25,""))) | AP25: =IF($I25<>"",J25,"") | AQ25: =IF($I25<>"",L25,"") | AR25: =IF($I25<>"",O25,"") | AS25: =IF($I25<>"",Q25,"") | AT25: =IF($I25<>"",T25,"") | AU25: =IF($I25<>"",X25,"") | AV25: =IF($I25<>"",Z25,"") | AW25: 7 | AX25: =VLOOKUP($AW25,$AM$19:$AV$28,2,FALSE) -> #N/A | AY25: =VLOOKUP($AW25,$AM$19:$AV$28,3,FALSE) -> #N/A | AZ25: =VLOOKUP($AW25,$AM$19:$AV$28,4,FALSE) -> #N/A | BA25: =VLOOKUP($AW25,$AM$19:$AV$28,5,FALSE) -> #N/A | BB25: =VLOOKUP($AW25,$AM$19:$AV$28,6,FALSE) -> #N/A | BC25: =VLOOKUP($AW25,$AM$19:$AV$28,7,FALSE) -> #N/A | BD25: =VLOOKUP($AW25,$AM$19:$AV$28,8,FALSE) -> #N/A | BE25: =VLOOKUP($AW25,$AM$19:$AV$28,9,FALSE) -> #N/A | BF25: =VLOOKUP($AW25,$AM$19:$AV$28,10,FALSE) -> #N/A | BH25: =IF($BI25<>"",MAX(BH$18:BH24)+1,"") | BI25: =IF($I25<>"",G25,"") | BJ25: =IF(ISNA($AB25<>""),"",$I25) -> 0 | BK25: =IF(AB25=0,"",IF(ISNA(AB25),"",IF($AB25<>"",AB25,""))) | BL25: =IF(ISNA(AB25),"",IF($AB25<>"",AF25,"")) | BM25: =IF(AH25<>"",AH25,"") | BN25: =IF(AJ25<>"",AJ25,"") | BO25: =IF($BP25<>"",MAX(BO$18:BO24)+1,"") | BP25: =IF(BK25<>"", BI25,"") | BQ25: =IF(BL25<>"", BJ25,"") | BR25: =IF(BJ25<>"", BK25,"") | BS25: =IF(BK25<>"", BL25,"") | BT25: =IF(BK25<>"", BM25,"") | BU25: =IF(BK25<>"", BN25,"") | BV25: 7 | BW25: =VLOOKUP($BV25,$BO$19:$BR$28,2,FALSE) -> #N/A | BX25: =VLOOKUP($BV25,$BO$19:$BU$28,3,FALSE) -> #N/A | BY25: =VLOOKUP($BV25,$BO$19:$BU$28,4,FALSE) -> #N/A | BZ25: =VLOOKUP($BV25,$BO$19:$BU$28,5,FALSE) -> #N/A | CA25: =VLOOKUP($BV25,$BO$19:$BU$28,6,FALSE) -> #N/A | CB25: =VLOOKUP($BV25,$BO$19:$BU$28,7,FALSE) -> #N/A | CH25: =IF(ISNA(BD25),"",BD25)
AM26: =IF($AN26<>"",MAX(AM$18:AM25)+1,"") | AN26: =IF(AP26=0,"",IF(ISNA(AP26),"",IF($I26<>"",G26,""))) | AO26: =IF(AP26=0,"",IF(ISNA(AP26),"",IF($I26<>"",I26,""))) | AP26: =IF($I26<>"",J26,"") | AQ26: =IF($I26<>"",L26,"") | AR26: =IF($I26<>"",O26,"") | AS26: =IF($I26<>"",Q26,"") | AT26: =IF($I26<>"",T26,"") | AU26: =IF($I26<>"",X26,"") | AV26: =IF($I26<>"",Z26,"") | AW26: 8 | AX26: =VLOOKUP($AW26,$AM$19:$AV$28,2,FALSE) -> #N/A | AY26: =VLOOKUP($AW26,$AM$19:$AV$28,3,FALSE) -> #N/A | AZ26: =VLOOKUP($AW26,$AM$19:$AV$28,4,FALSE) -> #N/A | BA26: =VLOOKUP($AW26,$AM$19:$AV$28,5,FALSE) -> #N/A | BB26: =VLOOKUP($AW26,$AM$19:$AV$28,6,FALSE) -> #N/A | BC26: =VLOOKUP($AW26,$AM$19:$AV$28,7,FALSE) -> #N/A | BD26: =VLOOKUP($AW26,$AM$19:$AV$28,8,FALSE) -> #N/A | BE26: =VLOOKUP($AW26,$AM$19:$AV$28,9,FALSE) -> #N/A | BF26: =VLOOKUP($AW26,$AM$19:$AV$28,10,FALSE) -> #N/A | BH26: =IF($BI26<>"",MAX(BH$18:BH25)+1,"") | BI26: =IF($I26<>"",G26,"") | BJ26: =IF(ISNA($AB26<>""),"",$I26) -> 0 | BK26: =IF(AB26=0,"",IF(ISNA(AB26),"",IF($AB26<>"",AB26,""))) | BL26: =IF(ISNA(AB26),"",IF($AB26<>"",AF26,"")) | BM26: =IF(AH26<>"",AH26,"") | BN26: =IF(AJ26<>"",AJ26,"") | BO26: =IF($BP26<>"",MAX(BO$18:BO25)+1,"") | BP26: =IF(BK26<>"", BI26,"") | BQ26: =IF(BL26<>"", BJ26,"") | BR26: =IF(BJ26<>"", BK26,"") | BS26: =IF(BK26<>"", BL26,"") | BT26: =IF(BK26<>"", BM26,"") | BU26: =IF(BK26<>"", BN26,"") | BV26: 8 | BW26: =VLOOKUP($BV26,$BO$19:$BR$28,2,FALSE) -> #N/A | BX26: =VLOOKUP($BV26,$BO$19:$BU$28,3,FALSE) -> #N/A | BY26: =VLOOKUP($BV26,$BO$19:$BU$28,4,FALSE) -> #N/A | BZ26: =VLOOKUP($BV26,$BO$19:$BU$28,5,FALSE) -> #N/A | CA26: =VLOOKUP($BV26,$BO$19:$BU$28,6,FALSE) -> #N/A | CB26: =VLOOKUP($BV26,$BO$19:$BU$28,7,FALSE) -> #N/A | CH26: =IF(ISNA(BD26),"",BD26)
AM27: =IF($AN27<>"",MAX(AM$18:AM26)+1,"") | AN27: =IF(AP27=0,"",IF(ISNA(AP27),"",IF($I27<>"",G27,""))) | AO27: =IF(AP27=0,"",IF(ISNA(AP27),"",IF($I27<>"",I27,""))) | AP27: =IF($I27<>"",J27,"") | AQ27: =IF($I27<>"",L27,"") | AR27: =IF($I27<>"",O27,"") | AS27: =IF($I27<>"",Q27,"") | AT27: =IF($I27<>"",T27,"") | AU27: =IF($I27<>"",X27,"") | AV27: =IF($I27<>"",Z27,"") | AW27: 9 | AX27: =VLOOKUP($AW27,$AM$19:$AV$28,2,FALSE) -> #N/A | AY27: =VLOOKUP($AW27,$AM$19:$AV$28,3,FALSE) -> #N/A | AZ27: =VLOOKUP($AW27,$AM$19:$AV$28,4,FALSE) -> #N/A | BA27: =VLOOKUP($AW27,$AM$19:$AV$28,5,FALSE) -> #N/A | BB27: =VLOOKUP($AW27,$AM$19:$AV$28,6,FALSE) -> #N/A | BC27: =VLOOKUP($AW27,$AM$19:$AV$28,7,FALSE) -> #N/A | BD27: =VLOOKUP($AW27,$AM$19:$AV$28,8,FALSE) -> #N/A | BE27: =VLOOKUP($AW27,$AM$19:$AV$28,9,FALSE) -> #N/A | BF27: =VLOOKUP($AW27,$AM$19:$AV$28,10,FALSE) -> #N/A | BH27: =IF($BI27<>"",MAX(BH$18:BH26)+1,"") | BI27: =IF($I27<>"",G27,"") | BJ27: =IF(ISNA($AB27<>""),"",$I27) -> 0 | BK27: =IF(AB27=0,"",IF(ISNA(AB27),"",IF($AB27<>"",AB27,""))) | BL27: =IF(ISNA(AB27),"",IF($AB27<>"",AF27,"")) | BM27: =IF(AH27<>"",AH27,"") | BN27: =IF(AJ27<>"",AJ27,"") | BO27: =IF($BP27<>"",MAX(BO$18:BO26)+1,"") | BP27: =IF(BK27<>"", BI27,"") | BQ27: =IF(BL27<>"", BJ27,"") | BR27: =IF(BJ27<>"", BK27,"") | BS27: =IF(BK27<>"", BL27,"") | BT27: =IF(BK27<>"", BM27,"") | BU27: =IF(BK27<>"", BN27,"") | BV27: 9 | BW27: =VLOOKUP($BV27,$BO$19:$BR$28,2,FALSE) -> #N/A | BX27: =VLOOKUP($BV27,$BO$19:$BU$28,3,FALSE) -> #N/A | BY27: =VLOOKUP($BV27,$BO$19:$BU$28,4,FALSE) -> #N/A | BZ27: =VLOOKUP($BV27,$BO$19:$BU$28,5,FALSE) -> #N/A | CA27: =VLOOKUP($BV27,$BO$19:$BU$28,6,FALSE) -> #N/A | CB27: =VLOOKUP($BV27,$BO$19:$BU$28,7,FALSE) -> #N/A | CH27: =IF(ISNA(BD27),"",BD27)
AM28: =IF($AN28<>"",MAX(AM$18:AM27)+1,"") | AN28: =IF(AP28=0,"",IF(ISNA(AP28),"",IF($I28<>"",G28,""))) | AO28: =IF(AP28=0,"",IF(ISNA(AP28),"",IF($I28<>"",I28,""))) | AP28: =IF($I28<>"",J28,"") | AQ28: =IF($I28<>"",L28,"") | AR28: =IF($I28<>"",O28,"") | AS28: =IF($I28<>"",Q28,"") | AT28: =IF($I28<>"",T28,"") | AU28: =IF($I28<>"",X28,"") | AV28: =IF($I28<>"",Z28,"") | AW28: 10 | AX28: =VLOOKUP($AW28,$AM$19:$AV$28,2,FALSE) -> #N/A | AY28: =VLOOKUP($AW28,$AM$19:$AV$28,3,FALSE) -> #N/A | AZ28: =VLOOKUP($AW28,$AM$19:$AV$28,4,FALSE) -> #N/A | BA28: =VLOOKUP($AW28,$AM$19:$AV$28,5,FALSE) -> #N/A | BB28: =VLOOKUP($AW28,$AM$19:$AV$28,6,FALSE) -> #N/A | BC28: =VLOOKUP($AW28,$AM$19:$AV$28,7,FALSE) -> #N/A | BD28: =VLOOKUP($AW28,$AM$19:$AV$28,8,FALSE) -> #N/A | BE28: =VLOOKUP($AW28,$AM$19:$AV$28,9,FALSE) -> #N/A | BF28: =VLOOKUP($AW28,$AM$19:$AV$28,10,FALSE) -> #N/A | BH28: =IF($BI28<>"",MAX(BH$18:BH27)+1,"") | BI28: =IF($I28<>"",G28,"") | BJ28: =IF(ISNA($AB28<>""),"",$I28) -> 0 | BK28: =IF(AB28=0,"",IF(ISNA(AB28),"",IF($AB28<>"",AB28,""))) | BL28: =IF(ISNA(AB28),"",IF($AB28<>"",AF28,"")) | BM28: =IF(AH28<>"",AH28,"") | BN28: =IF(AJ28<>"",AJ28,"") | BO28: =IF($BP28<>"",MAX(BO$18:BO27)+1,"") | BP28: =IF(BK28<>"", BI28,"") | BQ28: =IF(BL28<>"", BJ28,"") | BR28: =IF(BJ28<>"", BK28,"") | BS28: =IF(BK28<>"", BL28,"") | BT28: =IF(BK28<>"", BM28,"") | BU28: =IF(BK28<>"", BN28,"") | BV28: 10 | BW28: =VLOOKUP($BV28,$BO$19:$BR$28,2,FALSE) -> #N/A | BX28: =VLOOKUP($BV28,$BO$19:$BU$28,3,FALSE) -> #N/A | BY28: =VLOOKUP($BV28,$BO$19:$BU$28,4,FALSE) -> #N/A | BZ28: =VLOOKUP($BV28,$BO$19:$BU$28,5,FALSE) -> #N/A | CA28: =VLOOKUP($BV28,$BO$19:$BU$28,6,FALSE) -> #N/A | CB28: =VLOOKUP($BV28,$BO$19:$BU$28,7,FALSE) -> #N/A | CH28: =IF(ISNA(BD28),"",BD28)
D30: =INDIRECT('D1-D2-D3'!$J$4&"!C169") -> Simulation | G30: =INDIRECT('D1-D2-D3'!$J$4&"!C158") -> Verification of the causes
G31: =INDIRECT('D1-D2-D3'!$J$4&"!C170") -> In order to confirm root causes defect must be reproduced by creating same condition if possible | AA31: =INDIRECT('D1-D2-D3'!$J$4&"!C171") -> Simulation possible ? | AC31: =INDIRECT('D1-D2-D3'!$J$4&"!C83") -> Responsible | AI31: =INDIRECT('D1-D2-D3'!$J$4&"!C69") -> Date
H33: =IF(AB31=DropDown!N11,INDIRECT('D1-D2-D3'!$J$4&"!C172"),INDIRECT('D1-D2-D3'!$J$4&"!C173")) -> Reason why simulation is not possible:
H36: =INDIRECT('D1-D2-D3'!$J$4&"!C174") -> Does the reproduced defect match the given fault ? | L36: =IF(K36=DropDown!N11,INDIRECT('D1-D2-D3'!$J$4&"!C175"),INDIRECT('D1-D2-D3'!$J$4&"!C176")) -> → Root cause not verified → Go back to D4 to find the right root cause
D40: =INDIRECT('D1-D2-D3'!$J$4&"!C269") -> Technical consideration factors | J40: =INDIRECT('D1-D2-D3'!$J$4&"!C150") -> 5-Why-Analysis | X40: =INDIRECT('D1-D2-D3'!$J$4&"!C157") -> Fault category | Z40: =INDIRECT('D1-D2-D3'!$J$4&"!C158") -> Verification of the causes | AB40: =INDIRECT('D1-D2-D3'!$J$4&"!C163") -> Action Plan
J41: =INDIRECT('D1-D2-D3'!$J$4&"!C138") -> Systemic consideration | AM41: SYSTEMIC - ROOT CAUSE AND 5WHYs | BH41: ACTION PLAN - SYST
AX42: FINAL CAUSE + 5WHys SYSTEM for 8D | BW42: SVERWEIS: CAUSE + ACTIONS
D43: =INDIRECT('D1-D2-D3'!$J$4&"!C149") -> Factors identification | I43: =INDIRECT('D1-D2-D3'!$J$4&"!C151") -> Influent factors | J43: =INDIRECT('D1-D2-D3'!$J$4&"!C152") -> Why 1 | L43: =INDIRECT('D1-D2-D3'!$J$4&"!C153") -> Why 2 | O43: =INDIRECT('D1-D2-D3'!$J$4&"!C154") -> Why 3 | Q43: =INDIRECT('D1-D2-D3'!$J$4&"!C155") -> Why 4 | T43: =INDIRECT('D1-D2-D3'!$J$4&"!C156") -> Why 5 | X43: =INDIRECT('D1-D2-D3'!$J$4&"!C159") -> Category | Z43: =INDIRECT('D1-D2-D3'!$J$4&"!C160") -> Method of cause verification | AB43: =INDIRECT('D1-D2-D3'!$J$4&"!C164") -> Corrective Action | AE43: =INDIRECT('D1-D2-D3'!$J$4&"!C165") -> Pic. No. | AF43: =INDIRECT('D1-D2-D3'!$J$4&"!C83") -> Responsible | AH43: =INDIRECT('D1-D2-D3'!$J$4&"!C166") -> Target Date | AJ43: =INDIRECT('D1-D2-D3'!$J$4&"!C84") -> Impl. Date | AM43: 0 | AX43: SVERWEIS - FOR 8D | BH43: 0 | BI43: occ | BJ43: fault | BK43: action | BL43: respo | BM43: target | BN43: implem | BO43: 0 | BW43: FINAL | BY43: respons | BZ43: target | CA43: Target | CB43: impl
D44: =INDIRECT('D1-D2-D3'!$J$4&"!C149")&"/"& INDIRECT('D1-D2-D3'!$J$4&"!C151") -> Factors identification/Influent factors | AM44: =IF($AN$44<>"",$AM$43+1,"") | AN44: =IF(AP44=0,"",IF(ISNA(AP44),"",IF($I44<>"",G44,""))) | AO44: =IF(AP44=0,"",IF(ISNA(AP44),"",IF($I44<>"",I44,""))) | AP44: =IF($I44<>"",J44,"") | AQ44: =IF($I44<>"",L44,"") | AR44: =IF($I44<>"",O44,"") | AS44: =IF($I44<>"",Q44,"") | AT44: =IF($I44<>"",T44,"") | AU44: =IF($I44<>"",X44,"") | AV44: =IF($I44<>"",Z44,"") | AW44: 1 | AX44: =VLOOKUP($AW44,$AM$44:$AV$53,2,FALSE) -> #N/A | AY44: =VLOOKUP($AW44,$AM$44:$AV$53,3,FALSE) -> #N/A | AZ44: =VLOOKUP($AW44,$AM$44:$AV$53,4,FALSE) -> #N/A | BA44: =VLOOKUP($AW44,$AM$44:$AV$53,5,FALSE) -> #N/A | BB44: =VLOOKUP($AW44,$AM$44:$AV$53,6,FALSE) -> #N/A | BC44: =VLOOKUP($AW44,$AM$44:$AV$53,7,FALSE) -> #N/A | BD44: =VLOOKUP($AW44,$AM$44:$AV$53,8,FALSE) -> #N/A | BE44: =VLOOKUP($AW44,$AM$44:$AV$53,9,FALSE) -> #N/A | BF44: =VLOOKUP($AW44,$AM$44:$AV$53,10,FALSE) -> #N/A | BH44: =IF($BI44<>"",BH43+1,"") | BI44: =IF($I44<>"",G44,"") | BJ44: =IF($AB44<>"",I44,"") | BK44: =IF(AB44=0,"",IF(ISNA(AB44),"",IF($AB44<>"",AB44,""))) | BL44: =IF(ISNA(AB44),"",IF($AB44<>"",AF44,"")) | BM44: =IF(AH44<>"",AH44,"") | BN44: =IF(AJ44<>"",AJ44,"") | BO44: =IF($BP44<>"",BO43+1,"") | BP44: =IF(BK44<>"", BI44,"") | BQ44: =IF(BL44<>"", BJ44,"") | BR44: =IF(BJ44<>"", BK44,"") | BS44: =IF(BK44<>"", BL44,"") | BT44: =IF(BK44<>"", BM44,"") | BU44: =IF(BK44<>"", BN44,"") | BV44: 1 | BW44: =VLOOKUP($BV44,$BO$44:$BU$53,2,FALSE) -> #N/A | BX44: =VLOOKUP($BV44,$BO$44:$BU$53,3,FALSE) -> #N/A | BY44: =VLOOKUP($BV44,$BO$44:$BU$53,4,FALSE) -> #N/A | BZ44: =VLOOKUP($BV44,$BO$44:$BU$53,5,FALSE) -> #N/A | CA44: =VLOOKUP($BV44,$BO$44:$BU$53,6,FALSE) -> #N/A | CB44: =VLOOKUP($BV44,$BO$44:$BU$53,7,FALSE) -> #N/A
AM45: =IF($AN45<>"",MAX(AM$43:AM44)+1,"") | AN45: =IF(AP45=0,"",IF(ISNA(AP45),"",IF($I45<>"",G45,""))) | AO45: =IF(AP45=0,"",IF(ISNA(AP45),"",IF($I45<>"",I45,""))) | AP45: =IF($I45<>"",J45,"") | AQ45: =IF($I45<>"",L45,"") | AR45: =IF($I45<>"",O45,"") | AS45: =IF($I45<>"",Q45,"") | AT45: =IF($I45<>"",T45,"") | AU45: =IF($I45<>"",X45,"") | AV45: =IF($I45<>"",Z45,"") | AW45: 2 | AX45: =VLOOKUP($AW45,$AM$44:$AV$53,2,FALSE) -> #N/A | AY45: =VLOOKUP($AW45,$AM$44:$AV$53,3,FALSE) -> #N/A | AZ45: =VLOOKUP($AW45,$AM$44:$AV$53,4,FALSE) -> #N/A | BA45: =VLOOKUP($AW45,$AM$44:$AV$53,5,FALSE) -> #N/A | BB45: =VLOOKUP($AW45,$AM$44:$AV$53,6,FALSE) -> #N/A | BC45: =VLOOKUP($AW45,$AM$44:$AV$53,7,FALSE) -> #N/A | BD45: =VLOOKUP($AW45,$AM$44:$AV$53,8,FALSE) -> #N/A | BE45: =VLOOKUP($AW45,$AM$44:$AV$53,9,FALSE) -> #N/A | BF45: =VLOOKUP($AW45,$AM$44:$AV$53,10,FALSE) -> #N/A | BH45: =IF($BI45<>"",MAX(BH$43:BH44)+1,"") | BI45: =IF($I45<>"",G45,"") | BJ45: =IF($AB45<>"",I45,"") | BK45: =IF(AB45=0,"",IF(ISNA(AB45),"",IF($AB45<>"",AB45,""))) | BL45: =IF(ISNA(AB45),"",IF($AB45<>"",AF45,"")) | BM45: =IF(AH45<>"",AH45,"") | BN45: =IF(AJ45<>"",AJ45,"") | BO45: =IF($BP45<>"",MAX(BO$43:BO44)+1,"") | BP45: =IF(BK45<>"", BI45,"") | BQ45: =IF(BL45<>"", BJ45,"") | BR45: =IF(BJ45<>"", BK45,"") | BS45: =IF(BK45<>"", BL45,"") | BT45: =IF(BK45<>"", BM45,"") | BU45: =IF(BK45<>"", BN45,"") | BV45: 2 | BW45: =VLOOKUP($BV45,$BO$44:$BU$53,2,FALSE) -> #N/A | BX45: =VLOOKUP($BV45,$BO$44:$BU$53,3,FALSE) -> #N/A | BY45: =VLOOKUP($BV45,$BO$44:$BU$53,4,FALSE) -> #N/A | BZ45: =VLOOKUP($BV45,$BO$44:$BU$53,5,FALSE) -> #N/A | CA45: =VLOOKUP($BV45,$BO$44:$BU$53,6,FALSE) -> #N/A | CB45: =VLOOKUP($BV45,$BO$44:$BU$53,7,FALSE) -> #N/A
AM46: =IF($AN46<>"",MAX(AM$43:AM45)+1,"") | AN46: =IF(AP46=0,"",IF(ISNA(AP46),"",IF($I46<>"",G46,""))) | AO46: =IF(AP46=0,"",IF(ISNA(AP46),"",IF($I46<>"",I46,""))) | AP46: =IF($I46<>"",J46,"") | AQ46: =IF($I46<>"",L46,"") | AR46: =IF($I46<>"",O46,"") | AS46: =IF($I46<>"",Q46,"") | AT46: =IF($I46<>"",T46,"") | AU46: =IF($I46<>"",X46,"") | AV46: =IF($I46<>"",Z46,"") | AW46: 3 | AX46: =VLOOKUP($AW46,$AM$44:$AV$53,2,FALSE) -> #N/A | AY46: =VLOOKUP($AW46,$AM$44:$AV$53,3,FALSE) -> #N/A | AZ46: =VLOOKUP($AW46,$AM$44:$AV$53,4,FALSE) -> #N/A | BA46: =VLOOKUP($AW46,$AM$44:$AV$53,5,FALSE) -> #N/A | BB46: =VLOOKUP($AW46,$AM$44:$AV$53,6,FALSE) -> #N/A | BC46: =VLOOKUP($AW46,$AM$44:$AV$53,7,FALSE) -> #N/A | BD46: =VLOOKUP($AW46,$AM$44:$AV$53,8,FALSE) -> #N/A | BE46: =VLOOKUP($AW46,$AM$44:$AV$53,9,FALSE) -> #N/A | BF46: =VLOOKUP($AW46,$AM$44:$AV$53,10,FALSE) -> #N/A | BH46: =IF($BI46<>"",MAX(BH$43:BH45)+1,"") | BI46: =IF($I46<>"",G46,"") | BJ46: =IF($AB46<>"",I46,"") | BK46: =IF(AB46=0,"",IF(ISNA(AB46),"",IF($AB46<>"",AB46,""))) | BL46: =IF(ISNA(AB46),"",IF($AB46<>"",AF46,"")) | BM46: =IF(AH46<>"",AH46,"") | BN46: =IF(AJ46<>"",AJ46,"") | BO46: =IF($BP46<>"",MAX(BO$43:BO45)+1,"") | BP46: =IF(BK46<>"", BI46,"") | BQ46: =IF(BL46<>"", BJ46,"") | BR46: =IF(BJ46<>"", BK46,"") | BS46: =IF(BK46<>"", BL46,"") | BT46: =IF(BK46<>"", BM46,"") | BU46: =IF(BK46<>"", BN46,"") | BV46: 3 | BW46: =VLOOKUP($BV46,$BO$44:$BU$53,2,FALSE) -> #N/A | BX46: =VLOOKUP($BV46,$BO$44:$BU$53,3,FALSE) -> #N/A | BY46: =VLOOKUP($BV46,$BO$44:$BU$53,4,FALSE) -> #N/A | BZ46: =VLOOKUP($BV46,$BO$44:$BU$53,5,FALSE) -> #N/A | CA46: =VLOOKUP($BV46,$BO$44:$BU$53,6,FALSE) -> #N/A | CB46: =VLOOKUP($BV46,$BO$44:$BU$53,7,FALSE) -> #N/A
AM47: =IF($AN47<>"",MAX(AM$43:AM46)+1,"") | AN47: =IF(AP47=0,"",IF(ISNA(AP47),"",IF($I47<>"",G47,""))) | AO47: =IF(AP47=0,"",IF(ISNA(AP47),"",IF($I47<>"",I47,""))) | AP47: =IF($I47<>"",J47,"") | AQ47: =IF($I47<>"",L47,"") | AR47: =IF($I47<>"",O47,"") | AS47: =IF($I47<>"",Q47,"") | AT47: =IF($I47<>"",T47,"") | AU47: =IF($I47<>"",X47,"") | AV47: =IF($I47<>"",Z47,"") | AW47: 4 | AX47: =VLOOKUP($AW47,$AM$44:$AV$53,2,FALSE) -> #N/A | AY47: =VLOOKUP($AW47,$AM$44:$AV$53,3,FALSE) -> #N/A | AZ47: =VLOOKUP($AW47,$AM$44:$AV$53,4,FALSE) -> #N/A | BA47: =VLOOKUP($AW47,$AM$44:$AV$53,5,FALSE) -> #N/A | BB47: =VLOOKUP($AW47,$AM$44:$AV$53,6,FALSE) -> #N/A | BC47: =VLOOKUP($AW47,$AM$44:$AV$53,7,FALSE) -> #N/A | BD47: =VLOOKUP($AW47,$AM$44:$AV$53,8,FALSE) -> #N/A | BE47: =VLOOKUP($AW47,$AM$44:$AV$53,9,FALSE) -> #N/A | BF47: =VLOOKUP($AW47,$AM$44:$AV$53,10,FALSE) -> #N/A | BH47: =IF($BI47<>"",MAX(BH$43:BH46)+1,"") | BI47: =IF($I47<>"",G47,"") | BJ47: =IF($AB47<>"",I47,"") | BK47: =IF(AB47=0,"",IF(ISNA(AB47),"",IF($AB47<>"",AB47,""))) | BL47: =IF(ISNA(AB47),"",IF($AB47<>"",AF47,"")) | BM47: =IF(AH47<>"",AH47,"") | BN47: =IF(AJ47<>"",AJ47,"") | BO47: =IF($BP47<>"",MAX(BO$43:BO46)+1,"") | BP47: =IF(BK47<>"", BI47,"") | BQ47: =IF(BL47<>"", BJ47,"") | BR47: =IF(BJ47<>"", BK47,"") | BS47: =IF(BK47<>"", BL47,"") | BT47: =IF(BK47<>"", BM47,"") | BU47: =IF(BK47<>"", BN47,"") | BV47: 4 | BW47: =VLOOKUP($BV47,$BO$44:$BU$53,2,FALSE) -> #N/A | BX47: =VLOOKUP($BV47,$BO$44:$BU$53,3,FALSE) -> #N/A | BY47: =VLOOKUP($BV47,$BO$44:$BU$53,4,FALSE) -> #N/A | BZ47: =VLOOKUP($BV47,$BO$44:$BU$53,5,FALSE) -> #N/A | CA47: =VLOOKUP($BV47,$BO$44:$BU$53,6,FALSE) -> #N/A | CB47: =VLOOKUP($BV47,$BO$44:$BU$53,7,FALSE) -> #N/A
AM48: =IF($AN48<>"",MAX(AM$43:AM47)+1,"") | AN48: =IF(AP48=0,"",IF(ISNA(AP48),"",IF($I48<>"",G48,""))) | AO48: =IF(AP48=0,"",IF(ISNA(AP48),"",IF($I48<>"",I48,""))) | AP48: =IF($I48<>"",J48,"") | AQ48: =IF($I48<>"",L48,"") | AR48: =IF($I48<>"",O48,"") | AS48: =IF($I48<>"",Q48,"") | AT48: =IF($I48<>"",T48,"") | AU48: =IF($I48<>"",X48,"") | AV48: =IF($I48<>"",Z48,"") | AW48: 9 | AX48: =VLOOKUP($AW48,$AM$44:$AV$53,2,FALSE) -> #N/A | AY48: =VLOOKUP($AW48,$AM$44:$AV$53,3,FALSE) -> #N/A | AZ48: =VLOOKUP($AW48,$AM$44:$AV$53,4,FALSE) -> #N/A | BA48: =VLOOKUP($AW48,$AM$44:$AV$53,5,FALSE) -> #N/A | BB48: =VLOOKUP($AW48,$AM$44:$AV$53,6,FALSE) -> #N/A | BC48: =VLOOKUP($AW48,$AM$44:$AV$53,7,FALSE) -> #N/A | BD48: =VLOOKUP($AW48,$AM$44:$AV$53,8,FALSE) -> #N/A | BE48: =VLOOKUP($AW48,$AM$44:$AV$53,9,FALSE) -> #N/A | BF48: =VLOOKUP($AW48,$AM$44:$AV$53,10,FALSE) -> #N/A | BH48: =IF($BI48<>"",MAX(BH$43:BH47)+1,"") | BI48: =IF($I48<>"",G48,"") | BJ48: =IF($AB48<>"",I48,"") | BK48: =IF(AB48=0,"",IF(ISNA(AB48),"",IF($AB48<>"",AB48,""))) | BL48: =IF(ISNA(AB48),"",IF($AB48<>"",AF48,"")) | BM48: =IF(AH48<>"",AH48,"") | BN48: =IF(AJ48<>"",AJ48,"") | BO48: =IF($BP48<>"",MAX(BO$43:BO47)+1,"") | BP48: =IF(BK48<>"", BI48,"") | BQ48: =IF(BL48<>"", BJ48,"") | BR48: =IF(BJ48<>"", BK48,"") | BS48: =IF(BK48<>"", BL48,"") | BT48: =IF(BK48<>"", BM48,"") | BU48: =IF(BK48<>"", BN48,"") | BV48: 5 | BW48: =VLOOKUP($BV48,$BO$44:$BU$53,2,FALSE) -> #N/A | BX48: =VLOOKUP($BV48,$BO$44:$BU$53,3,FALSE) -> #N/A | BY48: =VLOOKUP($BV48,$BO$44:$BU$53,4,FALSE) -> #N/A | BZ48: =VLOOKUP($BV48,$BO$44:$BU$53,5,FALSE) -> #N/A | CA48: =VLOOKUP($BV48,$BO$44:$BU$53,6,FALSE) -> #N/A | CB48: =VLOOKUP($BV48,$BO$44:$BU$53,7,FALSE) -> #N/A
AM49: =IF($AN49<>"",MAX(AM$43:AM48)+1,"") | AN49: =IF(AP49=0,"",IF(ISNA(AP49),"",IF($I49<>"",G49,""))) | AO49: =IF(AP49=0,"",IF(ISNA(AP49),"",IF($I49<>"",I49,""))) | AP49: =IF($I49<>"",J49,"") | AQ49: =IF($I49<>"",L49,"") | AR49: =IF($I49<>"",O49,"") | AS49: =IF($I49<>"",Q49,"") | AT49: =IF($I49<>"",T49,"") | AU49: =IF($I49<>"",X49,"") | AV49: =IF($I49<>"",Z49,"") | AW49: 6 | AX49: =VLOOKUP($AW49,$AM$44:$AV$53,2,FALSE) -> #N/A | AY49: =VLOOKUP($AW49,$AM$44:$AV$53,3,FALSE) -> #N/A | AZ49: =VLOOKUP($AW49,$AM$44:$AV$53,4,FALSE) -> #N/A | BA49: =VLOOKUP($AW49,$AM$44:$AV$53,5,FALSE) -> #N/A | BB49: =VLOOKUP($AW49,$AM$44:$AV$53,6,FALSE) -> #N/A | BC49: =VLOOKUP($AW49,$AM$44:$AV$53,7,FALSE) -> #N/A | BD49: =VLOOKUP($AW49,$AM$44:$AV$53,8,FALSE) -> #N/A | BE49: =VLOOKUP($AW49,$AM$44:$AV$53,9,FALSE) -> #N/A | BF49: =VLOOKUP($AW49,$AM$44:$AV$53,10,FALSE) -> #N/A | BH49: =IF($BI49<>"",MAX(BH$43:BH48)+1,"") | BI49: =IF($I49<>"",G49,"") | BJ49: =IF($AB49<>"",I49,"") | BK49: =IF(AB49=0,"",IF(ISNA(AB49),"",IF($AB49<>"",AB49,""))) | BL49: =IF(ISNA(AB49),"",IF($AB49<>"",AF49,"")) | BM49: =IF(AH49<>"",AH49,"") | BN49: =IF(AJ49<>"",AJ49,"") | BO49: =IF($BP49<>"",MAX(BO$43:BO48)+1,"") | BP49: =IF(BK49<>"", BI49,"") | BQ49: =IF(BL49<>"", BJ49,"") | BR49: =IF(BJ49<>"", BK49,"") | BS49: =IF(BK49<>"", BL49,"") | BT49: =IF(BK49<>"", BM49,"") | BU49: =IF(BK49<>"", BN49,"") | BV49: 6 | BW49: =VLOOKUP($BV49,$BO$44:$BU$53,2,FALSE) -> #N/A | BX49: =VLOOKUP($BV49,$BO$44:$BU$53,3,FALSE) -> #N/A | BY49: =VLOOKUP($BV49,$BO$44:$BU$53,4,FALSE) -> #N/A | BZ49: =VLOOKUP($BV49,$BO$44:$BU$53,5,FALSE) -> #N/A | CA49: =VLOOKUP($BV49,$BO$44:$BU$53,6,FALSE) -> #N/A | CB49: =VLOOKUP($BV49,$BO$44:$BU$53,7,FALSE) -> #N/A
AM50: =IF($AN50<>"",MAX(AM$43:AM49)+1,"") | AN50: =IF(AP50=0,"",IF(ISNA(AP50),"",IF($I50<>"",G50,""))) | AO50: =IF(AP50=0,"",IF(ISNA(AP50),"",IF($I50<>"",I50,""))) | AP50: =IF($I50<>"",J50,"") | AQ50: =IF($I50<>"",L50,"") | AR50: =IF($I50<>"",O50,"") | AS50: =IF($I50<>"",Q50,"") | AT50: =IF($I50<>"",T50,"") | AU50: =IF($I50<>"",X50,"") | AV50: =IF($I50<>"",Z50,"") | AW50: 7 | AX50: =VLOOKUP($AW50,$AM$44:$AV$53,2,FALSE) -> #N/A | AY50: =VLOOKUP($AW50,$AM$44:$AV$53,3,FALSE) -> #N/A | AZ50: =VLOOKUP($AW50,$AM$44:$AV$53,4,FALSE) -> #N/A | BA50: =VLOOKUP($AW50,$AM$44:$AV$53,5,FALSE) -> #N/A | BB50: =VLOOKUP($AW50,$AM$44:$AV$53,6,FALSE) -> #N/A | BC50: =VLOOKUP($AW50,$AM$44:$AV$53,7,FALSE) -> #N/A | BD50: =VLOOKUP($AW50,$AM$44:$AV$53,8,FALSE) -> #N/A | BE50: =VLOOKUP($AW50,$AM$44:$AV$53,9,FALSE) -> #N/A | BF50: =VLOOKUP($AW50,$AM$44:$AV$53,10,FALSE) -> #N/A | BH50: =IF($BI50<>"",MAX(BH$43:BH49)+1,"") | BI50: =IF($I50<>"",G50,"") | BJ50: =IF($AB50<>"",I50,"") | BK50: =IF(AB50=0,"",IF(ISNA(AB50),"",IF($AB50<>"",AB50,""))) | BL50: =IF(ISNA(AB50),"",IF($AB50<>"",AF50,"")) | BM50: =IF(AH50<>"",AH50,"") | BN50: =IF(AJ50<>"",AJ50,"") | BO50: =IF($BP50<>"",MAX(BO$43:BO49)+1,"") | BP50: =IF(BK50<>"", BI50,"") | BQ50: =IF(BL50<>"", BJ50,"") | BR50: =IF(BJ50<>"", BK50,"") | BS50: =IF(BK50<>"", BL50,"") | BT50: =IF(BK50<>"", BM50,"") | BU50: =IF(BK50<>"", BN50,"") | BV50: 7 | BW50: =VLOOKUP($BV50,$BO$44:$BU$53,2,FALSE) -> #N/A | BX50: =VLOOKUP($BV50,$BO$44:$BU$53,3,FALSE) -> #N/A | BY50: =VLOOKUP($BV50,$BO$44:$BU$53,4,FALSE) -> #N/A | BZ50: =VLOOKUP($BV50,$BO$44:$BU$53,5,FALSE) -> #N/A | CA50: =VLOOKUP($BV50,$BO$44:$BU$53,6,FALSE) -> #N/A | CB50: =VLOOKUP($BV50,$BO$44:$BU$53,7,FALSE) -> #N/A
AM51: =IF($AN51<>"",MAX(AM$43:AM50)+1,"") | AN51: =IF(AP51=0,"",IF(ISNA(AP51),"",IF($I51<>"",G51,""))) | AO51: =IF(AP51=0,"",IF(ISNA(AP51),"",IF($I51<>"",I51,""))) | AP51: =IF($I51<>"",J51,"") | AQ51: =IF($I51<>"",L51,"") | AR51: =IF($I51<>"",O51,"") | AS51: =IF($I51<>"",Q51,"") | AT51: =IF($I51<>"",T51,"") | AU51: =IF($I51<>"",X51,"") | AV51: =IF($I51<>"",Z51,"") | AW51: 8 | AX51: =VLOOKUP($AW51,$AM$44:$AV$53,2,FALSE) -> #N/A | AY51: =VLOOKUP($AW51,$AM$44:$AV$53,3,FALSE) -> #N/A | AZ51: =VLOOKUP($AW51,$AM$44:$AV$53,4,FALSE) -> #N/A | BA51: =VLOOKUP($AW51,$AM$44:$AV$53,5,FALSE) -> #N/A | BB51: =VLOOKUP($AW51,$AM$44:$AV$53,6,FALSE) -> #N/A | BC51: =VLOOKUP($AW51,$AM$44:$AV$53,7,FALSE) -> #N/A | BD51: =VLOOKUP($AW51,$AM$44:$AV$53,8,FALSE) -> #N/A | BE51: =VLOOKUP($AW51,$AM$44:$AV$53,9,FALSE) -> #N/A | BF51: =VLOOKUP($AW51,$AM$44:$AV$53,10,FALSE) -> #N/A | BH51: =IF($BI51<>"",MAX(BH$43:BH50)+1,"") | BI51: =IF($I51<>"",G51,"") | BJ51: =IF($AB51<>"",I51,"") | BK51: =IF(AB51=0,"",IF(ISNA(AB51),"",IF($AB51<>"",AB51,""))) | BL51: =IF(ISNA(AB51),"",IF($AB51<>"",AF51,"")) | BM51: =IF(AH51<>"",AH51,"") | BN51: =IF(AJ51<>"",AJ51,"") | BO51: =IF($BP51<>"",MAX(BO$43:BO50)+1,"") | BP51: =IF(BK51<>"", BI51,"") | BQ51: =IF(BL51<>"", BJ51,"") | BR51: =IF(BJ51<>"", BK51,"") | BS51: =IF(BK51<>"", BL51,"") | BT51: =IF(BK51<>"", BM51,"") | BU51: =IF(BK51<>"", BN51,"") | BV51: 8 | BW51: =VLOOKUP($BV51,$BO$44:$BU$53,2,FALSE) -> #N/A | BX51: =VLOOKUP($BV51,$BO$44:$BU$53,3,FALSE) -> #N/A | BY51: =VLOOKUP($BV51,$BO$44:$BU$53,4,FALSE) -> #N/A | BZ51: =VLOOKUP($BV51,$BO$44:$BU$53,5,FALSE) -> #N/A | CA51: =VLOOKUP($BV51,$BO$44:$BU$53,6,FALSE) -> #N/A | CB51: =VLOOKUP($BV51,$BO$44:$BU$53,7,FALSE) -> #N/A
AM52: =IF($AN52<>"",MAX(AM$43:AM51)+1,"") | AN52: =IF(AP52=0,"",IF(ISNA(AP52),"",IF($I52<>"",G52,""))) | AO52: =IF(AP52=0,"",IF(ISNA(AP52),"",IF($I52<>"",I52,""))) | AP52: =IF($I52<>"",J52,"") | AQ52: =IF($I52<>"",L52,"") | AR52: =IF($I52<>"",O52,"") | AS52: =IF($I52<>"",Q52,"") | AT52: =IF($I52<>"",T52,"") | AU52: =IF($I52<>"",X52,"") | AV52: =IF($I52<>"",Z52,"") | AW52: 9 | AX52: =VLOOKUP($AW52,$AM$44:$AV$53,2,FALSE) -> #N/A | AY52: =VLOOKUP($AW52,$AM$44:$AV$53,3,FALSE) -> #N/A | AZ52: =VLOOKUP($AW52,$AM$44:$AV$53,4,FALSE) -> #N/A | BA52: =VLOOKUP($AW52,$AM$44:$AV$53,5,FALSE) -> #N/A | BB52: =VLOOKUP($AW52,$AM$44:$AV$53,6,FALSE) -> #N/A | BC52: =VLOOKUP($AW52,$AM$44:$AV$53,7,FALSE) -> #N/A | BD52: =VLOOKUP($AW52,$AM$44:$AV$53,8,FALSE) -> #N/A | BE52: =VLOOKUP($AW52,$AM$44:$AV$53,9,FALSE) -> #N/A | BF52: =VLOOKUP($AW52,$AM$44:$AV$53,10,FALSE) -> #N/A | BH52: =IF($BI52<>"",MAX(BH$43:BH51)+1,"") | BI52: =IF($I52<>"",G52,"") | BJ52: =IF($AB52<>"",I52,"") | BK52: =IF(AB52=0,"",IF(ISNA(AB52),"",IF($AB52<>"",AB52,""))) | BL52: =IF(ISNA(AB52),"",IF($AB52<>"",AF52,"")) | BM52: =IF(AH52<>"",AH52,"") | BN52: =IF(AJ52<>"",AJ52,"") | BO52: =IF($BP52<>"",MAX(BO$43:BO51)+1,"") | BP52: =IF(BK52<>"", BI52,"") | BQ52: =IF(BL52<>"", BJ52,"") | BR52: =IF(BJ52<>"", BK52,"") | BS52: =IF(BK52<>"", BL52,"") | BT52: =IF(BK52<>"", BM52,"") | BU52: =IF(BK52<>"", BN52,"") | BV52: 9 | BW52: =VLOOKUP($BV52,$BO$44:$BU$53,2,FALSE) -> #N/A | BX52: =VLOOKUP($BV52,$BO$44:$BU$53,3,FALSE) -> #N/A | BY52: =VLOOKUP($BV52,$BO$44:$BU$53,4,FALSE) -> #N/A | BZ52: =VLOOKUP($BV52,$BO$44:$BU$53,5,FALSE) -> #N/A | CA52: =VLOOKUP($BV52,$BO$44:$BU$53,6,FALSE) -> #N/A | CB52: =VLOOKUP($BV52,$BO$44:$BU$53,7,FALSE) -> #N/A
AM53: =IF($AN53<>"",MAX(AM$43:AM52)+1,"") | AN53: =IF(AP53=0,"",IF(ISNA(AP53),"",IF($I53<>"",G53,""))) | AO53: =IF(AP53=0,"",IF(ISNA(AP53),"",IF($I53<>"",I53,""))) | AP53: =IF($I53<>"",J53,"") | AQ53: =IF($I53<>"",L53,"") | AR53: =IF($I53<>"",O53,"") | AS53: =IF($I53<>"",Q53,"") | AT53: =IF($I53<>"",T53,"") | AU53: =IF($I53<>"",X53,"") | AV53: =IF($I53<>"",Z53,"") | AW53: 10 | AX53: =VLOOKUP($AW53,$AM$44:$AV$53,2,FALSE) -> #N/A | AY53: =VLOOKUP($AW53,$AM$44:$AV$53,3,FALSE) -> #N/A | AZ53: =VLOOKUP($AW53,$AM$44:$AV$53,4,FALSE) -> #N/A | BA53: =VLOOKUP($AW53,$AM$44:$AV$53,5,FALSE) -> #N/A | BB53: =VLOOKUP($AW53,$AM$44:$AV$53,6,FALSE) -> #N/A | BC53: =VLOOKUP($AW53,$AM$44:$AV$53,7,FALSE) -> #N/A | BD53: =VLOOKUP($AW53,$AM$44:$AV$53,8,FALSE) -> #N/A | BE53: =VLOOKUP($AW53,$AM$44:$AV$53,9,FALSE) -> #N/A | BF53: =VLOOKUP($AW53,$AM$44:$AV$53,10,FALSE) -> #N/A | BH53: =IF($BI53<>"",MAX(BH$43:BH52)+1,"") | BI53: =IF($I53<>"",G53,"") | BJ53: =IF($AB53<>"",I53,"") | BK53: =IF(AB53=0,"",IF(ISNA(AB53),"",IF($AB53<>"",AB53,""))) | BL53: =IF(ISNA(AB53),"",IF($AB53<>"",AF53,"")) | BM53: =IF(AH53<>"",AH53,"") | BN53: =IF(AJ53<>"",AJ53,"") | BO53: =IF($BP53<>"",MAX(BO$43:BO52)+1,"") | BP53: =IF(BK53<>"", BI53,"") | BQ53: =IF(BL53<>"", BJ53,"") | BR53: =IF(BJ53<>"", BK53,"") | BS53: =IF(BK53<>"", BL53,"") | BT53: =IF(BK53<>"", BM53,"") | BU53: =IF(BK53<>"", BN53,"") | BV53: 10 | BW53: =VLOOKUP($BV53,$BO$44:$BU$53,2,FALSE) -> #N/A | BX53: =VLOOKUP($BV53,$BO$44:$BU$53,3,FALSE) -> #N/A | BY53: =VLOOKUP($BV53,$BO$44:$BU$53,4,FALSE) -> #N/A | BZ53: =VLOOKUP($BV53,$BO$44:$BU$53,5,FALSE) -> #N/A | CA53: =VLOOKUP($BV53,$BO$44:$BU$53,6,FALSE) -> #N/A | CB53: =VLOOKUP($BV53,$BO$44:$BU$53,7,FALSE) -> #N/A
E55: =INDIRECT('D1-D2-D3'!$J$4&"!C93") -> Comments
AM57: =IF($Y46<>"",MAX(AM$54:AM56)+1,"")
D106: ='D4.5Why''s-D5-D6'!D44 -> Factors identification/Influent factors

Sheet D4-D5-D6 Pictures
H2: =INDIRECT('D1-D2-D3'!$J$4&"!C2")&" "&INDIRECT('D1-D2-D3'!$J$4&"!C179") -> PROBLEM SOLVING SHEET Corrective Actions - Pictures | M2: =INDIRECT('D1-D2-D3'!$J$4&"!C3") -> PSS No. | P2: ='D1-D2-D3'!$AI$4 -> 0 | Q2: 4.15.03.00 | S2: II | T2: =INDIRECT('D1-D2-D3'!$J$4&"!C178") -> Page 4: D4-D5-D6
B4: =INDIRECT('D1-D2-D3'!$J$4&"!C182") -> Picture 1 | D4: =INDIRECT('D1-D2-D3'!$J$4&"!C180") -> Before | O4: =INDIRECT('D1-D2-D3'!$J$4&"!C181") -> After
D8: =INDIRECT('D1-D2-D3'!$J$4&"!C93")&":" -> Comments:
B11: =INDIRECT('D1-D2-D3'!$J$4&"!C183") -> Picture 2 | D11: =INDIRECT('D1-D2-D3'!$J$4&"!C180") -> Before | O11: =INDIRECT('D1-D2-D3'!$J$4&"!C181") -> After
D15: =INDIRECT('D1-D2-D3'!$J$4&"!C93")&":" -> Comments:
B18: =INDIRECT('D1-D2-D3'!$J$4&"!C184") -> Picture 3 | D18: =INDIRECT('D1-D2-D3'!$J$4&"!C180") -> Before | O18: =INDIRECT('D1-D2-D3'!$J$4&"!C181") -> After
D22: =INDIRECT('D1-D2-D3'!$J$4&"!C93")&":" -> Comments:
B25: =INDIRECT('D1-D2-D3'!$J$4&"!C185") -> Picture 4 | D25: =INDIRECT('D1-D2-D3'!$J$4&"!C180") -> Before | O25: =INDIRECT('D1-D2-D3'!$J$4&"!C181") -> After
D29: =INDIRECT('D1-D2-D3'!$J$4&"!C93")&":" -> Comments:
B33: =INDIRECT('D1-D2-D3'!$J$4&"!C186") -> Picture 5 | D33: =INDIRECT('D1-D2-D3'!$J$4&"!C180") -> Before | O33: =INDIRECT('D1-D2-D3'!$J$4&"!C181") -> After
D37: =INDIRECT('D1-D2-D3'!$J$4&"!C93")&":" -> Comments:
D40: =INDIRECT('D1-D2-D3'!$J$4&"!C180") -> Before | O40: =INDIRECT('D1-D2-D3'!$J$4&"!C181") -> After
B42: =INDIRECT('D1-D2-D3'!$J$4&"!C187") -> Picture
D44: =INDIRECT('D1-D2-D3'!$J$4&"!C93")&":" -> Comments:
D47: =INDIRECT('D1-D2-D3'!$J$4&"!C180") -> Before | O47: =INDIRECT('D1-D2-D3'!$J$4&"!C181") -> After
B49: =INDIRECT('D1-D2-D3'!$J$4&"!C187") -> Picture
D51: =INDIRECT('D1-D2-D3'!$J$4&"!C93")&":" -> Comments:
D54: =INDIRECT('D1-D2-D3'!$J$4&"!C180") -> Before | O54: =INDIRECT('D1-D2-D3'!$J$4&"!C181") -> After
B56: =INDIRECT('D1-D2-D3'!$J$4&"!C187") -> Picture
D58: =INDIRECT('D1-D2-D3'!$J$4&"!C93")&":" -> Comments:
D61: =INDIRECT('D1-D2-D3'!$J$4&"!C180") -> Before | O61: =INDIRECT('D1-D2-D3'!$J$4&"!C181") -> After
B63: =INDIRECT('D1-D2-D3'!$J$4&"!C187") -> Picture
D65: =INDIRECT('D1-D2-D3'!$J$4&"!C93")&":" -> Comments:
D68: =INDIRECT('D1-D2-D3'!$J$4&"!C180") -> Before | O68: =INDIRECT('D1-D2-D3'!$J$4&"!C181") -> After
B70: =INDIRECT('D1-D2-D3'!$J$4&"!C187") -> Picture
D72: =INDIRECT('D1-D2-D3'!$J$4&"!C93")&":" -> Comments:
D75: =INDIRECT('D1-D2-D3'!$J$4&"!C180") -> Before | O75: =INDIRECT('D1-D2-D3'!$J$4&"!C181") -> After
B77: =INDIRECT('D1-D2-D3'!$J$4&"!C187") -> Picture
D79: =INDIRECT('D1-D2-D3'!$J$4&"!C93")&":" -> Comments:
D82: =INDIRECT('D1-D2-D3'!$J$4&"!C180") -> Before | O82: =INDIRECT('D1-D2-D3'!$J$4&"!C181") -> After
B84: =INDIRECT('D1-D2-D3'!$J$4&"!C187") -> Picture
D86: =INDIRECT('D1-D2-D3'!$J$4&"!C93")&":" -> Comments:

Sheet D6.Verification-D7-D8
F2: =INDIRECT('D1-D2-D3'!$J$4&"!C2")&" "&INDIRECT('D1-D2-D3'!$J$4&"!C189") -> PROBLEM SOLVING SHEET Verification, Preventive Actions, Closure | T2: =INDIRECT('D1-D2-D3'!$J$4&"!C3") -> PSS No. | V2: ='D1-D2-D3'!AI4 -> 0 | X2: 4.15.03.00 | AA2: =INDIRECT('D1-D2-D3'!$J$4&"!C188") -> Page 5: D6-D7-D8
B5: =INDIRECT('D1-D2-D3'!$J$4&"!C162") -> D6 - Implementation of permanent corrective action(s)
C7: =INDIRECT('D1-D2-D3'!$J$4&"!C298") -> 0 | D7: =INDIRECT('D1-D2-D3'!$J$4&"!C190") -> Verification of effectiveness of corrective actions | O7: =INDIRECT('D1-D2-D3'!$J$4&"!C68")&":" -> Status: | Z7: =INDIRECT('D1-D2-D3'!$J$4&"!C69") -> Date
D10: =INDIRECT('D1-D2-D3'!$J$4&"!C149") -> Factors identification | E10: =INDIRECT('D1-D2-D3'!$J$4&"!C192") -> Result and evidence of effectiveness check and comment
D11: =INDIRECT('D1-D2-D3'!$J$4&"!C139") -> Occurrence
D19: =INDIRECT('D1-D2-D3'!$J$4&"!C140") -> Non-detection
C28: =INDIRECT('D1-D2-D3'!$J$4&"!C93")&" - " &" "&INDIRECT('D1-D2-D3'!$J$4&"!C231") -> Comments - Optional additional notes (pictures etc.)
B44: =INDIRECT('D1-D2-D3'!$J$4&"!C193") -> D7 - Preventive Actions
C46: =INDIRECT('D1-D2-D3'!$J$4&"!C279") -> 0 | D46: =INDIRECT('D1-D2-D3'!$J$4&"!C194") -> Documentation - Standard updates | O46: =INDIRECT('D1-D2-D3'!$J$4&"!C68")&":" -> Status: | Z46: =INDIRECT('D1-D2-D3'!$J$4&"!C69") -> Date
D50: =INDIRECT('D1-D2-D3'!$J$4&"!C195") -> Documentation | G50: =INDIRECT('D1-D2-D3'!$J$4&"!C266")&"/ "&INDIRECT('D1-D2-D3'!$J$4&"!C267") -> New/ Updated | I50: =INDIRECT('D1-D2-D3'!$J$4&"!C196") -> Designation | O50: =INDIRECT('D1-D2-D3'!$J$4&"!C166") -> Target Date | R50: =INDIRECT('D1-D2-D3'!$J$4&"!C84") -> Impl. Date | U50: =INDIRECT('D1-D2-D3'!$J$4&"!C83") -> Responsible | Y50: =INDIRECT('D1-D2-D3'!$J$4&"!C93") -> Comments
D51: =INDIRECT('D1-D2-D3'!$J$4&"!C197") -> FMEA
D52: =INDIRECT('D1-D2-D3'!$J$4&"!C198") -> PCP
D53: =INDIRECT('D1-D2-D3'!$J$4&"!C199") -> WI
D54: =INDIRECT('D1-D2-D3'!$J$4&"!C200") -> Maintenance Plan
D55: =INDIRECT('D1-D2-D3'!$J$4&"!C201") -> Drawing
D56: =INDIRECT('D1-D2-D3'!$J$4&"!C202") -> Lessons Learned Card
D57: =INDIRECT('D1-D2-D3'!$J$4&"!C203") -> Training standard
D58: =INDIRECT('D1-D2-D3'!$J$4&"!C204") -> Procedure
D59: =INDIRECT('D1-D2-D3'!$J$4&"!C205") -> Specification
D60: =INDIRECT('D1-D2-D3'!$J$4&"!C135") -> Others
C62: =INDIRECT('D1-D2-D3'!$J$4&"!C206") -> Implementation of measures to similar processes/products
D64: =INDIRECT('D1-D2-D3'!$J$4&"!C207") -> Processes | I64: =INDIRECT('D1-D2-D3'!$J$4&"!C265") -> Inform Prevention-Team | U64: Mail to: | W64: pss@ksab.kroschu.com
D66: =INDIRECT('D1-D2-D3'!$J$4&"!C208") -> Concerned processes | I66: =INDIRECT('D1-D2-D3'!$J$4&"!C80") -> Action | U66: =INDIRECT('D1-D2-D3'!$J$4&"!C83") -> Responsible | Y66: =INDIRECT('D1-D2-D3'!$J$4&"!C211")&" - "&INDIRECT('D1-D2-D3'!$J$4&"!C69") -> E-mail sent to responsible - Date
D71: =INDIRECT('D1-D2-D3'!$J$4&"!C209") -> Products
D73: =INDIRECT('D1-D2-D3'!$J$4&"!C210") -> Concerned products | I73: =INDIRECT('D1-D2-D3'!$J$4&"!C80") -> Action | U73: =INDIRECT('D1-D2-D3'!$J$4&"!C83") -> Responsible | Y73: =INDIRECT('D1-D2-D3'!$J$4&"!C211")&" - "&INDIRECT('D1-D2-D3'!$J$4&"!C69") -> E-mail sent to responsible - Date
B79: =INDIRECT('D1-D2-D3'!$J$4&"!C214")&" " &INDIRECT('D1-D2-D3'!$J$4&"!C215") -> D8 - PSS closure and appreciation of team's success
D81: =INDIRECT('D1-D2-D3'!$J$4&"!C216") -> Last Update | L81: =INDIRECT('D1-D2-D3'!$J$4&"!C217") -> Status of complaint
D83: =INDIRECT('D1-D2-D3'!$J$4&"!C221") -> Position | G83: =INDIRECT('D1-D2-D3'!$J$4&"!C24") -> Name, prename | L83: =INDIRECT('D1-D2-D3'!$J$4&"!C69") -> Date | N83: =INDIRECT('D1-D2-D3'!$J$4&"!C232") -> Comments, conclusion (result of final discussion)
D84: ='D1-D2-D3'!DX15 -> PSC | L84: =INDIRECT('D1-D2-D3'!$J$4&"!C227") -> informed on
D85: =INDIRECT('D1-D2-D3'!$J$4&"!C223") -> Responsible Q | L85: =INDIRECT('D1-D2-D3'!$J$4&"!C227") -> informed on
D86: =INDIRECT('D1-D2-D3'!$J$4&"!C224") -> AP-team leader | L86: =INDIRECT('D1-D2-D3'!$J$4&"!C228") -> verified on
D87: =INDIRECT('D1-D2-D3'!$J$4&"!C225") -> Problem coordinator | L87: =INDIRECT('D1-D2-D3'!$J$4&"!C229") -> closed on
C92: =INDIRECT('D1-D2-D3'!$J$4&"!C226") -> Information about result of 3 month-evaluation
DM204: =IF('D6.Verification-D7-D8'!AC64="","",'D6.Verification-D7-D8'!F64)

Sheet 8D-Report (with link)
R2: =INDIRECT($J$4&"!C230") -> 8D-report | CG2: 4.15.02.00
C4: ='D1-D2-D3'!C4 -> Language | J4: ='D1-D2-D3'!J4:V4 -> ENGLISH | AA4: ='D1-D2-D3'!AA4 -> PSS No. | AI4: =IF('D1-D2-D3'!AI4:AU4="","",'D1-D2-D3'!AI4:AU4) | AZ4: ='D1-D2-D3'!AZ4:BI4 -> Fault type | BJ4: =IF('D1-D2-D3'!BJ4:BV4="","",'D1-D2-D3'!$BJ$4)
C7: ='D1-D2-D3'!C7:M7 -> Kroschu plant | N7: =IF('D1-D2-D3'!N7:Z7="","",'D1-D2-D3'!N7:Z7) | AF7: ='D1-D2-D3'!AF7:AQ7 -> Opening date | AR7: =IF('D1-D2-D3'!AR7:BD7="","",'D1-D2-D3'!AR7:BD7) | BM7: ='D1-D2-D3'!BU7 -> Report version
C9: =INDIRECT($J$4&"!C10") -> Customer | N9: =IF('D1-D2-D3'!N8:Z8="","",'D1-D2-D3'!N8:Z8) | AF9: ='D1-D2-D3'!AF8:AQ8 -> Project | AR9: =IF('D1-D2-D3'!AR8:BD8="","",'D1-D2-D3'!AR8:BD8) | BM9: ='D1-D2-D3'!BU8 -> Customer complaint No. | CK9: =IF('D1-D2-D3'!CK8="","",'D1-D2-D3'!$CK$8)
B11: ='D1-D2-D3'!B11:AR12 -> Basic Data
D14: ='D1-D2-D3'!D14:M14 -> KSK | N14: =IF('D1-D2-D3'!N14:AH14="","",'D1-D2-D3'!N14:AH14) | AM14: ='D1-D2-D3'!$AM$14 -> Int. KSK-No. | BC14: =IF('D1-D2-D3'!BC14="","",'D1-D2-D3'!$BC$14) | CC14: ='D1-D2-D3'!CC14 -> Production date/time | DD14: =IF('D1-D2-D3'!DD14:DR14="","",'D1-D2-D3'!DD14:DR14)
D17: ='D1-D2-D3'!D16:M16 -> Index | N17: =IF('D1-D2-D3'!N16:AH16="","",'D1-D2-D3'!N16:AH16) | AM17: ='D1-D2-D3'!AM16:BB16 -> Lfd./Serial | BC17: =IF('D1-D2-D3'!BC16:BU16="","",'D1-D2-D3'!BC16:BU16) | CC17: ='D1-D2-D3'!CC16 -> Safety-relevant characterisitc | DD17: =IF('D1-D2-D3'!DD16:DR16="","",'D1-D2-D3'!DD16:DR16)
B20: ='D1-D2-D3'!B18 -> D1 - Team
D22: =INDIRECT($J$4&"!C23") -> Coordinator (/Champion) | BL22: =INDIRECT($J$4&"!C26") -> Sponsor
D23: =INDIRECT($J$4&"!C24") -> Name, prename | W23: =INDIRECT($J$4&"!C25") -> Department/function Contact data | BK23: =INDIRECT($J$4&"!C24") -> Name, prename | CD23: =INDIRECT($J$4&"!C25") -> Department/function Contact data
D24: =IF('D1-D2-D3'!D22="","",'D1-D2-D3'!D22) | S24: =IF('D1-D2-D3'!S22="","",'D1-D2-D3'!S22) | AI24: =IF('D1-D2-D3'!AI22="","",'D1-D2-D3'!AI22) | BL24: =IF('D1-D2-D3'!BL22="","",'D1-D2-D3'!BL22) | CA24: =IF('D1-D2-D3'!CA22="","",'D1-D2-D3'!CA22) | CQ24: =IF('D1-D2-D3'!CQ22="","",'D1-D2-D3'!CQ22)
D26: =INDIRECT($J$4&"!C27") -> Members
D28: =IF('D1-D2-D3'!D26="","",'D1-D2-D3'!D26) | S28: =IF('D1-D2-D3'!S26="","",'D1-D2-D3'!S26) | AI28: =IF('D1-D2-D3'!AI26="","",'D1-D2-D3'!AI26) | BL28: =IF('D1-D2-D3'!BL26="","",'D1-D2-D3'!BL26) | CA28: =IF('D1-D2-D3'!CA26="","",'D1-D2-D3'!CA26) | CQ28: =IF('D1-D2-D3'!CQ26="","",'D1-D2-D3'!CQ26)
D29: =IF('D1-D2-D3'!D27="","",'D1-D2-D3'!D27) | S29: =IF('D1-D2-D3'!S27="","",'D1-D2-D3'!S27) | AI29: =IF('D1-D2-D3'!AI27="","",'D1-D2-D3'!AI27) | BL29: =IF('D1-D2-D3'!BL27="","",'D1-D2-D3'!BL27) | CA29: =IF('D1-D2-D3'!CA27="","",'D1-D2-D3'!CA27) | CQ29: =IF('D1-D2-D3'!CQ27="","",'D1-D2-D3'!CQ27)
D30: =IF('D1-D2-D3'!D28="","",'D1-D2-D3'!D28) | S30: =IF('D1-D2-D3'!S28="","",'D1-D2-D3'!S28) | AI30: =IF('D1-D2-D3'!AI28="","",'D1-D2-D3'!AI28) | BL30: =IF('D1-D2-D3'!BL28="","",'D1-D2-D3'!BL28) | CA30: =IF('D1-D2-D3'!CA28="","",'D1-D2-D3'!CA28) | CQ30: =IF('D1-D2-D3'!CQ28="","",'D1-D2-D3'!CQ28)
D31: =IF('D1-D2-D3'!D29="","",'D1-D2-D3'!D29) | S31: =IF('D1-D2-D3'!S29="","",'D1-D2-D3'!S29) | AI31: =IF('D1-D2-D3'!AI29="","",'D1-D2-D3'!AI29) | BL31: =IF('D1-D2-D3'!BL29="","",'D1-D2-D3'!BL29) | CA31: =IF('D1-D2-D3'!CA29="","",'D1-D2-D3'!CA29) | CQ31: =IF('D1-D2-D3'!CQ29="","",'D1-D2-D3'!CQ29)
D32: =IF('D1-D2-D3'!D30="","",'D1-D2-D3'!D30) | S32: =IF('D1-D2-D3'!S30="","",'D1-D2-D3'!S30) | AI32: =IF('D1-D2-D3'!AI30="","",'D1-D2-D3'!AI30) | BL32: =IF('D1-D2-D3'!BL30="","",'D1-D2-D3'!BL30) | CA32: =IF('D1-D2-D3'!CA30="","",'D1-D2-D3'!CA30) | CQ32: =IF('D1-D2-D3'!CQ30="","",'D1-D2-D3'!CQ30)
B35: ='D1-D2-D3'!B33 -> D2 - Problem description
D38: ='D1-D2-D3'!D36 -> NOK PART | BL38: ='D1-D2-D3'!BL36 -> OK PART
D45: ='D1-D2-D3'!D46 -> Symptom description | V45: =IF('D1-D2-D3'!V46="","",'D1-D2-D3'!V46) | AV45: ='D1-D2-D3'!AU46 -> IS | CH45: ='D1-D2-D3'!CG46 -> IS NOT
AS46: ='D1-D2-D3'!AR47 -> What | AV46: ='D1-D2-D3'!AU47 -> Which product/process does the problem concern ? | CH46: ='D1-D2-D3'!CG47 -> Are there comparable products/processes where the problem did not occur ?
D47: ='D1-D2-D3'!D48 -> Problem description | V47: =IF('D1-D2-D3'!V48="","",'D1-D2-D3'!V48) | AV47: =IF('D1-D2-D3'!AU48="","",'D1-D2-D3'!AU48) | CH47: =IF('D1-D2-D3'!CG48="","",'D1-D2-D3'!CG48)
AV48: ='D1-D2-D3'!AU49 -> What is the deviation ? | CH48: ='D1-D2-D3'!CG49 -> Are additional deviations of the affected product/process expected ?
AV49: =IF('D1-D2-D3'!AU50="","",'D1-D2-D3'!AU50) | CH49: =IF('D1-D2-D3'!CG50="","",'D1-D2-D3'!CG50)
D50: =INDIRECT($J$4&"!C31")&" & "&INDIRECT($J$4&"!C32") -> Fault code & Fault description | AH50: =IF('D1-D2-D3'!AH51="","",'D1-D2-D3'!AH51) | AS50: ='D1-D2-D3'!AR51 -> Where | AV50: ='D1-D2-D3'!AU51 -> Where was the product/process when the deviation first occurred ? | CH50: ='D1-D2-D3'!CG51 -> Where else could the deviation occur ?
D51: =IF('D1-D2-D3'!D52="","",'D1-D2-D3'!D52) -> #N/A | AV51: =IF('D1-D2-D3'!AU52="","",'D1-D2-D3'!AU52) | CH51: =IF('D1-D2-D3'!CG52="","",'D1-D2-D3'!CG52)
AV52: ='D1-D2-D3'!AU53 -> Where in the product/process did the deviation occur ? | CH52: ='D1-D2-D3'!CG53 -> What are the names of the neighbouring products/processes and which of them are not affected by the deviation ?
D53: =INDIRECT($J$4&"!C33") -> Fault location | M53: =IF('D1-D2-D3'!M54="","",'D1-D2-D3'!M54) | AV53: =IF('D1-D2-D3'!AU54="","",'D1-D2-D3'!AU54) | CH53: =IF('D1-D2-D3'!CG54="","",'D1-D2-D3'!CG54)
AS54: ='D1-D2-D3'!AR55 -> When | AV54: ='D1-D2-D3'!AU55 -> When was the deviation first detected ? (Date of occurrence & life cycle) | CH54: ='D1-D2-D3'!CG55 -> Can the problem have occurred in an earlier phase/time ?
D55: =INDIRECT($J$4&"!C34") -> Workplace | M55: =IF('D1-D2-D3'!M56="","",'D1-D2-D3'!M56) | AV55: =IF('D1-D2-D3'!AU56="","",'D1-D2-D3'!AU56) | CH55: =IF('D1-D2-D3'!CG56="","",'D1-D2-D3'!CG56)
D56: =INDIRECT($J$4&"!C35") -> Qualification | M56: =IF('D1-D2-D3'!M57="","",'D1-D2-D3'!M57) | AV56: ='D1-D2-D3'!AU57 -> Is there a recognisable systematic of failures ? (single failure, continuous increase/fall, random or cyclical) ? | CH56: ='D1-D2-D3'!CG57 -> Can additional failures be expected since the discovery ?
D57: =INDIRECT($J$4&"!C36") -> Line | M57: =IF('D1-D2-D3'!M58="","",'D1-D2-D3'!M58) | AV57: =IF('D1-D2-D3'!AU58="","",'D1-D2-D3'!AU58) | CH57: =IF('D1-D2-D3'!CG58="","",'D1-D2-D3'!CG58)
D58: =INDIRECT($J$4&"!C37") -> Team | M58: =IF('D1-D2-D3'!M59="","",'D1-D2-D3'!M59) | AS58: ='D1-D2-D3'!AR59 -> How many | AV58: ='D1-D2-D3'!AU59 -> How many failures ? (number & PPM's) | CH58: ='D1-D2-D3'!CG59 -> How many more can be expected in the future ?
D59: =INDIRECT($J$4&"!C38") -> Equipment | M59: =IF('D1-D2-D3'!M60="","",'D1-D2-D3'!M60) | AV59: =IF('D1-D2-D3'!AU60="","",'D1-D2-D3'!AU60) | CH59: =IF('D1-D2-D3'!CG60="","",'D1-D2-D3'!CG60)
D60: =INDIRECT($J$4&"!C39")&":" -> Repetitive fault: | R60: =INDIRECT($J$4&"!C40")&":" -> If yes, PSS No./ 8D No.: | AV60: ='D1-D2-D3'!AU61 -> Which persons are affected ? What costs have been incurred so far ? Will these rise, fall or remain stable ? | CH60: ='D1-D2-D3'!CG61 -> What can lead to worse/better circumstances ?
M61: =IF('D1-D2-D3'!M62="","",'D1-D2-D3'!M62) | R61: =IF('D1-D2-D3'!R62="","",'D1-D2-D3'!R62) | AV61: =IF('D1-D2-D3'!AU62="","",'D1-D2-D3'!AU62) | CH61: =IF('D1-D2-D3'!CG62="","",'D1-D2-D3'!CG62)
B64: ='D1-D2-D3'!B65 -> D3 - Immediate action(s)
BR65: ='D1-D2-D3'!BR66 -> Status: | BY65: =IF('D1-D2-D3'!BY66:CK66="","",'D1-D2-D3'!BY66:CK66) | DI65: ='D1-D2-D3'!CZ66 -> Date | DJ65: =IF('D1-D2-D3'!DE66="","",'D1-D2-D3'!DE66)
D68: ='D1-D2-D3'!D69 -> Were the relevant emloyees informed ? | AJ68: =IF('D1-D2-D3'!AH69="","",'D1-D2-D3'!AH69) | AR68: ='D1-D2-D3'!AR69 -> Date | BA68: =IF('D1-D2-D3'!BA69="","",'D1-D2-D3'!BA69) | BX68: ='D1-D2-D3'!BW69 -> Responsible | BY68: =IF('D1-D2-D3'!BY69="","",'D1-D2-D3'!BY69)
D70: ='D1-D2-D3'!D71:DR71 -> Limitation of affected products
D72: ='D1-D2-D3'!D73 -> Is it possible to do a limitation of the affected products ? | AJ72: =IF('D1-D2-D3'!BA73="","",'D1-D2-D3'!BA73) -> Yes | BB72: =IF('D1-D2-D3'!BB77="","",'D1-D2-D3'!BB77) -> 0 | BL72: ='D1-D2-D3'!BL77 -> total amount of affected products
G74: =INDIRECT('D1-D2-D3'!$J$4&"!C80") -> Action | BM74: =INDIRECT('D1-D2-D3'!$J$4&"!C233") -> Risk assessment | CR74: =INDIRECT('D1-D2-D3'!$J$4&"!C81") -> Effectiveness verification
T75: =INDIRECT('D1-D2-D3'!$J$4&"!C80") -> Action | AO75: ='D1-D2-D3'!AZ80 -> Start date | AV75: ='D1-D2-D3'!BG80 -> Closing date | BC75: =INDIRECT('D1-D2-D3'!$J$4&"!C83") -> Responsible | BM75: =INDIRECT('D1-D2-D3'!$J$4&"!C256") -> Hazard/ Risk | CB75: ='Risk assesment (for D3 & D5)'!AO18 -> Level | CF75: =INDIRECT('D1-D2-D3'!$J$4&"!C259") -> Measures | CR75: =INDIRECT($J$4&"!C82") -> Method | DC75: =INDIRECT($J$4&"!C69") -> Date | DH75: =INDIRECT($J$4&"!C83") -> Responsible | DN75: Result
D77: ='D1-D2-D3'!D81 -> Measures for continuing secure production at customer | L77: =IF('D1-D2-D3'!L81="","",'D1-D2-D3'!L81) | T77: =IF('D1-D2-D3'!T81="","",'D1-D2-D3'!T81) | AO77: =IF('D1-D2-D3'!AZ81="","",'D1-D2-D3'!AZ81) | AV77: =IF('D1-D2-D3'!BG81="","",'D1-D2-D3'!BG81) | BC77: =IF('D1-D2-D3'!BN81="","",'D1-D2-D3'!BN81) | BM77: =IF('Risk assesment (for D3 & D5)'!U19="","",'Risk assesment (for D3 & D5)'!U19) | CB77: ='Risk assesment (for D3 & D5)'!AO19 | CF77: =IF('Risk assesment (for D3 & D5)'!AS19="","",'Risk assesment (for D3 & D5)'!AS19) | CR77: =IF('D1-D2-D3'!BX81="","",'D1-D2-D3'!BX81) | DC77: =IF('D1-D2-D3'!CW81="","",'D1-D2-D3'!CW81) | DH77: =IF('D1-D2-D3'!DD81="","",'D1-D2-D3'!DD81) | DN77: =IF('D1-D2-D3'!DM81="","",'D1-D2-D3'!DM81)
L78: =IF('D1-D2-D3'!L82="","",'D1-D2-D3'!L82) | T78: =IF('D1-D2-D3'!T82="","",'D1-D2-D3'!T82) | AO78: =IF('D1-D2-D3'!AZ82="","",'D1-D2-D3'!AZ82) | AV78: =IF('D1-D2-D3'!BG82="","",'D1-D2-D3'!BG82) | BC78: =IF('D1-D2-D3'!BN82="","",'D1-D2-D3'!BN82) | BM78: =IF('Risk assesment (for D3 & D5)'!U20="","",'Risk assesment (for D3 & D5)'!U20) | CB78: ='Risk assesment (for D3 & D5)'!AO20 | CF78: =IF('Risk assesment (for D3 & D5)'!AS20="","",'Risk assesment (for D3 & D5)'!AS20) | CR78: =IF('D1-D2-D3'!BX82="","",'D1-D2-D3'!BX82) | DC78: =IF('D1-D2-D3'!CW82="","",'D1-D2-D3'!CW82) | DH78: =IF('D1-D2-D3'!DD82="","",'D1-D2-D3'!DD82) | DN78: =IF('D1-D2-D3'!DM82="","",'D1-D2-D3'!DM82)
L79: =IF('D1-D2-D3'!L83="","",'D1-D2-D3'!L83) | T79: =IF('D1-D2-D3'!T83="","",'D1-D2-D3'!T83) | AO79: =IF('D1-D2-D3'!AZ83="","",'D1-D2-D3'!AZ83) | AV79: =IF('D1-D2-D3'!BG83="","",'D1-D2-D3'!BG83) | BC79: =IF('D1-D2-D3'!BN83="","",'D1-D2-D3'!BN83) | BM79: =IF('Risk assesment (for D3 & D5)'!U21="","",'Risk assesment (for D3 & D5)'!U21) | CB79: ='Risk assesment (for D3 & D5)'!AO21 | CF79: =IF('Risk assesment (for D3 & D5)'!AS21="","",'Risk assesment (for D3 & D5)'!AS21) | CR79: =IF('D1-D2-D3'!BX83="","",'D1-D2-D3'!BX83) | DC79: =IF('D1-D2-D3'!CW83="","",'D1-D2-D3'!CW83) | DH79: =IF('D1-D2-D3'!DD83="","",'D1-D2-D3'!DD83) | DN79: =IF('D1-D2-D3'!DM83="","",'D1-D2-D3'!DM83)
D80: ='D1-D2-D3'!D84 -> Measures for continuing delivery | L80: =IF('D1-D2-D3'!L84="","",'D1-D2-D3'!L84) | T80: =IF('D1-D2-D3'!T84="","",'D1-D2-D3'!T84) | AO80: =IF('D1-D2-D3'!AZ84="","",'D1-D2-D3'!AZ84) | AV80: =IF('D1-D2-D3'!BG84="","",'D1-D2-D3'!BG84) | BC80: =IF('D1-D2-D3'!BN84="","",'D1-D2-D3'!BN84) | BM80: =IF('Risk assesment (for D3 & D5)'!U22="","",'Risk assesment (for D3 & D5)'!U22) | CB80: ='Risk assesment (for D3 & D5)'!AO22 | CF80: =IF('Risk assesment (for D3 & D5)'!AS22="","",'Risk assesment (for D3 & D5)'!AS22) | CR80: =IF('D1-D2-D3'!BX84="","",'D1-D2-D3'!BX84) | DC80: =IF('D1-D2-D3'!CW84="","",'D1-D2-D3'!CW84) | DH80: =IF('D1-D2-D3'!DD84="","",'D1-D2-D3'!DD84) | DN80: =IF('D1-D2-D3'!DM84="","",'D1-D2-D3'!DM84)
L81: =IF('D1-D2-D3'!L85="","",'D1-D2-D3'!L85) | T81: =IF('D1-D2-D3'!T85="","",'D1-D2-D3'!T85) | AO81: =IF('D1-D2-D3'!AZ85="","",'D1-D2-D3'!AZ85) | AV81: =IF('D1-D2-D3'!BG85="","",'D1-D2-D3'!BG85) | BC81: =IF('D1-D2-D3'!BN85="","",'D1-D2-D3'!BN85) | BM81: =IF('Risk assesment (for D3 & D5)'!U23="","",'Risk assesment (for D3 & D5)'!U23) | CB81: ='Risk assesment (for D3 & D5)'!AO23 | CF81: =IF('Risk assesment (for D3 & D5)'!AS23="","",'Risk assesment (for D3 & D5)'!AS23) | CR81: =IF('D1-D2-D3'!BX85="","",'D1-D2-D3'!BX85) | DC81: =IF('D1-D2-D3'!CW85="","",'D1-D2-D3'!CW85) | DH81: =IF('D1-D2-D3'!DD85="","",'D1-D2-D3'!DD85) | DN81: =IF('D1-D2-D3'!DM85="","",'D1-D2-D3'!DM85)
L82: =IF('D1-D2-D3'!L86="","",'D1-D2-D3'!L86) | T82: =IF('D1-D2-D3'!T86="","",'D1-D2-D3'!T86) | AO82: =IF('D1-D2-D3'!AZ86="","",'D1-D2-D3'!AZ86) | AV82: =IF('D1-D2-D3'!BG86="","",'D1-D2-D3'!BG86) | BC82: =IF('D1-D2-D3'!BN86="","",'D1-D2-D3'!BN86) | BM82: =IF('Risk assesment (for D3 & D5)'!U24="","",'Risk assesment (for D3 & D5)'!U24) | CB82: ='Risk assesment (for D3 & D5)'!AO24 | CF82: =IF('Risk assesment (for D3 & D5)'!AS24="","",'Risk assesment (for D3 & D5)'!AS24) | CR82: =IF('D1-D2-D3'!BX86="","",'D1-D2-D3'!BX86) | DC82: =IF('D1-D2-D3'!CW86="","",'D1-D2-D3'!CW86) | DH82: =IF('D1-D2-D3'!DD86="","",'D1-D2-D3'!DD86) | DN82: =IF('D1-D2-D3'!DM86="","",'D1-D2-D3'!DM86)
D83: ='D1-D2-D3'!D87 -> Measures for continuing Kroschu-production | L83: =IF('D1-D2-D3'!L87="","",'D1-D2-D3'!L87) | T83: =IF('D1-D2-D3'!T87="","",'D1-D2-D3'!T87) | AO83: =IF('D1-D2-D3'!AZ87="","",'D1-D2-D3'!AZ87) | AV83: =IF('D1-D2-D3'!BG87="","",'D1-D2-D3'!BG87) | BC83: =IF('D1-D2-D3'!BN87="","",'D1-D2-D3'!BN87) | BM83: =IF('Risk assesment (for D3 & D5)'!U25="","",'Risk assesment (for D3 & D5)'!U25) | CB83: ='Risk assesment (for D3 & D5)'!AO25 | CF83: =IF('Risk assesment (for D3 & D5)'!AS25="","",'Risk assesment (for D3 & D5)'!AS25) | CR83: =IF('D1-D2-D3'!BX87="","",'D1-D2-D3'!BX87) | DC83: =IF('D1-D2-D3'!CW87="","",'D1-D2-D3'!CW87) | DH83: =IF('D1-D2-D3'!DD87="","",'D1-D2-D3'!DD87) | DN83: =IF('D1-D2-D3'!DM87="","",'D1-D2-D3'!DM87)
L84: =IF('D1-D2-D3'!L88="","",'D1-D2-D3'!L88) | T84: =IF('D1-D2-D3'!T88="","",'D1-D2-D3'!T88) | AO84: =IF('D1-D2-D3'!AZ88="","",'D1-D2-D3'!AZ88) | AV84: =IF('D1-D2-D3'!BG88="","",'D1-D2-D3'!BG88) | BC84: =IF('D1-D2-D3'!BN88="","",'D1-D2-D3'!BN88) | BM84: =IF('Risk assesment (for D3 & D5)'!U26="","",'Risk assesment (for D3 & D5)'!U26) | CB84: ='Risk assesment (for D3 & D5)'!AO26 | CF84: =IF('Risk assesment (for D3 & D5)'!AS26="","",'Risk assesment (for D3 & D5)'!AS26) | CR84: =IF('D1-D2-D3'!BX88="","",'D1-D2-D3'!BX88) | DC84: =IF('D1-D2-D3'!CW88="","",'D1-D2-D3'!CW88) | DH84: =IF('D1-D2-D3'!DD88="","",'D1-D2-D3'!DD88) | DN84: =IF('D1-D2-D3'!DM88="","",'D1-D2-D3'!DM88)
L85: =IF('D1-D2-D3'!L89="","",'D1-D2-D3'!L89) | T85: =IF('D1-D2-D3'!T89="","",'D1-D2-D3'!T89) | AO85: =IF('D1-D2-D3'!AZ89="","",'D1-D2-D3'!AZ89) | AV85: =IF('D1-D2-D3'!BG89="","",'D1-D2-D3'!BG89) | BC85: =IF('D1-D2-D3'!BN89="","",'D1-D2-D3'!BN89) | BM85: =IF('Risk assesment (for D3 & D5)'!U27="","",'Risk assesment (for D3 & D5)'!U27) | CB85: ='Risk assesment (for D3 & D5)'!AO27 | CF85: =IF('Risk assesment (for D3 & D5)'!AS27="","",'Risk assesment (for D3 & D5)'!AS27) | CR85: =IF('D1-D2-D3'!BX89="","",'D1-D2-D3'!BX89) | DC85: =IF('D1-D2-D3'!CW89="","",'D1-D2-D3'!CW89) | DH85: =IF('D1-D2-D3'!DD89="","",'D1-D2-D3'!DD89) | DN85: =IF('D1-D2-D3'!DM89="","",'D1-D2-D3'!DM89)
D87: =INDIRECT($J$4&"!C85") -> Sorting actions | H87: =INDIRECT($J$4&"!C73") -> delivered to the customer | AU87: =INDIRECT($J$4&"!C74") -> on transit | CH87: =INDIRECT($J$4&"!C75") -> at Kroschu
H89: =INDIRECT($J$4&"!C85") -> Sorting actions | AD89: =IF('D1-D2-D3'!AD93="","",'D1-D2-D3'!AD93) | AU89: =INDIRECT($J$4&"!C85") -> Sorting actions | BQ89: =IF('D1-D2-D3'!BQ93="","",'D1-D2-D3'!BQ93) | CH89: =INDIRECT($J$4&"!C85") -> Sorting actions | DD89: =IF('D1-D2-D3'!DD93="","",'D1-D2-D3'!DD93)
H91: =INDIRECT($J$4&"!C86") -> Quantity sorted | AD91: =IF('D1-D2-D3'!AD95="","",'D1-D2-D3'!AD95) | AU91: =INDIRECT($J$4&"!C86") -> Quantity sorted | BQ91: =IF('D1-D2-D3'!BQ95="","",'D1-D2-D3'!BQ95) | CH91: =INDIRECT($J$4&"!C86") -> Quantity sorted | DD91: =IF('D1-D2-D3'!DD95="","",'D1-D2-D3'!DD95)
H94: =INDIRECT($J$4&"!C87") -> No. NOK parts found | AD94: =IF('D1-D2-D3'!AD98="","",'D1-D2-D3'!AD98) | AU94: =INDIRECT($J$4&"!C87") -> No. NOK parts found | BQ94: =IF('D1-D2-D3'!BQ98="","",'D1-D2-D3'!BQ98) | CH94: =INDIRECT($J$4&"!C87") -> No. NOK parts found | DD94: =IF('D1-D2-D3'!DD98="","",'D1-D2-D3'!DD98)
H97: =INDIRECT($J$4&"!C88") -> Identification OK Parts | AD97: =IF('D1-D2-D3'!AD101="","",'D1-D2-D3'!AD101) | AU97: =INDIRECT($J$4&"!C88") -> Identification OK Parts | BQ97: =IF('D1-D2-D3'!BQ101="","",'D1-D2-D3'!BQ101) | CH97: =INDIRECT($J$4&"!C88") -> Identification OK Parts | DD97: =IF('D1-D2-D3'!DD101="","",'D1-D2-D3'!DD101)
CH99: =INDIRECT($J$4&"!C89") -> clean point | DD99: =IF('D1-D2-D3'!DD103="","",'D1-D2-D3'!DD103)
L101: =IF('D1-D2-D3'!L106:P106="","",'D1-D2-D3'!L106:P106) -> 0 | R101: ='D1-D2-D3'!R106 -> total amount of sorted parts | AR101: =IF('D1-D2-D3'!AR106:AV106="","",'D1-D2-D3'!AR106:AV106) -> 0 | AX101: ='D1-D2-D3'!AX106 -> total amount of NOK parts found | CB101: =IF('D1-D2-D3'!CB106:CF106="","",'D1-D2-D3'!CB106:CF106) -> 0 | CH101: ='D1-D2-D3'!CH106 -> total amount of OK parts identified
D103: ='D1-D2-D3'!D109 -> Comments
B110: ='D4.5Why''s-D5-D6'!B6 -> D4 - Root cause analysis
D113: ='D4.5Why''s-D5-D6'!D19 -> Factors identification/Influent factors | AH113: ='D4.5Why''s-D5-D6'!J18 -> Why 1 | AS113: ='D4.5Why''s-D5-D6'!L18 -> Why 2 | BF113: ='D4.5Why''s-D5-D6'!O18 -> Why 3 | BS113: ='D4.5Why''s-D5-D6'!Q18 -> Why 4 | CF113: ='D4.5Why''s-D5-D6'!T18 -> Why 5 | CS113: ='D4.5Why''s-D5-D6'!X16 -> Fault category | DC113: ='D4.5Why''s-D5-D6'!Z16 -> Verification of the causes
D115: ='D4.5Why''s-D5-D6'!D40 -> Technical consideration factors | E115: =IF(ISNA('D4.5Why''s-D5-D6'!AX19),"",'D4.5Why''s-D5-D6'!AX19) | M115: =IF(ISNA('D4.5Why''s-D5-D6'!AY19),"",'D4.5Why''s-D5-D6'!AY19) | AH115: =IF(ISNA('D4.5Why''s-D5-D6'!AZ19),"",'D4.5Why''s-D5-D6'!AZ19) | AS115: =IF(ISNA('D4.5Why''s-D5-D6'!BA19),"",'D4.5Why''s-D5-D6'!BA19) | BF115: =IF(ISNA('D4.5Why''s-D5-D6'!BB19),"",'D4.5Why''s-D5-D6'!BB19) | BS115: =IF(ISNA('D4.5Why''s-D5-D6'!BC19),"",'D4.5Why''s-D5-D6'!BC19) | CF115: =IF(ISNA('D4.5Why''s-D5-D6'!BD19),"",'D4.5Why''s-D5-D6'!BD19) | CS115: =IF(ISNA('D4.5Why''s-D5-D6'!BE19),"",'D4.5Why''s-D5-D6'!BE19) | DC115: =IF(ISNA('D4.5Why''s-D5-D6'!BF19),"",'D4.5Why''s-D5-D6'!BF19)
E116: =IF(ISNA('D4.5Why''s-D5-D6'!AX20),"",'D4.5Why''s-D5-D6'!AX20) | M116: =IF(ISNA('D4.5Why''s-D5-D6'!AY20),"",'D4.5Why''s-D5-D6'!AY20) | AH116: =IF(ISNA('D4.5Why''s-D5-D6'!AZ20),"",'D4.5Why''s-D5-D6'!AZ20) | AS116: =IF(ISNA('D4.5Why''s-D5-D6'!BA20),"",'D4.5Why''s-D5-D6'!BA20) | BF116: =IF(ISNA('D4.5Why''s-D5-D6'!BB20),"",'D4.5Why''s-D5-D6'!BB20) | BS116: =IF(ISNA('D4.5Why''s-D5-D6'!BC20),"",'D4.5Why''s-D5-D6'!BC20) | CF116: =IF(ISNA('D4.5Why''s-D5-D6'!BD20),"",'D4.5Why''s-D5-D6'!BD20) | CS116: =IF(ISNA('D4.5Why''s-D5-D6'!BE20),"",'D4.5Why''s-D5-D6'!BE20) | DC116: =IF(ISNA('D4.5Why''s-D5-D6'!BF20),"",'D4.5Why''s-D5-D6'!BF20)
E117: =IF(ISNA('D4.5Why''s-D5-D6'!AX21),"",'D4.5Why''s-D5-D6'!AX21) | M117: =IF(ISNA('D4.5Why''s-D5-D6'!AY21),"",'D4.5Why''s-D5-D6'!AY21) | AH117: =IF(ISNA('D4.5Why''s-D5-D6'!AZ21),"",'D4.5Why''s-D5-D6'!AZ21) | AS117: =IF(ISNA('D4.5Why''s-D5-D6'!BA21),"",'D4.5Why''s-D5-D6'!BA21) | BF117: =IF(ISNA('D4.5Why''s-D5-D6'!BB21),"",'D4.5Why''s-D5-D6'!BB21) | BS117: =IF(ISNA('D4.5Why''s-D5-D6'!BC21),"",'D4.5Why''s-D5-D6'!BC21) | CF117: =IF(ISNA('D4.5Why''s-D5-D6'!BD21),"",'D4.5Why''s-D5-D6'!BD21) | CS117: =IF(ISNA('D4.5Why''s-D5-D6'!BE21),"",'D4.5Why''s-D5-D6'!BE21) | DC117: =IF(ISNA('D4.5Why''s-D5-D6'!BF21),"",'D4.5Why''s-D5-D6'!BF21)
E118: =IF(ISNA('D4.5Why''s-D5-D6'!AX22),"",'D4.5Why''s-D5-D6'!AX22) | M118: =IF(ISNA('D4.5Why''s-D5-D6'!AY22),"",'D4.5Why''s-D5-D6'!AY22) | AH118: =IF(ISNA('D4.5Why''s-D5-D6'!AZ22),"",'D4.5Why''s-D5-D6'!AZ22) | AS118: =IF(ISNA('D4.5Why''s-D5-D6'!BA22),"",'D4.5Why''s-D5-D6'!BA22) | BF118: =IF(ISNA('D4.5Why''s-D5-D6'!BB22),"",'D4.5Why''s-D5-D6'!BB22) | BS118: =IF(ISNA('D4.5Why''s-D5-D6'!BC22),"",'D4.5Why''s-D5-D6'!BC22) | CF118: =IF(ISNA('D4.5Why''s-D5-D6'!BD22),"",'D4.5Why''s-D5-D6'!BD22) | CS118: =IF(ISNA('D4.5Why''s-D5-D6'!BE22),"",'D4.5Why''s-D5-D6'!BE22) | DC118: =IF(ISNA('D4.5Why''s-D5-D6'!BF22),"",'D4.5Why''s-D5-D6'!BF22)
E119: =IF(ISNA('D4.5Why''s-D5-D6'!AX23),"",'D4.5Why''s-D5-D6'!AX23) | M119: =IF(ISNA('D4.5Why''s-D5-D6'!AY23),"",'D4.5Why''s-D5-D6'!AY23) | AH119: =IF(ISNA('D4.5Why''s-D5-D6'!AZ23),"",'D4.5Why''s-D5-D6'!AZ23) | AS119: =IF(ISNA('D4.5Why''s-D5-D6'!BA23),"",'D4.5Why''s-D5-D6'!BA23) | BF119: =IF(ISNA('D4.5Why''s-D5-D6'!BB23),"",'D4.5Why''s-D5-D6'!BB23) | BS119: =IF(ISNA('D4.5Why''s-D5-D6'!BC23),"",'D4.5Why''s-D5-D6'!BC23) | CF119: =IF(ISNA('D4.5Why''s-D5-D6'!BD23),"",'D4.5Why''s-D5-D6'!BD23) | CS119: =IF(ISNA('D4.5Why''s-D5-D6'!BE23),"",'D4.5Why''s-D5-D6'!BE23) | DC119: =IF(ISNA('D4.5Why''s-D5-D6'!BF23),"",'D4.5Why''s-D5-D6'!BF23)
E120: =IF(ISNA('D4.5Why''s-D5-D6'!AX24),"",'D4.5Why''s-D5-D6'!AX24) | M120: =IF(ISNA('D4.5Why''s-D5-D6'!AY24),"",'D4.5Why''s-D5-D6'!AY24) | AH120: =IF(ISNA('D4.5Why''s-D5-D6'!AZ24),"",'D4.5Why''s-D5-D6'!AZ24) | AS120: =IF(ISNA('D4.5Why''s-D5-D6'!BA24),"",'D4.5Why''s-D5-D6'!BA24) | BF120: =IF(ISNA('D4.5Why''s-D5-D6'!BB24),"",'D4.5Why''s-D5-D6'!BB24) | BS120: =IF(ISNA('D4.5Why''s-D5-D6'!BC24),"",'D4.5Why''s-D5-D6'!BC24) | CF120: =IF(ISNA('D4.5Why''s-D5-D6'!BD24),"",'D4.5Why''s-D5-D6'!BD24) | CS120: =IF(ISNA('D4.5Why''s-D5-D6'!BE24),"",'D4.5Why''s-D5-D6'!BE24) | DC120: =IF(ISNA('D4.5Why''s-D5-D6'!BF24),"",'D4.5Why''s-D5-D6'!BF24)
E121: =IF(ISNA('D4.5Why''s-D5-D6'!AX25),"",'D4.5Why''s-D5-D6'!AX25) | M121: =IF(ISNA('D4.5Why''s-D5-D6'!AY25),"",'D4.5Why''s-D5-D6'!AY25) | AH121: =IF(ISNA('D4.5Why''s-D5-D6'!AZ25),"",'D4.5Why''s-D5-D6'!AZ25) | AS121: =IF(ISNA('D4.5Why''s-D5-D6'!BA25),"",'D4.5Why''s-D5-D6'!BA25) | BF121: =IF(ISNA('D4.5Why''s-D5-D6'!BB25),"",'D4.5Why''s-D5-D6'!BB25) | BS121: =IF(ISNA('D4.5Why''s-D5-D6'!BC25),"",'D4.5Why''s-D5-D6'!BC25) | CF121: =IF(ISNA('D4.5Why''s-D5-D6'!BD25),"",'D4.5Why''s-D5-D6'!BD25) | CS121: =IF(ISNA('D4.5Why''s-D5-D6'!BE25),"",'D4.5Why''s-D5-D6'!BE25) | DC121: =IF(ISNA('D4.5Why''s-D5-D6'!BF25),"",'D4.5Why''s-D5-D6'!BF25)
E122: =IF(ISNA('D4.5Why''s-D5-D6'!AX26),"",'D4.5Why''s-D5-D6'!AX26) | M122: =IF(ISNA('D4.5Why''s-D5-D6'!AY26),"",'D4.5Why''s-D5-D6'!AY26) | AH122: =IF(ISNA('D4.5Why''s-D5-D6'!AZ26),"",'D4.5Why''s-D5-D6'!AZ26) | AS122: =IF(ISNA('D4.5Why''s-D5-D6'!BA26),"",'D4.5Why''s-D5-D6'!BA26) | BF122: =IF(ISNA('D4.5Why''s-D5-D6'!BB26),"",'D4.5Why''s-D5-D6'!BB26) | BS122: =IF(ISNA('D4.5Why''s-D5-D6'!BC26),"",'D4.5Why''s-D5-D6'!BC26) | CF122: =IF(ISNA('D4.5Why''s-D5-D6'!BD26),"",'D4.5Why''s-D5-D6'!BD26) | CS122: =IF(ISNA('D4.5Why''s-D5-D6'!BE26),"",'D4.5Why''s-D5-D6'!BE26) | DC122: =IF(ISNA('D4.5Why''s-D5-D6'!BF26),"",'D4.5Why''s-D5-D6'!BF26)
E123: =IF(ISNA('D4.5Why''s-D5-D6'!AX27),"",'D4.5Why''s-D5-D6'!AX27) | M123: =IF(ISNA('D4.5Why''s-D5-D6'!AY27),"",'D4.5Why''s-D5-D6'!AY27) | AH123: =IF(ISNA('D4.5Why''s-D5-D6'!AZ27),"",'D4.5Why''s-D5-D6'!AZ27) | AS123: =IF(ISNA('D4.5Why''s-D5-D6'!BA27),"",'D4.5Why''s-D5-D6'!BA27) | BF123: =IF(ISNA('D4.5Why''s-D5-D6'!BB27),"",'D4.5Why''s-D5-D6'!BB27) | BS123: =IF(ISNA('D4.5Why''s-D5-D6'!BC27),"",'D4.5Why''s-D5-D6'!BC27) | CF123: =IF(ISNA('D4.5Why''s-D5-D6'!BD27),"",'D4.5Why''s-D5-D6'!BD27) | CS123: =IF(ISNA('D4.5Why''s-D5-D6'!BE27),"",'D4.5Why''s-D5-D6'!BE27) | DC123: =IF(ISNA('D4.5Why''s-D5-D6'!BF27),"",'D4.5Why''s-D5-D6'!BF27)
E124: =IF(ISNA('D4.5Why''s-D5-D6'!AX28),"",'D4.5Why''s-D5-D6'!AX28) | M124: =IF(ISNA('D4.5Why''s-D5-D6'!AY28),"",'D4.5Why''s-D5-D6'!AY28) | AH124: =IF(ISNA('D4.5Why''s-D5-D6'!AZ28),"",'D4.5Why''s-D5-D6'!AZ28) | AS124: =IF(ISNA('D4.5Why''s-D5-D6'!BA28),"",'D4.5Why''s-D5-D6'!BA28) | BF124: =IF(ISNA('D4.5Why''s-D5-D6'!BB28),"",'D4.5Why''s-D5-D6'!BB28) | BS124: =IF(ISNA('D4.5Why''s-D5-D6'!BC28),"",'D4.5Why''s-D5-D6'!BC28) | CF124: =IF(ISNA('D4.5Why''s-D5-D6'!BD28),"",'D4.5Why''s-D5-D6'!BD28) | CS124: =IF(ISNA('D4.5Why''s-D5-D6'!BE28),"",'D4.5Why''s-D5-D6'!BE28) | DC124: =IF(ISNA('D4.5Why''s-D5-D6'!BF28),"",'D4.5Why''s-D5-D6'!BF28)
D126: ='D4.5Why''s-D5-D6'!J41 -> Systemic consideration | E126: =IF(ISNA('D4.5Why''s-D5-D6'!AX44),"",'D4.5Why''s-D5-D6'!AX44) | M126: =IF(ISNA('D4.5Why''s-D5-D6'!AY44),"",'D4.5Why''s-D5-D6'!AY44) | AH126: =IF(ISNA('D4.5Why''s-D5-D6'!AZ44),"",'D4.5Why''s-D5-D6'!AZ44) | AS126: =IF(ISNA('D4.5Why''s-D5-D6'!BA44),"",'D4.5Why''s-D5-D6'!BA44) | BF126: =IF(ISNA('D4.5Why''s-D5-D6'!BB44),"",'D4.5Why''s-D5-D6'!BB44) | BS126: =IF(ISNA('D4.5Why''s-D5-D6'!BC44),"",'D4.5Why''s-D5-D6'!BC44) | CF126: =IF(ISNA('D4.5Why''s-D5-D6'!BD44),"",'D4.5Why''s-D5-D6'!BD44) | CK126: =IF(ISNA('D4.5Why''s-D5-D6'!BC44),"",'D4.5Why''s-D5-D6'!BC44) | CS126: =IF(ISNA('D4.5Why''s-D5-D6'!BE44),"",'D4.5Why''s-D5-D6'!BE44) | DB126: =IF(ISNA('D4.5Why''s-D5-D6'!BD44),"",'D4.5Why''s-D5-D6'!BD44) | DC126: =IF(ISNA('D4.5Why''s-D5-D6'!BF44),"",'D4.5Why''s-D5-D6'!BF44)
E127: =IF(ISNA('D4.5Why''s-D5-D6'!AX45),"",'D4.5Why''s-D5-D6'!AX45) | M127: =IF(ISNA('D4.5Why''s-D5-D6'!AY45),"",'D4.5Why''s-D5-D6'!AY45) | AH127: =IF(ISNA('D4.5Why''s-D5-D6'!AZ45),"",'D4.5Why''s-D5-D6'!AZ45) | AS127: =IF(ISNA('D4.5Why''s-D5-D6'!BA45),"",'D4.5Why''s-D5-D6'!BA45) | BF127: =IF(ISNA('D4.5Why''s-D5-D6'!BB45),"",'D4.5Why''s-D5-D6'!BB45) | BS127: =IF(ISNA('D4.5Why''s-D5-D6'!BC45),"",'D4.5Why''s-D5-D6'!BC45) | CF127: =IF(ISNA('D4.5Why''s-D5-D6'!BD45),"",'D4.5Why''s-D5-D6'!BD45) | CK127: =IF(ISNA('D4.5Why''s-D5-D6'!BC45),"",'D4.5Why''s-D5-D6'!BC45) | CS127: =IF(ISNA('D4.5Why''s-D5-D6'!BE45),"",'D4.5Why''s-D5-D6'!BE45) | DB127: =IF(ISNA('D4.5Why''s-D5-D6'!BD45),"",'D4.5Why''s-D5-D6'!BD45) | DC127: =IF(ISNA('D4.5Why''s-D5-D6'!BF45),"",'D4.5Why''s-D5-D6'!BF45)
E128: =IF(ISNA('D4.5Why''s-D5-D6'!AX46),"",'D4.5Why''s-D5-D6'!AX46) | M128: =IF(ISNA('D4.5Why''s-D5-D6'!AY46),"",'D4.5Why''s-D5-D6'!AY46) | AH128: =IF(ISNA('D4.5Why''s-D5-D6'!AZ46),"",'D4.5Why''s-D5-D6'!AZ46) | AS128: =IF(ISNA('D4.5Why''s-D5-D6'!BA46),"",'D4.5Why''s-D5-D6'!BA46) | BF128: =IF(ISNA('D4.5Why''s-D5-D6'!BB46),"",'D4.5Why''s-D5-D6'!BB46) | BS128: =IF(ISNA('D4.5Why''s-D5-D6'!BC46),"",'D4.5Why''s-D5-D6'!BC46) | CF128: =IF(ISNA('D4.5Why''s-D5-D6'!BD46),"",'D4.5Why''s-D5-D6'!BD46) | CK128: =IF(ISNA('D4.5Why''s-D5-D6'!BC46),"",'D4.5Why''s-D5-D6'!BC46) | CS128: =IF(ISNA('D4.5Why''s-D5-D6'!BE46),"",'D4.5Why''s-D5-D6'!BE46) | DB128: =IF(ISNA('D4.5Why''s-D5-D6'!BD46),"",'D4.5Why''s-D5-D6'!BD46) | DC128: =IF(ISNA('D4.5Why''s-D5-D6'!BF46),"",'D4.5Why''s-D5-D6'!BF46)
E129: =IF(ISNA('D4.5Why''s-D5-D6'!AX47),"",'D4.5Why''s-D5-D6'!AX47) | M129: =IF(ISNA('D4.5Why''s-D5-D6'!AY47),"",'D4.5Why''s-D5-D6'!AY47) | AH129: =IF(ISNA('D4.5Why''s-D5-D6'!AZ47),"",'D4.5Why''s-D5-D6'!AZ47) | AS129: =IF(ISNA('D4.5Why''s-D5-D6'!BA47),"",'D4.5Why''s-D5-D6'!BA47) | BF129: =IF(ISNA('D4.5Why''s-D5-D6'!BB47),"",'D4.5Why''s-D5-D6'!BB47) | BS129: =IF(ISNA('D4.5Why''s-D5-D6'!BC47),"",'D4.5Why''s-D5-D6'!BC47) | CF129: =IF(ISNA('D4.5Why''s-D5-D6'!BD47),"",'D4.5Why''s-D5-D6'!BD47) | CK129: =IF(ISNA('D4.5Why''s-D5-D6'!BC47),"",'D4.5Why''s-D5-D6'!BC47) | CS129: =IF(ISNA('D4.5Why''s-D5-D6'!BE47),"",'D4.5Why''s-D5-D6'!BE47) | DB129: =IF(ISNA('D4.5Why''s-D5-D6'!BD47),"",'D4.5Why''s-D5-D6'!BD47) | DC129: =IF(ISNA('D4.5Why''s-D5-D6'!BF47),"",'D4.5Why''s-D5-D6'!BF47)
E130: =IF(ISNA('D4.5Why''s-D5-D6'!AX48),"",'D4.5Why''s-D5-D6'!AX48) | M130: =IF(ISNA('D4.5Why''s-D5-D6'!AY48),"",'D4.5Why''s-D5-D6'!AY48) | AH130: =IF(ISNA('D4.5Why''s-D5-D6'!AZ48),"",'D4.5Why''s-D5-D6'!AZ48) | AS130: =IF(ISNA('D4.5Why''s-D5-D6'!BA48),"",'D4.5Why''s-D5-D6'!BA48) | BF130: =IF(ISNA('D4.5Why''s-D5-D6'!BB48),"",'D4.5Why''s-D5-D6'!BB48) | BS130: =IF(ISNA('D4.5Why''s-D5-D6'!BC48),"",'D4.5Why''s-D5-D6'!BC48) | CF130: =IF(ISNA('D4.5Why''s-D5-D6'!BD48),"",'D4.5Why''s-D5-D6'!BD48) | CK130: =IF(ISNA('D4.5Why''s-D5-D6'!BC48),"",'D4.5Why''s-D5-D6'!BC48) | CS130: =IF(ISNA('D4.5Why''s-D5-D6'!BE48),"",'D4.5Why''s-D5-D6'!BE48) | DB130: =IF(ISNA('D4.5Why''s-D5-D6'!BD48),"",'D4.5Why''s-D5-D6'!BD48) | DC130: =IF(ISNA('D4.5Why''s-D5-D6'!BF48),"",'D4.5Why''s-D5-D6'!BF48)
E131: =IF(ISNA('D4.5Why''s-D5-D6'!AX49),"",'D4.5Why''s-D5-D6'!AX49) | M131: =IF(ISNA('D4.5Why''s-D5-D6'!AY49),"",'D4.5Why''s-D5-D6'!AY49) | AH131: =IF(ISNA('D4.5Why''s-D5-D6'!AZ49),"",'D4.5Why''s-D5-D6'!AZ49) | AS131: =IF(ISNA('D4.5Why''s-D5-D6'!BA49),"",'D4.5Why''s-D5-D6'!BA49) | BF131: =IF(ISNA('D4.5Why''s-D5-D6'!BB49),"",'D4.5Why''s-D5-D6'!BB49) | BS131: =IF(ISNA('D4.5Why''s-D5-D6'!BC49),"",'D4.5Why''s-D5-D6'!BC49) | CF131: =IF(ISNA('D4.5Why''s-D5-D6'!BD49),"",'D4.5Why''s-D5-D6'!BD49) | CK131: =IF(ISNA('D4.5Why''s-D5-D6'!BC49),"",'D4.5Why''s-D5-D6'!BC49) | CS131: =IF(ISNA('D4.5Why''s-D5-D6'!BE49),"",'D4.5Why''s-D5-D6'!BE49) | DB131: =IF(ISNA('D4.5Why''s-D5-D6'!BD49),"",'D4.5Why''s-D5-D6'!BD49) | DC131: =IF(ISNA('D4.5Why''s-D5-D6'!BF49),"",'D4.5Why''s-D5-D6'!BF49)
E132: =IF(ISNA('D4.5Why''s-D5-D6'!AX50),"",'D4.5Why''s-D5-D6'!AX50) | M132: =IF(ISNA('D4.5Why''s-D5-D6'!AY50),"",'D4.5Why''s-D5-D6'!AY50) | AH132: =IF(ISNA('D4.5Why''s-D5-D6'!AZ50),"",'D4.5Why''s-D5-D6'!AZ50) | AS132: =IF(ISNA('D4.5Why''s-D5-D6'!BA50),"",'D4.5Why''s-D5-D6'!BA50) | BF132: =IF(ISNA('D4.5Why''s-D5-D6'!BB50),"",'D4.5Why''s-D5-D6'!BB50) | BS132: =IF(ISNA('D4.5Why''s-D5-D6'!BC50),"",'D4.5Why''s-D5-D6'!BC50) | CF132: =IF(ISNA('D4.5Why''s-D5-D6'!BD50),"",'D4.5Why''s-D5-D6'!BD50) | CK132: =IF(ISNA('D4.5Why''s-D5-D6'!BC50),"",'D4.5Why''s-D5-D6'!BC50) | CS132: =IF(ISNA('D4.5Why''s-D5-D6'!BE50),"",'D4.5Why''s-D5-D6'!BE50) | DB132: =IF(ISNA('D4.5Why''s-D5-D6'!BD50),"",'D4.5Why''s-D5-D6'!BD50) | DC132: =IF(ISNA('D4.5Why''s-D5-D6'!BF50),"",'D4.5Why''s-D5-D6'!BF50)
E133: =IF(ISNA('D4.5Why''s-D5-D6'!AX51),"",'D4.5Why''s-D5-D6'!AX51) | M133: =IF(ISNA('D4.5Why''s-D5-D6'!AY51),"",'D4.5Why''s-D5-D6'!AY51) | AH133: =IF(ISNA('D4.5Why''s-D5-D6'!AZ51),"",'D4.5Why''s-D5-D6'!AZ51) | AS133: =IF(ISNA('D4.5Why''s-D5-D6'!BA51),"",'D4.5Why''s-D5-D6'!BA51) | BF133: =IF(ISNA('D4.5Why''s-D5-D6'!BB51),"",'D4.5Why''s-D5-D6'!BB51) | BS133: =IF(ISNA('D4.5Why''s-D5-D6'!BC51),"",'D4.5Why''s-D5-D6'!BC51) | CF133: =IF(ISNA('D4.5Why''s-D5-D6'!BD51),"",'D4.5Why''s-D5-D6'!BD51) | CK133: =IF(ISNA('D4.5Why''s-D5-D6'!BC51),"",'D4.5Why''s-D5-D6'!BC51) | CS133: =IF(ISNA('D4.5Why''s-D5-D6'!BE51),"",'D4.5Why''s-D5-D6'!BE51) | DB133: =IF(ISNA('D4.5Why''s-D5-D6'!BD51),"",'D4.5Why''s-D5-D6'!BD51) | DC133: =IF(ISNA('D4.5Why''s-D5-D6'!BF51),"",'D4.5Why''s-D5-D6'!BF51)
E134: =IF(ISNA('D4.5Why''s-D5-D6'!AX52),"",'D4.5Why''s-D5-D6'!AX52) | M134: =IF(ISNA('D4.5Why''s-D5-D6'!AY52),"",'D4.5Why''s-D5-D6'!AY52) | AH134: =IF(ISNA('D4.5Why''s-D5-D6'!AZ52),"",'D4.5Why''s-D5-D6'!AZ52) | AS134: =IF(ISNA('D4.5Why''s-D5-D6'!BA52),"",'D4.5Why''s-D5-D6'!BA52) | BF134: =IF(ISNA('D4.5Why''s-D5-D6'!BB52),"",'D4.5Why''s-D5-D6'!BB52) | BS134: =IF(ISNA('D4.5Why''s-D5-D6'!BC52),"",'D4.5Why''s-D5-D6'!BC52) | CF134: =IF(ISNA('D4.5Why''s-D5-D6'!BD52),"",'D4.5Why''s-D5-D6'!BD52) | CK134: =IF(ISNA('D4.5Why''s-D5-D6'!BC52),"",'D4.5Why''s-D5-D6'!BC52) | CS134: =IF(ISNA('D4.5Why''s-D5-D6'!BE52),"",'D4.5Why''s-D5-D6'!BE52) | DB134: =IF(ISNA('D4.5Why''s-D5-D6'!BD52),"",'D4.5Why''s-D5-D6'!BD52) | DC134: =IF(ISNA('D4.5Why''s-D5-D6'!BF52),"",'D4.5Why''s-D5-D6'!BF52)
E135: =IF(ISNA('D4.5Why''s-D5-D6'!AX53),"",'D4.5Why''s-D5-D6'!AX53) | M135: =IF(ISNA('D4.5Why''s-D5-D6'!AY53),"",'D4.5Why''s-D5-D6'!AY53) | AH135: =IF(ISNA('D4.5Why''s-D5-D6'!AZ53),"",'D4.5Why''s-D5-D6'!AZ53) | AS135: =IF(ISNA('D4.5Why''s-D5-D6'!BA53),"",'D4.5Why''s-D5-D6'!BA53) | BF135: =IF(ISNA('D4.5Why''s-D5-D6'!BB53),"",'D4.5Why''s-D5-D6'!BB53) | BS135: =IF(ISNA('D4.5Why''s-D5-D6'!BC53),"",'D4.5Why''s-D5-D6'!BC53) | CF135: =IF(ISNA('D4.5Why''s-D5-D6'!BD53),"",'D4.5Why''s-D5-D6'!BD53) | CK135: =IF(ISNA('D4.5Why''s-D5-D6'!BC53),"",'D4.5Why''s-D5-D6'!BC53) | CS135: =IF(ISNA('D4.5Why''s-D5-D6'!BE53),"",'D4.5Why''s-D5-D6'!BE53) | DB135: =IF(ISNA('D4.5Why''s-D5-D6'!BD53),"",'D4.5Why''s-D5-D6'!BD53) | DC135: =IF(ISNA('D4.5Why''s-D5-D6'!BF53),"",'D4.5Why''s-D5-D6'!BF53)
D137: ='D1-D2-D3'!D109 -> Comments
B143: ='D4.5Why''s-D5-D6'!AB6&"/ "& 'D4.5Why''s-D5-D6'!AF6 -> D5 - Corrective Action(s)/ D6 - Implementation of permanent corrective action(s)
D146: ='D4.5Why''s-D5-D6'!AB16&":" -> Action Plan: | CO146: =INDIRECT('D1-D2-D3'!$J$4&"!C233") -> Risk assessment
D149: ='D4.5Why''s-D5-D6'!D40 -> Technical consideration factors
D151: ='D4.5Why''s-D5-D6'!D19 -> Factors identification/Influent factors | AC151: ='D4.5Why''s-D5-D6'!AB18 -> Corrective Action | BQ151: =INDIRECT('D1-D2-D3'!$J$4&"!C83") -> Responsible | BZ151: =INDIRECT('D1-D2-D3'!$J$4&"!C166") -> Target Date | CG151: =INDIRECT('D1-D2-D3'!$J$4&"!C84") -> Impl. Date | CO151: =INDIRECT('D1-D2-D3'!$J$4&"!C256") -> Hazard/ Risk | DD151: ='Risk assesment (for D3 & D5)'!AO18 -> Level | DI151: =INDIRECT('D1-D2-D3'!$J$4&"!C259") -> Measures
D153: =IF(ISNA('D4.5Why''s-D5-D6'!BW19),"",'D4.5Why''s-D5-D6'!BW19) | I153: =IF(ISNA('D4.5Why''s-D5-D6'!BX19),"",'D4.5Why''s-D5-D6'!BX19) | AC153: =IF(ISNA('D4.5Why''s-D5-D6'!BY19),"",'D4.5Why''s-D5-D6'!BY19) | BQ153: =IF(ISNA('D4.5Why''s-D5-D6'!BZ19),"",'D4.5Why''s-D5-D6'!BZ19) | BZ153: =IF(ISNA('D4.5Why''s-D5-D6'!CA19),"",'D4.5Why''s-D5-D6'!CA19) | CG153: =IF(ISNA('D4.5Why''s-D5-D6'!CB19),"",'D4.5Why''s-D5-D6'!CB19) | CO153: =IF(ISNA('Risk assesment (for D3 & D5)'!CF31),"",'Risk assesment (for D3 & D5)'!CF31) | DD153: =IF(ISNA('Risk assesment (for D3 & D5)'!CG31),"",'Risk assesment (for D3 & D5)'!CG31) | DH153: =IF(ISNA('Risk assesment (for D3 & D5)'!CH31),"",'Risk assesment (for D3 & D5)'!CH31)
D154: =IF(ISNA('D4.5Why''s-D5-D6'!BW20),"",'D4.5Why''s-D5-D6'!BW20) | I154: =IF(ISNA('D4.5Why''s-D5-D6'!BX20),"",'D4.5Why''s-D5-D6'!BX20) | AC154: =IF(ISNA('D4.5Why''s-D5-D6'!BY20),"",'D4.5Why''s-D5-D6'!BY20) | BQ154: =IF(ISNA('D4.5Why''s-D5-D6'!BZ20),"",'D4.5Why''s-D5-D6'!BZ20) | BZ154: =IF(ISNA('D4.5Why''s-D5-D6'!CA20),"",'D4.5Why''s-D5-D6'!CA20) | CG154: =IF(ISNA('D4.5Why''s-D5-D6'!CB20),"",'D4.5Why''s-D5-D6'!CB20) | CO154: =IF(ISNA('Risk assesment (for D3 & D5)'!CF32),"",'Risk assesment (for D3 & D5)'!CF32) | DD154: =IF(ISNA('Risk assesment (for D3 & D5)'!CG32),"",'Risk assesment (for D3 & D5)'!CG32) | DH154: =IF(ISNA('Risk assesment (for D3 & D5)'!CH32),"",'Risk assesment (for D3 & D5)'!CH32)
D155: =IF(ISNA('D4.5Why''s-D5-D6'!BW21),"",'D4.5Why''s-D5-D6'!BW21) | I155: =IF(ISNA('D4.5Why''s-D5-D6'!BX21),"",'D4.5Why''s-D5-D6'!BX21) | AC155: =IF(ISNA('D4.5Why''s-D5-D6'!BY21),"",'D4.5Why''s-D5-D6'!BY21) | BQ155: =IF(ISNA('D4.5Why''s-D5-D6'!BZ21),"",'D4.5Why''s-D5-D6'!BZ21) | BZ155: =IF(ISNA('D4.5Why''s-D5-D6'!CA21),"",'D4.5Why''s-D5-D6'!CA21) | CG155: =IF(ISNA('D4.5Why''s-D5-D6'!CB21),"",'D4.5Why''s-D5-D6'!CB21) | CO155: =IF(ISNA('Risk assesment (for D3 & D5)'!CF33),"",'Risk assesment (for D3 & D5)'!CF33) | DD155: =IF(ISNA('Risk assesment (for D3 & D5)'!CG33),"",'Risk assesment (for D3 & D5)'!CG33) | DH155: =IF(ISNA('Risk assesment (for D3 & D5)'!CH33),"",'Risk assesment (for D3 & D5)'!CH33)
D156: =IF(ISNA('D4.5Why''s-D5-D6'!BW22),"",'D4.5Why''s-D5-D6'!BW22) | I156: =IF(ISNA('D4.5Why''s-D5-D6'!BX22),"",'D4.5Why''s-D5-D6'!BX22) | AC156: =IF(ISNA('D4.5Why''s-D5-D6'!BY22),"",'D4.5Why''s-D5-D6'!BY22) | BQ156: =IF(ISNA('D4.5Why''s-D5-D6'!BZ22),"",'D4.5Why''s-D5-D6'!BZ22) | BZ156: =IF(ISNA('D4.5Why''s-D5-D6'!CA22),"",'D4.5Why''s-D5-D6'!CA22) | CG156: =IF(ISNA('D4.5Why''s-D5-D6'!CB22),"",'D4.5Why''s-D5-D6'!CB22) | CO156: =IF(ISNA('Risk assesment (for D3 & D5)'!CF34),"",'Risk assesment (for D3 & D5)'!CF34) | DD156: =IF(ISNA('Risk assesment (for D3 & D5)'!CG34),"",'Risk assesment (for D3 & D5)'!CG34) | DH156: =IF(ISNA('Risk assesment (for D3 & D5)'!CH34),"",'Risk assesment (for D3 & D5)'!CH34)
D157: =IF(ISNA('D4.5Why''s-D5-D6'!BW23),"",'D4.5Why''s-D5-D6'!BW23) | I157: =IF(ISNA('D4.5Why''s-D5-D6'!BX23),"",'D4.5Why''s-D5-D6'!BX23) | AC157: =IF(ISNA('D4.5Why''s-D5-D6'!BY23),"",'D4.5Why''s-D5-D6'!BY23) | BQ157: =IF(ISNA('D4.5Why''s-D5-D6'!BZ23),"",'D4.5Why''s-D5-D6'!BZ23) | BZ157: =IF(ISNA('D4.5Why''s-D5-D6'!CA23),"",'D4.5Why''s-D5-D6'!CA23) | CG157: =IF(ISNA('D4.5Why''s-D5-D6'!CB23),"",'D4.5Why''s-D5-D6'!CB23) | CO157: =IF(ISNA('Risk assesment (for D3 & D5)'!CF35),"",'Risk assesment (for D3 & D5)'!CF35) | DD157: =IF(ISNA('Risk assesment (for D3 & D5)'!CG35),"",'Risk assesment (for D3 & D5)'!CG35) | DH157: =IF(ISNA('Risk assesment (for D3 & D5)'!CH35),"",'Risk assesment (for D3 & D5)'!CH35)
D158: =IF(ISNA('D4.5Why''s-D5-D6'!BW24),"",'D4.5Why''s-D5-D6'!BW24) | I158: =IF(ISNA('D4.5Why''s-D5-D6'!BX24),"",'D4.5Why''s-D5-D6'!BX24) | AC158: =IF(ISNA('D4.5Why''s-D5-D6'!BY24),"",'D4.5Why''s-D5-D6'!BY24) | BQ158: =IF(ISNA('D4.5Why''s-D5-D6'!BZ24),"",'D4.5Why''s-D5-D6'!BZ24) | BZ158: =IF(ISNA('D4.5Why''s-D5-D6'!CA24),"",'D4.5Why''s-D5-D6'!CA24) | CG158: =IF(ISNA('D4.5Why''s-D5-D6'!CB24),"",'D4.5Why''s-D5-D6'!CB24) | CO158: =IF(ISNA('Risk assesment (for D3 & D5)'!CF36),"",'Risk assesment (for D3 & D5)'!CF36) | DD158: =IF(ISNA('Risk assesment (for D3 & D5)'!CG36),"",'Risk assesment (for D3 & D5)'!CG36) | DH158: =IF(ISNA('Risk assesment (for D3 & D5)'!CH36),"",'Risk assesment (for D3 & D5)'!CH36)
D159: =IF(ISNA('D4.5Why''s-D5-D6'!BW25),"",'D4.5Why''s-D5-D6'!BW25) | I159: =IF(ISNA('D4.5Why''s-D5-D6'!BX25),"",'D4.5Why''s-D5-D6'!BX25) | AC159: =IF(ISNA('D4.5Why''s-D5-D6'!BY25),"",'D4.5Why''s-D5-D6'!BY25) | BQ159: =IF(ISNA('D4.5Why''s-D5-D6'!BZ25),"",'D4.5Why''s-D5-D6'!BZ25) | BZ159: =IF(ISNA('D4.5Why''s-D5-D6'!CA25),"",'D4.5Why''s-D5-D6'!CA25) | CG159: =IF(ISNA('D4.5Why''s-D5-D6'!CB25),"",'D4.5Why''s-D5-D6'!CB25) | CO159: =IF(ISNA('Risk assesment (for D3 & D5)'!CF37),"",'Risk assesment (for D3 & D5)'!CF37) | DD159: =IF(ISNA('Risk assesment (for D3 & D5)'!CG37),"",'Risk assesment (for D3 & D5)'!CG37) | DH159: =IF(ISNA('Risk assesment (for D3 & D5)'!CH37),"",'Risk assesment (for D3 & D5)'!CH37)
D160: =IF(ISNA('D4.5Why''s-D5-D6'!BW26),"",'D4.5Why''s-D5-D6'!BW26) | I160: =IF(ISNA('D4.5Why''s-D5-D6'!BX26),"",'D4.5Why''s-D5-D6'!BX26) | AC160: =IF(ISNA('D4.5Why''s-D5-D6'!BY26),"",'D4.5Why''s-D5-D6'!BY26) | BQ160: =IF(ISNA('D4.5Why''s-D5-D6'!BZ26),"",'D4.5Why''s-D5-D6'!BZ26) | BZ160: =IF(ISNA('D4.5Why''s-D5-D6'!CA26),"",'D4.5Why''s-D5-D6'!CA26) | CG160: =IF(ISNA('D4.5Why''s-D5-D6'!CB26),"",'D4.5Why''s-D5-D6'!CB26) | CO160: =IF(ISNA('Risk assesment (for D3 & D5)'!CF38),"",'Risk assesment (for D3 & D5)'!CF38) | DD160: =IF(ISNA('Risk assesment (for D3 & D5)'!CG38),"",'Risk assesment (for D3 & D5)'!CG38) | DH160: =IF(ISNA('Risk assesment (for D3 & D5)'!CH38),"",'Risk assesment (for D3 & D5)'!CH38)
D161: =IF(ISNA('D4.5Why''s-D5-D6'!BW27),"",'D4.5Why''s-D5-D6'!BW27) | I161: =IF(ISNA('D4.5Why''s-D5-D6'!BX27),"",'D4.5Why''s-D5-D6'!BX27) | AC161: =IF(ISNA('D4.5Why''s-D5-D6'!BY27),"",'D4.5Why''s-D5-D6'!BY27) | BQ161: =IF(ISNA('D4.5Why''s-D5-D6'!BZ27),"",'D4.5Why''s-D5-D6'!BZ27) | BZ161: =IF(ISNA('D4.5Why''s-D5-D6'!CA27),"",'D4.5Why''s-D5-D6'!CA27) | CG161: =IF(ISNA('D4.5Why''s-D5-D6'!CB27),"",'D4.5Why''s-D5-D6'!CB27) | CO161: =IF(ISNA('Risk assesment (for D3 & D5)'!CF39),"",'Risk assesment (for D3 & D5)'!CF39) | DD161: =IF(ISNA('Risk assesment (for D3 & D5)'!CG39),"",'Risk assesment (for D3 & D5)'!CG39) | DH161: =IF(ISNA('Risk assesment (for D3 & D5)'!CH39),"",'Risk assesment (for D3 & D5)'!CH39)
D162: =IF(ISNA('D4.5Why''s-D5-D6'!BW28),"",'D4.5Why''s-D5-D6'!BW28) | I162: =IF(ISNA('D4.5Why''s-D5-D6'!BX28),"",'D4.5Why''s-D5-D6'!BX28) | AC162: =IF(ISNA('D4.5Why''s-D5-D6'!BY28),"",'D4.5Why''s-D5-D6'!BY28) | BQ162: =IF(ISNA('D4.5Why''s-D5-D6'!BZ28),"",'D4.5Why''s-D5-D6'!BZ28) | BZ162: =IF(ISNA('D4.5Why''s-D5-D6'!CA28),"",'D4.5Why''s-D5-D6'!CA28) | CG162: =IF(ISNA('D4.5Why''s-D5-D6'!CB28),"",'D4.5Why''s-D5-D6'!CB28) | CO162: =IF(ISNA('Risk assesment (for D3 & D5)'!CF40),"",'Risk assesment (for D3 & D5)'!CF40) | DD162: =IF(ISNA('Risk assesment (for D3 & D5)'!CG40),"",'Risk assesment (for D3 & D5)'!CG40) | DH162: =IF(ISNA('Risk assesment (for D3 & D5)'!CH40),"",'Risk assesment (for D3 & D5)'!CH40)
D164: ='D4.5Why''s-D5-D6'!J41 -> Systemic consideration
D166: =IF(ISNA('D4.5Why''s-D5-D6'!BW44),"",'D4.5Why''s-D5-D6'!BW44) | H166: =IF(ISNA('D4.5Why''s-D5-D6'!BX44),"",'D4.5Why''s-D5-D6'!BX44) | I166: =IF(ISNA('D4.5Why''s-D5-D6'!BX44),"",'D4.5Why''s-D5-D6'!BX44) | AB166: =IF(ISNA('D4.5Why''s-D5-D6'!BY44),"",'D4.5Why''s-D5-D6'!BY44) | AC166: =IF(ISNA('D4.5Why''s-D5-D6'!BY44),"",'D4.5Why''s-D5-D6'!BY44) | BQ166: =IF(ISNA('D4.5Why''s-D5-D6'!BZ44),"",'D4.5Why''s-D5-D6'!BZ44) | BZ166: =IF(ISNA('D4.5Why''s-D5-D6'!CA44),"",'D4.5Why''s-D5-D6'!CA44) | CG166: =IF(ISNA('D4.5Why''s-D5-D6'!CB44),"",'D4.5Why''s-D5-D6'!CB44) | CO166: =IF(ISNA('Risk assesment (for D3 & D5)'!CF42),"",'Risk assesment (for D3 & D5)'!CF42) | DD166: =IF(ISNA('Risk assesment (for D3 & D5)'!CG42),"",'Risk assesment (for D3 & D5)'!CG42) | DH166: =IF(ISNA('Risk assesment (for D3 & D5)'!CH42),"",'Risk assesment (for D3 & D5)'!CH42)
D167: =IF(ISNA('D4.5Why''s-D5-D6'!BW45),"",'D4.5Why''s-D5-D6'!BW45) | H167: =IF(ISNA('D4.5Why''s-D5-D6'!BX45),"",'D4.5Why''s-D5-D6'!BX45) | I167: =IF(ISNA('D4.5Why''s-D5-D6'!BX45),"",'D4.5Why''s-D5-D6'!BX45) | AB167: =IF(ISNA('D4.5Why''s-D5-D6'!BY45),"",'D4.5Why''s-D5-D6'!BY45) | AC167: =IF(ISNA('D4.5Why''s-D5-D6'!BY45),"",'D4.5Why''s-D5-D6'!BY45) | BQ167: =IF(ISNA('D4.5Why''s-D5-D6'!BZ45),"",'D4.5Why''s-D5-D6'!BZ45) | BZ167: =IF(ISNA('D4.5Why''s-D5-D6'!CA45),"",'D4.5Why''s-D5-D6'!CA45) | CG167: =IF(ISNA('D4.5Why''s-D5-D6'!CB45),"",'D4.5Why''s-D5-D6'!CB45) | CO167: =IF(ISNA('Risk assesment (for D3 & D5)'!CF43),"",'Risk assesment (for D3 & D5)'!CF43) | DD167: =IF(ISNA('Risk assesment (for D3 & D5)'!CG43),"",'Risk assesment (for D3 & D5)'!CG43) | DH167: =IF(ISNA('Risk assesment (for D3 & D5)'!CH43),"",'Risk assesment (for D3 & D5)'!CH43)
...

Sheet 8D-Report (no link)
R2: =INDIRECT($J$4&"!C230") -> 8D-report | CG2: 4.15.02.00.
C4: =INDIRECT($J$4&"!C5") -> Language | J4: ENGLISH | AA4: =INDIRECT($J$4&"!C3") -> PSS No. | AZ4: =INDIRECT($J$4&"!C6") -> Fault type
C7: =INDIRECT($J$4&"!C8") -> Kroschu plant | AF7: =INDIRECT($J$4&"!C9") -> Opening date | BM7: ='D1-D2-D3'!BU7 -> Report version | DV7: 1 | DW7: =IF(DX7="","",MAX($DW$6:DW6)+1) -> 1 | DX7: =IF($D14=DropDown!$N$8,DropDown!N5,"") -> Int. KSK-No. | DY7: =VLOOKUP(DV7,$DW$7:$DX$9,2,FALSE) -> Int. KSK-No.
DV8: 2 | DW8: =IF(DX8="","",MAX($DW$6:DW7)+1) | DX8: =IF($D14=DropDown!$N$9,DropDown!N6,"")
C9: =INDIRECT($J$4&"!C10") -> Customer | AF9: =INDIRECT($J$4&"!C11") -> Project | BM9: =INDIRECT($J$4&"!C12") -> Customer complaint No. | DV9: 3 | DW9: =IF(DX9="","",MAX($DW$6:DW8)+1) | DX9: =IF($D14=DropDown!$N$10,DropDown!N7,"")
B11: ='D1-D2-D3'!B11:AR12 -> Basic Data
D14: KSK | AM14: =DY7 -> Int. KSK-No. | CC14: =INDIRECT($J$4&"!C21") -> Production date/time
D17: =INDIRECT($J$4&"!C17") -> Index | AM17: =INDIRECT($J$4&"!C16") -> Lfd./Serial | CC17: Safety-relevant characterisitc
B20: ='D1-D2-D3'!B18 -> D1 - Team
D22: =INDIRECT($J$4&"!C23") -> Coordinator (/Champion) | BL22: =INDIRECT($J$4&"!C26") -> Sponsor
D23: =INDIRECT($J$4&"!C24") -> Name, prename | W23: =INDIRECT($J$4&"!C25") -> Department/function Contact data | BK23: =INDIRECT($J$4&"!C24") -> Name, prename | CD23: =INDIRECT($J$4&"!C25") -> Department/function Contact data
D26: =INDIRECT($J$4&"!C27") -> Members
B35: =INDIRECT($J$4&"!C28") -> D2 - Problem description
D38: =INDIRECT($J$4&"!C29") -> NOK PART | BL38: =INDIRECT($J$4&"!C30") -> OK PART
D45: =INDIRECT($J$4&"!C65") -> Symptom description | AV45: =INDIRECT($J$4&"!C43") -> IS | CH45: =INDIRECT($J$4&"!C44") -> IS NOT
AS46: =INDIRECT($J$4&"!C45") -> What | AV46: =INDIRECT($J$4&"!C49") -> Which product/process does the problem concern ? | CH46: =INDIRECT($J$4&"!C57") -> Are there comparable products/processes where the problem did not occur ?
D47: =INDIRECT($J$4&"!C66") -> Problem description
AV48: =INDIRECT($J$4&"!C50") -> What is the deviation ? | CH48: =INDIRECT($J$4&"!C58") -> Are additional deviations of the affected product/process expected ?
D50: =INDIRECT($J$4&"!C31")&" & "&INDIRECT($J$4&"!C32") -> Fault code & Fault description | AS50: =INDIRECT($J$4&"!C46") -> Where | AV50: =INDIRECT($J$4&"!C51") -> Where was the product/process when the deviation first occurred ? | CH50: =INDIRECT($J$4&"!C59") -> Where else could the deviation occur ?
D51: =VLOOKUP(AH50,'Fault catalogue'!A1:C573,3,0) -> #N/A
AV52: =INDIRECT($J$4&"!C52") -> Where in the product/process did the deviation occur ? | CH52: =INDIRECT($J$4&"!C60") -> What are the names of the neighbouring products/processes and which of them are not affected by the deviation ?
D53: =INDIRECT($J$4&"!C33") -> Fault location
AS54: =INDIRECT($J$4&"!C47") -> When | AV54: =INDIRECT($J$4&"!C53") -> When was the deviation first detected ? (Date of occurrence & life cycle) | CH54: =INDIRECT($J$4&"!C61") -> Can the problem have occurred in an earlier phase/time ?
D55: =INDIRECT($J$4&"!C34") -> Workplace
D56: =INDIRECT($J$4&"!C35") -> Qualification | AV56: =INDIRECT($J$4&"!C54") -> Is there a recognisable systematic of failures ? (single failure, continuous increase/fall, random or cyclical) ? | CH56: =INDIRECT($J$4&"!C62") -> Can additional failures be expected since the discovery ?
D57: =INDIRECT($J$4&"!C36") -> Line
D58: =INDIRECT($J$4&"!C37") -> Team | AS58: =INDIRECT($J$4&"!C48") -> How many | AV58: =INDIRECT($J$4&"!C55") -> How many failures ? (number & PPM's) | CH58: =INDIRECT($J$4&"!C63") -> How many more can be expected in the future ?
D59: =INDIRECT($J$4&"!C38") -> Equipment
D60: =INDIRECT($J$4&"!C39")&":" -> Repetitive fault: | R60: =INDIRECT($J$4&"!C40")&":" -> If yes, PSS No./ 8D No.: | AV60: =INDIRECT($J$4&"!C56") -> Which persons are affected ? What costs have been incurred so far ? Will these rise, fall or remain stable ? | CH60: =INDIRECT($J$4&"!C64") -> What can lead to worse/better circumstances ?
B64: =INDIRECT($J$4&"!C67") -> D3 - Immediate action(s)
BR65: =INDIRECT($J$4&"!C68") -> Status | DI65: =INDIRECT($J$4&"!C69") -> Date
D68: =INDIRECT($J$4&"!C70") -> Were the relevant emloyees informed ? | AR68: =INDIRECT($J$4&"!C69") -> Date | BX68: =INDIRECT($J$4&"!C83") -> Responsible
D70: =INDIRECT($J$4&"!C71") -> Limitation of affected products
D72: =INDIRECT($J$4&"!C72") -> Is it possible to do a limitation of the affected products ? | BK72: =INDIRECT($J$4&"!C73") -> delivered to the customer | BY72: =INDIRECT($J$4&"!C74") -> on transit | CJ72: =INDIRECT($J$4&"!C75") -> at Kroschu | CT72: =SUM(BL72,BZ72,CK72) -> 0 | CZ72: =INDIRECT($J$4&"!C76") -> total amount of affected products
G74: =INDIRECT($J$4&"!C80") -> Action | BM74: =INDIRECT($J$4&"!C233") -> Risk assessment | CR74: =INDIRECT($J$4&"!C81") -> Effectiveness verification
T75: =INDIRECT($J$4&"!C80") -> Action | AO75: =INDIRECT($J$4&"!C262") -> Start date | AV75: =INDIRECT($J$4&"!C263") -> Closing date | BD75: =INDIRECT($J$4&"!C83") -> Responsible | BM75: =INDIRECT($J$4&"!C256") -> Hazard/ Risk | CB75: =INDIRECT($J$4&"!C246") -> Level | CF75: =INDIRECT($J$4&"!C259") -> Measures | CR75: =INDIRECT($J$4&"!C82") -> Method | DC75: =INDIRECT($J$4&"!C69") -> Date | DH75: =INDIRECT($J$4&"!C83") -> Responsible | DN75: =INDIRECT($J$4&"!C264") -> Result
D77: =INDIRECT($J$4&"!C77") -> Measures for continuing secure production at customer
D80: =INDIRECT($J$4&"!C78") -> Measures for continuing delivery | CB80: ='Risk assesment (for D3 & D5)'!AO22
CB81: ='Risk assesment (for D3 & D5)'!AO23
CB82: ='Risk assesment (for D3 & D5)'!AO24
D83: =INDIRECT($J$4&"!C79") -> Measures for continuing Kroschu-production | CB83: ='Risk assesment (for D3 & D5)'!AO25
CB84: ='Risk assesment (for D3 & D5)'!AO26
CB85: ='Risk assesment (for D3 & D5)'!AO27
D87: =INDIRECT($J$4&"!C85") -> Sorting actions | H87: =INDIRECT($J$4&"!C73") -> delivered to the customer | AU87: =INDIRECT($J$4&"!C74") -> on transit | CH87: =INDIRECT($J$4&"!C75") -> at Kroschu
H89: =INDIRECT($J$4&"!C85") -> Sorting actions | AU89: =INDIRECT($J$4&"!C85") -> Sorting actions | CH89: =INDIRECT($J$4&"!C85") -> Sorting actions
H91: =INDIRECT($J$4&"!C86") -> Quantity sorted | AU91: =INDIRECT($J$4&"!C86") -> Quantity sorted | CH91: =INDIRECT($J$4&"!C86") -> Quantity sorted
H94: =INDIRECT($J$4&"!C87") -> No. NOK parts found | AU94: =INDIRECT($J$4&"!C87") -> No. NOK parts found | CH94: =INDIRECT($J$4&"!C87") -> No. NOK parts found
H97: =INDIRECT($J$4&"!C88") -> Identification OK Parts | AU97: =INDIRECT($J$4&"!C88") -> Identification OK Parts | CH97: =INDIRECT($J$4&"!C88") -> Identification OK Parts
CH99: =INDIRECT($J$4&"!C89") -> clean point
L101: =SUM(AD91,BQ91,DD91) -> 0 | R101: =INDIRECT($J$4&"!C90") -> total amount of sorted parts | AR101: =SUM(AD94,BQ94,DD94) -> 0 | AX101: =INDIRECT($J$4&"!C91") -> total amount of NOK parts found | BY101: =L101-AR101 -> 0 | CD101: =INDIRECT($J$4&"!C92") -> total amount of OK parts identified
D103: =INDIRECT($J$4&"!C93") -> Comments
B110: =INDIRECT($J$4&"!C145") -> D4 - Root cause analysis
D113: =INDIRECT($J$4&"!C149")&" / "& INDIRECT($J$4&"!C151") -> Factors identification / Influent factors | AH113: =INDIRECT($J$4&"!C152") -> Why 1 | AS113: =INDIRECT($J$4&"!C153") -> Why 2 | BF113: =INDIRECT($J$4&"!C154") -> Why 3 | BS113: =INDIRECT($J$4&"!C155") -> Why 4 | CF113: =INDIRECT($J$4&"!C156") -> Why 5 | CS113: =INDIRECT($J$4&"!C157") -> Fault category | DC113: =INDIRECT($J$4&"!C158") -> Verification of the causes
D115: =INDIRECT($J$4&"!C137") -> Technical consideration
D126: =INDIRECT($J$4&"!C138") -> Systemic consideration
D137: =INDIRECT($J$4&"!C93") -> Comments
B143: =INDIRECT($J$4&"!C161")&" / "& INDIRECT($J$4&"!C162") -> D5 - Corrective Action(s) / D6 - Implementation of permanent corrective action(s)
D146: =INDIRECT($J$4&"!C163")&":" -> Action Plan: | CO146: =INDIRECT('D1-D2-D3'!$J$4&"!C233") -> Risk assessment
D149: =INDIRECT($J$4&"!C137") -> Technical consideration
D151: =INDIRECT($J$4&"!C149")&" / "& INDIRECT($J$4&"!C151") -> Factors identification / Influent factors | AC151: =INDIRECT($J$4&"!C164") -> Corrective Action | BQ151: =INDIRECT($J$4&"!C83") -> Responsible | BZ151: =INDIRECT($J$4&"!C166") -> Target Date | CG151: =INDIRECT($J$4&"!C84") -> Impl. Date | CO151: =INDIRECT($J$4&"!C256") -> Hazard/ Risk | DD151: =INDIRECT($J$4&"!C246") -> Level | DI151: =INDIRECT($J$4&"!C259") -> Measures
D164: =INDIRECT($J$4&"!C138") -> Systemic consideration
C178: =INDIRECT($J$4&"!C190") -> Verification of effectiveness of corrective actions
D181: =INDIRECT($J$4&"!C149") -> Factors identification | H181: =INDIRECT($J$4&"!C192") -> Result and evidence of effectiveness check and comment
D182: =INDIRECT($J$4&"!C139") -> Occurrence
D190: =INDIRECT($J$4&"!C140") -> Non-detection
B200: =INDIRECT($J$4&"!C193") -> D7 - Preventive Actions | BR200: =INDIRECT($J$4&"!C68") -> Status | CZ200: =IF('D6.Verification-D7-D8'!Y46="","",'D6.Verification-D7-D8'!$Y$46) | DI200: =INDIRECT($J$4&"!C69") -> Date
D202: =INDIRECT($J$4&"!C194") -> Documentation - Standard updates
D205: =INDIRECT($J$4&"!C195") -> Documentation | Q205: =INDIRECT($J$4&"!C266")&"/"& INDIRECT($J$4&"!C267") -> New/Updated | W205: =INDIRECT($J$4&"!C196") -> Designation | AK205: =INDIRECT($J$4&"!C166") -> Target Date | AS205: =INDIRECT($J$4&"!C84") -> Impl. Date | BA205: =INDIRECT($J$4&"!C83") -> Responsible | BK205: =INDIRECT($J$4&"!C195") -> Documentation | BY205: =INDIRECT($J$4&"!C266")&"/"& INDIRECT($J$4&"!C267") -> New/Updated | CE205: =INDIRECT($J$4&"!C196") -> Designation | CT205: =INDIRECT($J$4&"!C166") -> Target Date | DB205: =INDIRECT($J$4&"!C84") -> Impl. Date | DJ205: =INDIRECT($J$4&"!C83") -> Responsible
D206: =INDIRECT($J$4&"!C197") -> FMEA | BK206: =INDIRECT($J$4&"!C202") -> Lessons Learned Card
D207: =INDIRECT($J$4&"!C198") -> PCP | BK207: =INDIRECT($J$4&"!C203") -> Training standard | BW207: =IF('D6.Verification-D7-D8'!G57="","",'D6.Verification-D7-D8'!G57)
D208: =INDIRECT($J$4&"!C199") -> WI | BK208: =INDIRECT($J$4&"!C204") -> Procedure | BW208: =IF('D6.Verification-D7-D8'!G58="","",'D6.Verification-D7-D8'!G58)
D209: =INDIRECT($J$4&"!C200") -> Maintenance Plan | BK209: =INDIRECT($J$4&"!C205") -> Specification | BW209: =IF('D6.Verification-D7-D8'!G59="","",'D6.Verification-D7-D8'!G59)
D210: =INDIRECT($J$4&"!C201") -> Drawing | BK210: =INDIRECT($J$4&"!C135") -> Others | BW210: =IF('D6.Verification-D7-D8'!G60="","",'D6.Verification-D7-D8'!G60)
C212: =INDIRECT($J$4&"!C206") -> Implementation of measures to similar processes/products
C214: =INDIRECT($J$4&"!C207") -> Processes | CM214: =INDIRECT($J$4&"!C265") -> Inform Prevention-Team | CO214: Mail to: | CV214: pss@ksab.kroschu.com
D216: =INDIRECT($J$4&"!C208") -> Concerned processes | Y216: =INDIRECT($J$4&"!C80") -> Action | CO216: =INDIRECT($J$4&"!C83") -> Responsible | DB216: =INDIRECT($J$4&"!C211")&" - "& INDIRECT($J$4&"!C69") -> E-mail sent to responsible - Date
C221: =INDIRECT($J$4&"!C212") -> Products
D223: =INDIRECT($J$4&"!C210") -> Concerned products | Y223: =INDIRECT($J$4&"!C80") -> Action | CO223: =INDIRECT($J$4&"!C83") -> Responsible | DB223: =INDIRECT($J$4&"!C211")&" - "& INDIRECT($J$4&"!C69") -> E-mail sent to responsible - Date
B230: =INDIRECT($J$4&"!C214") -> D8 - PSS closure | BF230: =INDIRECT($J$4&"!C217")&":" -> Status of complaint: | DI230: =INDIRECT($J$4&"!C216") -> Last Update
D233: =INDIRECT($J$4&"!C221") -> Position | Y233: =INDIRECT($J$4&"!C24") -> Name, prename | AV233: =INDIRECT($J$4&"!C69") -> Date | BW233: =INDIRECT($J$4&"!C232") -> Comments, conclusion (result of final discussion)
D234: =INDIRECT($J$4&"!C222") -> PSC | AV234: =INDIRECT($J$4&"!C227") -> informed on
D235: =INDIRECT($J$4&"!C223") -> Responsible Q | AV235: =INDIRECT($J$4&"!C227") -> informed on
D236: =INDIRECT($J$4&"!C224") -> AP-team leader | AV236: =INDIRECT($J$4&"!C228") -> verified on
D237: =INDIRECT($J$4&"!C225") -> Problem coordinator | AV237: =INDIRECT($J$4&"!C229") -> closed on

Sheet DropDown
O1: 04_KSSB
A2: Hotline | C2: CZECH | J2: =INDIRECT('D1-D2-D3'!$J$4&"!C96") -> Page 2: D4 | O2: 07_KSSE
A3: PPM-0km | C3: DEUTSCH | J3: =INDIRECT('D1-D2-D3'!$J$4&"!C97") -> Data/Facts/Numbers | O3: 08_KSRB
A4: Field Issue | C4: ENGLISH | J4: =INDIRECT('D1-D2-D3'!$J$4&"!C98") -> Rework | O4: 09_KSTN-Be2
A5: A-Fault PA | C5: ESPANOL | N5: =INDIRECT('D1-D2-D3'!$J$4&"!C15") -> Int. KSK-No. | O5: 11_KSRO-Ti
C6: FRANÇAIS | N6: =INDIRECT('D1-D2-D3'!$J$4&"!C18") -> Box Number | O6: 12_ KSRO-Me
A7: TOP FPQ | C7: MAGYAR | J7: =INDIRECT('D1-D2-D3'!$J$4&"!C94") -> In work | N7: External part Nr. | O7: 15_KSRO-Na
A8: TOP RR | C8: Македонски | J8: =INDIRECT('D1-D2-D3'!$J$4&"!C95") -> Completed | N8: KSK | O8: 42_KSMA-Ke2
A9: Serial Fault | C9: POLSKI | N9: P-Module | O9: 44_KSPY-As
A10: 0FG | C10: PORTUGESE | J10: =INDIRECT('D1-D2-D3'!$J$4&"!C218") -> Accepted | N10: Ident (Part Nr.) | O10: 49_KSMA-Ke
A11: System Audit | C11: ROMANA | J11: =INDIRECT('D1-D2-D3'!$J$4&"!C219") -> Rejected, accepted from customer/supplier/other Kroschu-plant | N11: =INDIRECT('D1-D2-D3'!$J$4&"!C41") -> Yes | O11: 50_KSCN-Ta
A12: TOP PA | C12: Српски | J12: =INDIRECT('D1-D2-D3'!$J$4&"!C220") -> Rejected | N12: =INDIRECT('D1-D2-D3'!$J$4&"!C42") -> No | O12: 51_KSK-Pi
A13: Destructive PA | C13: SLOVAK | J13: =INDIRECT('D1-D2-D3'!$J$4&"!C94") -> In work | O13: 52_KSD-Ji
A14: TOP 100% check | C14: УКРАЇНСьКА | O14: 54_KSME
A15: Optimization | C15: 中文 | J15: =INDIRECT('D1-D2-D3'!$J$4&"!C10") -> Customer | L15: =INDIRECT('D1-D2-D3'!$J$4&"!C20") -> Safety-relevant characterisitc | O15: 58_KSTN-Be
J16: =INDIRECT('D1-D2-D3'!$J$4&"!C74") -> on transit | L16: =INDIRECT('D1-D2-D3'!$J$4&"!C270") -> FuSi (Functional safety) | O16: 59_KSD-Ch
C17: =INDIRECT('D1-D2-D3'!$J$4&"!C139") -> Occurrence | J17: =INDIRECT('D1-D2-D3'!$J$4&"!C75") -> at Kroschu | O17: 60_KSD-Ti
C18: =INDIRECT('D1-D2-D3'!$J$4&"!C140") -> Non-detection | L18: =INDIRECT('D1-D2-D3'!$J$4&"!C222") -> PSC | O18: 61_KSK-La
J19: =INDIRECT('D1-D2-D3'!$J$4&"!C262") -> Start date | L19: =INDIRECT('D1-D2-D3'!$J$4&"!C271") -> PSC/ FSM | O19: 65_KSBR-Ma
C20: in process | J20: =INDIRECT('D1-D2-D3'!$J$4&"!C263") -> Closing date | O20: 66_KSMX-Le
C21: successful | J21: =INDIRECT('D1-D2-D3'!$J$4&"!C264") -> Result | O21: 70_KSK-An
C22: not successful | J22: =INDIRECT('D1-D2-D3'!$J$4&"!C265") -> Inform Prevention-Team | L22: high | O22: 71_KSBR-It
J23: =INDIRECT('D1-D2-D3'!$J$4&"!C266") -> New | L23: mid | O23: 73_KSBR-Ol
J24: =INDIRECT('D1-D2-D3'!$J$4&"!C267") -> Updated | L24: ALARP | O24: 75_KSMX-Ir
J25: =INDIRECT('D1-D2-D3'!$J$4&"!C268") -> Checked, NA | L25: low | O25: 77_KSRA
O26: 80_KSA
O27: 81_KSUA-Lu
O28: 83_KSSK
O29: 84_KSH
O30: 85_KSSR-Kr
O31: 87_KSUA-Zy
O32: 89_KSMK-Bt
O33: 94_KSME-Fu
O34: 95_KSMK-Sk

Sheet Amendments
A1: Amendments
A3: 23.12.2022 | B3: First release of this document.
A4: 27.02.2023 | B4: Hungarian language added.
A5: 22.06.2023 | B5: Portuguese language added.
A6: 45721 | B6: Basic Data: FuSi (Functional safety); D8: FSM added
A7: 45779 | B7: Added "09_KSTN-Be2" and "42_KSMA-Ke2" to Drop-down menu
A8: 45814 | B8: New: Tab "8D-Report (no link) Corrected: Fault code (363)
A9: 45853 | B9: Corrected: Fault codes

Sheet Lessons Learned Card
H1: LESSONS LEARNED CARD | V1: 4.15.07.00 Update: 01.12.2016/ AP/ tewit
V4: Nr.: | X4: Date:
A6: Problem: | N6: Photo / Sketch:
A13: Author:
A17: Plant:
A21: Project:
A25: Product:
A29: PCP:
A33: Equipment: | N33: Failure Code: | R33: =#REF! -> #REF!
A37: WIs & PIs: | N37: PSS Number: | R37: =#REF! -> #REF!
A41: Description of the failure:
A59: Corrective Action regards: | I59: Product | O59: Process | U59: Equipment
A62: Description of Corrective Action:
A84: Before Corrective Action | N84: After Corrective Action
A87: Photo/Sketch: | N87: Photo/Sketch:
A107: Following standards and documents have to be updated:
A110: Document | G110: Description of change | T110: Responsible * | X110: Date *
B129: * if not known in the plant, it will be decided by central AP

Sheet Fault catalogue
A1: FCs | C1: Descript. | D1: Catalogue issued on 05.2022
A2: 050 | C2: Wires swapped (wrong cavity)
A3: 052 | C3: Short circuit
A4: 060 | C4: Wire in wrong crimp/US connector
A5: 070 | C5: Wire missing
A6: 071 | C6: Too many wires
A7: 072 | C7: Wire not plugged (lost under taping)
A8: 074 | C8: Wire torn off
A9: 075 | C9: Wire cut
A10: 076 | C10: Wire not in connector/ not gripped
A11: 100 | C11: Wire colour wrong
A12: 101 | C12: Cross section too small
A13: 102 | C13: Cross section too great
... A35: 715 | C35: Wire wrongly routed
C36: Assembly wire harness/ branches
A37: 073 | C37: Wires swapped in wrong branch/ housing
A38: 080 | C38: Branch missing
A39: 081 | C39: Extra branch
A40: 082 | C40: Module missing
A41: 083 | C41: Extra module
A42: 084 | C42: Wrong module
A43: 085 | C43: Branch damaged
A44: 086 | C44: Module damaged
A45: 087 | C45: Incorrect building group fitted
A46: 390 | C46: Branch too long
A47: 391 | C47: Branch too short
A48: 521 | C48: Branch out wrong (orientation)
... A51: 381 | C51: Master dimension too small
C52: Water/ vacuum lead
A53: 740 | C53: Water/vacuum lead missing
A54: 741 | C54: Water/vacuum lead damaged, bent
A55: 742 | C55: Water/vacuum lead in wrong position
A56: 743 | C56: Water/vacuum lead not sealed
A57: 754 | C57: Water/vacuum lead wrong
A58: 755 | C58: Water/vacuum lead cap missing
C59: Fibre optic wire (LWL); Antennas; Ethernet wires
A60: 950 | C60: Damping too great
A61: 951 | C61: Wire recess too great
A62: 952 | C62: Wire recess too small
A63: 960 | C63: Bend radius too small
A64: 970 | C64: Radius delimiter missing
A65: 971 | C65: Wrong LWL/ antenna
A66: 972 | C66: LWL/ Antenna missing
A67: 973 | C67: Antenna assembled reversed
A68: 974 | C68: LWL/ Antenna damaged
A69: 975 | C69: LWL/ Antenna dimensionally not OK
A70: 976 | C70: Positioning not OK (X/ Y-Axis)
C71: CONNECTORS
C72: Crimp/pressed connection (plug-in -, ring terminal, barrel)
A73: 150 | C73: Insulation in crimp area
A74: 152 | C74: Conductor crimp empty
A75: 153 | C75: Single strands not gripped/ crimped on conductor crimp
A76: 154 | C76: Isocrimp open
A77: 155 | C77: Isocrimp too tight
A78: 157 | C78: Bell mouth not according to specification
A79: 158 | C79: Ring terminal not assembled together
A80: 159 | C80: Ring terminal assembled together wrongly
A81: 160 | C81: Terminal/ pressed connector wrong
A82: 161 | C82: Terminal/ pressed connector missing
A83: 162 | C83: Terminal/ pressed connector damaged, bent
A84: 163 | C84: Terminal broken
... A105: 192 | C105: Crimp barrel position wrong
C106: US-welded splice
A107: 151 | C107: Insulation in welded splice
A108: 156 | C108: Wrong position of conductor in welded splice
A109: 174 | C109: Peel strength not OK
A110: 201 | C110: No ultrasonic welding
A111: 202 | C111: Wire pulled out of welded splice
A112: 203 | C112: Welded splice broken/ damaged
A113: 420 | C113: Welded splice in wrong position
A114: 421 | C114: Welded splice high/ width not according to specification
A115: 422 | C115: Welded splice measure of length not according to specification
A116: 423 | C116: Welded splice overheated (blue discolouration)
A117: 424 | C117: Burr formation on welded splice not according to specification
A118: 570 | C118: Insulation sleeve on welded splice not watertight
C119: Comb connector
A120: 474 | C120: Comb connector wrong
A121: 486 | C121: Comb terminal not completely latched
A122: 487 | C122: Comb terminals pluged not in one direction
A123: 488 | C123: Comb connector deformed
A124: 489 | C124: Comb connector insulation (cover) not latched
A125: 490 | C125: Comb connector insulation (cover) damaged
A126: 491 | C126: Comb connector not sealed
A127: 492 | C127: Butyl stripes in wrong position in comb connector
A128: 493 | C128: Butyl on/ in torqueing area
A129: 494 | C129: Comb connector missing
C130: Insulation displacement connector
A131: 1100 | C131: Insulation displacement connector missing
A132: 1101 | C132: Insulation displacement connector wrong
A133: 1102 | C133: Insulation displacement connector damaged
A134: 1103 | C134: Incorrect pull-off force in Insulation displacement connector
A135: 1104 | C135: Wire insertion to the end not Ok
A136: 1105 | C136: Piercing depth not OK
A137: 1106 | C137: Insulation displacement connector not closed
A138: 262 | C138: Insulation displacement connector wrongly assembled
C139: Solder joints
A140: 180 | C140: Solder in terminal area
A141: 181 | C141: Cold solder joint
A142: 182 | C142: Solder under Insulation
A143: 183 | C143: Terminal not soldered
...

Sheet ENGLISH
A1: Deutsch | B1: English | C1: Landessprache/local language
A2: PROBLEMLÖSUNGSBLATT | B2: PROBLEM SOLVING SHEET | C2: PROBLEM SOLVING SHEET
A3: PSS No. | B3: PSS No. | C3: PSS No.
A4: Seite 1: D0-D1-D2-D3 | B4: Page 1: D0-D1-D2-D3 | C4: Page 1: D0-D1-D2-D3
A5: Sprache | B5: Language | C5: Language
A6: Fehlerart | B6: Fault type | C6: Fault type
A7: Grunddaten-Team-Problembeschreibung -Sofortige Maßnahme(n) | B7: Basic Data-Team-Problem Description-Immediate Action(s) | C7: Basic Data-Team-Problem Description-Immediate Action(s)
A8: Kroschu Werk | B8: Kroschu plant | C8: Kroschu plant
A9: Start Datum | B9: Opening date | C9: Opening date
A10: Kunde | B10: Customer | C10: Customer
A11: Projekt | B11: Project | C11: Project
A12: Kunden Reklamations Nr. | B12: Customer complaint No. | C12: Customer complaint No.
... A159: Kategorie | B159: Category | C159: Category
A160: Ursachenverifizierungs- methode | B160: Method of cause verification | C160: Method of cause verification | D160: 4
A161: D5 - Verbesserungsmaßnahmen | B161: D5 - Corrective Action(s) | C161: D5 - Corrective Action(s)
A162: D6 - Einführung der Korrekturmaßnahme(n) | B162: D6 - Implementation of permanent corrective action(s) | C162: D6 - Implementation of permanent corrective action(s)
A163: Maßnahmenplan | B163: Action Plan | C163: Action Plan
A164: Verbesserungsmaßnahme | B164: Corrective Action | C164: Corrective Action
A165: Bild Nr. | B165: Pic. No. | C165: Pic. No.
A166: Ziel-datum | B166: Target Date | C166: Target Date
A167: Wirksamkeitsnachweis/ Ablehnungsgrund | B167: Effectiveness check/ Rejection reason | C167: Effectiveness check/ Rejection reason
A168: Abschl.-datum | B168: Closure date | C168: Closure date
A169: Simulation | B169: Simulation | C169: Simulation
A170: Um die Grundursache zu bestätigen, muss der Fehler unter den gleichen Umständen reproduziert werden, wenn dies möglich ist | B170: In order to confirm root causes defect must be reproduced by creating same condition if possible | C170: In order to confirm root causes defect must be reproduced by creating same condition if possible
A171: Simulation möglich? | B171: Simulation possible? | C171: Simulation possible ?
A172: Wie wurde der Fehler nachgestellt? | B172: What was done to reproduce the fault? | C172: What was done to reproduce the fault ?
... A271: PSC/ FSM | B271: PSC/ FSM | C271: PSC/ FSM

Sheet DEUTSCH
A1: Deutsch | B1: English | C1: Landessprache/local language
A2: PROBLEMLÖSUNGSBLATT | B2: PROBLEM SOLVING SHEET | C2: PROBLEMLÖSUNGSBLATT
A3: PSS No. | B3: PSS No. | C3: PSS No.
A4: Seite 1: D0-D1-D2-D3 | B4: Page 1: D0-D1-D2-D3 | C4: Seite 1: D0-D1-D2-D3
A5: Sprache | B5: Language | C5: Sprache
A6: Fehlerart | B6: Fault type | C6: Fehlerart
A7: Grunddaten-Team-Problembeschreibung -Sofortige Maßnahme(n) | B7: Basic Data-Team-Problem Description-Immediate Action(s) | C7: Grunddaten-Team-Problembeschreibung -Sofortige Maßnahme(n)
A8: Kroschu Werk | B8: Kroschu plant | C8: Kroschu Werk
A9: Start Datum | B9: Opening date | C9: Start Datum
A10: Kunde | B10: Customer | C10: Kunde
A11: Projekt | B11: Project | C11: Projekt
A12: Kunden Reklamations Nr. | B12: Customer complaint No. | C12: Kunden Reklamations Nr.
... A159: Kategorie | B159: Category | C159: Kategorie
A160: Ursachenverifizierungs- methode | B160: Method of cause verification | C160: Ursachenverifizierungs- methode | D160: 4
A161: D5 - Verbesserungsmaßnahmen | B161: D5 - Corrective Action(s) | C161: D5 - Verbesserungsmaßnahmen
A162: D6 - Einführung der Korrekturmaßnahme(n) | B162: D6 - Implementation of permanent corrective action(s) | C162: D6 - Einführung der Korrekturmaßnahme(n)
A163: Maßnahmenplan | B163: Action Plan | C163: Maßnahmenplan
A164: Verbesserungsmaßnahme | B164: Corrective Action | C164: Verbesserungsmaßnahme
A165: Bild Nr. | B165: Pic. No. | C165: Bild Nr.
A166: Ziel-datum | B166: Target Date | C166: Ziel-datum
A167: Wirksamkeitsnachweis/ Ablehnungsgrund | B167: Effectiveness check/ Rejection reason | C167: Wirksamkeitsnachweis/ Ablehnungsgrund
A168: Abschl.-datum | B168: Closure date | C168: Abschl.-datum
A169: Simulation | B169: Simulation | C169: Simulation
A170: Um die Grundursache zu bestätigen, muss der Fehler unter den gleichen Umständen reproduziert werden, wenn dies möglich ist | B170: In order to confirm root causes defect must be reproduced by creating same condition if possible | C170: Um die Grundursache zu bestätigen, muss der Fehler unter den gleichen Umständen reproduziert werden, wenn dies möglich ist
A171: Simulation möglich? | B171: Simulation possible? | C171: Simulation möglich ?
A172: Wie wurde der Fehler nachgestellt? | B172: What was done to reproduce the fault? | C172: Wie wurde der Fehler nachgestellt ?
... A271: PSC/ FSM | B271: PSC/ FSM | C271: PSC/ FSM

Sheet CZECH
A1: Deutsch | B1: English | C1: Landessprache/local language
A2: PROBLEMLÖSUNGSBLATT | B2: PROBLEM SOLVING SHEET
A3: PSS No. | B3: PSS No.
A4: Seite 1: D0-D1-D2-D3 | B4: Page 1: D0-D1-D2-D3
A5: Sprache | B5: Language
A6: Fehlerart | B6: Fault type
A7: Grunddaten-Team-Problembeschreibung -Sofortige Maßnahme(n) | B7: Basic Data-Team-Problem Description-Immediate Action(s)
A8: Kroschu Werk | B8: Kroschu plant
A9: Start Datum | B9: Opening date
A10: Kunde | B10: Customer
A11: Projekt | B11: Project
A12: Kunden Reklamations Nr. | B12: Customer complaint No.
A13: Basis Daten | B13: Basic Data
... A269: Technische Betrachtungsfaktoren | B269: Technical consideration factors
A270: FuSi (Funktionale Sicherheit) | B270: FuSi (Functional safety) | C270: FuSi (Functional safety)
A271: PSC/ FSM | B271: PSC/ FSM | C271: PSC/ FSM

Sheet ESPANOL
A1: Deutsch | B1: English | C1: Landessprache/local language
A2: PROBLEMLÖSUNGSBLATT | B2: PROBLEM SOLVING SHEET | C2: HOJA DE SOLUCION DE PROBLEMAS
A3: PSS No. | B3: PSS No. | C3: N° PSS
A4: Seite 1: D0-D1-D2-D3 | B4: Page 1: D0-D1-D2-D3 | C4: Página 1: D0-D1-D2-D3
A5: Sprache | B5: Language | C5: Idioma
A6: Fehlerart | B6: Fault type | C6: Tipo de falla
A7: Grunddaten-Team-Problembeschreibung -Sofortige Maßnahme(n) | B7: Basic Data-Team-Problem Description-Immediate Action(s) | C7: Datos básicos-Equipo-Descripción del Problema -Acción(es) inmediatas
A8: Kroschu Werk | B8: Kroschu plant | C8: Planta Kroschu
A9: Start Datum | B9: Opening date | C9: Fecha de inicio
A10: Kunde | B10: Customer | C10: Cliente
A11: Projekt | B11: Project | C11: Proyecto
A12: Kunden Reklamations Nr. | B12: Customer complaint No. | C12: Nº reclamación de cliente
... A271: PSC/ FSM | B271: PSC/ FSM | C271: PSC/ FSM

Sheet FRANÇAIS
A1: Deutsch | B1: English | C1: Landessprache/local language
A2: PROBLEMLÖSUNGSBLATT | B2: PROBLEM SOLVING SHEET
A3: PSS No. | B3: PSS No.
A4: Seite 1: D0-D1-D2-D3 | B4: Page 1: D0-D1-D2-D3
A5: Sprache | B5: Language
A6: Fehlerart | B6: Fault type
A7: Grunddaten-Team-Problembeschreibung -Sofortige Maßnahme(n) | B7: Basic Data-Team-Problem Description-Immediate Action(s)
A8: Kroschu Werk | B8: Kroschu plant
A9: Start Datum | B9: Opening date
A10: Kunde | B10: Customer
A11: Projekt | B11: Project
A12: Kunden Reklamations Nr. | B12: Customer complaint No.
A13: Basis Daten | B13: Basic Data
... A269: Technische Betrachtungsfaktoren | B269: Technical consideration factors
A270: FuSi (Funktionale Sicherheit) | B270: FuSi (Functional safety) | C270: FuSi (Functional safety)
A271: PSC/ FSM | B271: PSC/ FSM | C271: PSC/ FSM

Sheet MAGYAR
A1: Deutsch | B1: English | C1: Landessprache/local language
A2: PROBLEMLÖSUNGSBLATT | B2: PROBLEM SOLVING SHEET | C2: Hibamegoldólap
A3: PSS No. | B3: PSS No. | C3: PSS sz.
A4: Seite 1: D0-D1-D2-D3 | B4: Page 1: D0-D1-D2-D3 | C4: Oldal 1: D0-D1-D2-D3
A5: Sprache | B5: Language | C5: Nyelv
A6: Fehlerart | B6: Fault type | C6: Hibatípus
A7: Grunddaten-Team-Problembeschreibung -Sofortige Maßnahme(n) | B7: Basic Data-Team-Problem Description-Immediate Action(s) | C7: Alapadatok-csapat-probléma leírása-azonnali intézkedések
A8: Kroschu Werk | B8: Kroschu plant | C8: Kroschu gyár
A9: Start Datum | B9: Opening date | C9: Kezdeti dátum
A10: Kunde | B10: Customer | C10: Vevõ
A11: Projekt | B11: Project | C11: Projekt
A12: Kunden Reklamations Nr. | B12: Customer complaint No. | C12: Vevõi reklamáció sz.
... A271: PSC/ FSM | B271: PSC/ FSM | C271: PSC/ FSM

Sheet Македонски
A1: Deutsch | B1: English | C1: Landessprache/local language
A2: PROBLEMLÖSUNGSBLATT | B2: PROBLEM SOLVING SHEET | C2: ОБРАЗЕЦ ЗА РЕШАВАЊЕ ПРОБЛЕМИ
A3: PSS No. | B3: PSS No. | C3: PSS бр.
A4: Seite 1: D0-D1-D2-D3 | B4: Page 1: D0-D1-D2-D3 | C4: Страница 1: D0-D1-D2-D3
A5: Sprache | B5: Language | C5: Јазик
A6: Fehlerart | B6: Fault type | C6: Тип на дефект
A7: Grunddaten-Team-Problembeschreibung -Sofortige Maßnahme(n) | B7: Basic Data-Team-Problem Description-Immediate Action(s) | C7: Основни податоци-Тим-Опис на проблемот-Итни мерки
A8: Kroschu Werk | B8: Kroschu plant | C8: Kroschu фабрика
A9: Start Datum | B9: Opening date | C9: Датум на отворање
A10: Kunde | B10: Customer | C10: Клиент
A11: Projekt | B11: Project | C11: Проект
A12: Kunden Reklamations Nr. | B12: Customer complaint No. | C12: Бр.на рекламација од клиент
... A271: PSC/ FSM | B271: PSC/ FSM | C271: PSC/ FSM

Sheet PORTUGESE
A1: Deutsch | B1: English | C1: Landessprache/local language
A2: PROBLEMLÖSUNGSBLATT | B2: PROBLEM SOLVING SHEET | C2: FOLHA DE SOLUÇÃO DE PROBLEMAS
A3: PSS No. | B3: PSS No. | C3: nº PSS
A4: Seite 1: D0-D1-D2-D3 | B4: Page 1: D0-D1-D2-D3 | C4: Página 1: D0-D1-D2-D3
A5: Sprache | B5: Language | C5: Idioma
A6: Fehlerart | B6: Fault type | C6: Tipo de falha
A7: Grunddaten-Team-Problembeschreibung -Sofortige Maßnahme(n) | B7: Basic Data-Team-Problem Description-Immediate Action(s) | C7: Dados básicos-Equipe-Descrição do Problema -Ação (ões) imediatas
A8: Kroschu Werk | B8: Kroschu plant | C8: Planta da Kroschu
A9: Start Datum | B9: Opening date | C9: Data de início
A10: Kunde | B10: Customer | C10: Cliente
A11: Projekt | B11: Project | C11: Projeto
A12: Kunden Reklamations Nr. | B12: Customer complaint No. | C12: Nº reclamação do cliente
... A271: PSC/ FSM | B271: PSC/ FSM | C271: PSC/ FSM

Sheet ROMANA
A1: Deutsch | B1: English | C1: Landessprache/local language
A2: PROBLEMLÖSUNGSBLATT | B2: PROBLEM SOLVING SHEET | C2: FORMULAR DE REZOLVARE A PROBLEMEI
A3: PSS No. | B3: PSS No. | C3: PSS Nr.
A4: Seite 1: D0-D1-D2-D3 | B4: Page 1: D0-D1-D2-D3 | C4: Pagina 1: D0-D1-D2-D3
A5: Sprache | B5: Language | C5: Limba
A6: Fehlerart | B6: Fault type | C6: Tip defect
A7: Grunddaten-Team-Problembeschreibung -Sofortige Maßnahme(n) | B7: Basic Data-Team-Problem Description-Immediate Action(s) | C7: Date de bază-Echipa-Descrierea problemei-Acțiuni imediate
A8: Kroschu Werk | B8: Kroschu plant | C8: Fabrica Kroschu
A9: Start Datum | B9: Opening date | C9: Data de Start
A10: Kunde | B10: Customer | C10: Client
A11: Projekt | B11: Project | C11: Proiect
A12: Kunden Reklamations Nr. | B12: Customer complaint No. | C12: Reclamație client Nr.
... A271: PSC/ FSM | B271: PSC/ FSM | C271: PSC/ FSM

Sheet Српски
A1: Deutsch | B1: English | C1: Landessprache/local language
A2: PROBLEMLÖSUNGSBLATT | B2: PROBLEM SOLVING SHEET
A3: PSS No. | B3: PSS No.
A4: Seite 1: D0-D1-D2-D3 | B4: Page 1: D0-D1-D2-D3
A5: Sprache | B5: Language
A6: Fehlerart | B6: Fault type
A7: Grunddaten-Team-Problembeschreibung -Sofortige Maßnahme(n) | B7: Basic Data-Team-Problem Description-Immediate Action(s)
A8: Kroschu Werk | B8: Kroschu plant
A9: Start Datum | B9: Opening date
A10: Kunde | B10: Customer
A11: Projekt | B11: Project
A12: Kunden Reklamations Nr. | B12: Customer complaint No.
A13: Basis Daten | B13: Basic Data
... A269: Technische Betrachtungsfaktoren | B269: Technical consideration factors
A270: FuSi (Funktionale Sicherheit) | B270: FuSi (Functional safety) | C270: FuSi (Functional safety)
A271: PSC/ FSM | B271: PSC/ FSM | C271: PSC/ FSM

Sheet SLOVAK
A1: Deutsch | B1: English | C1: Landessprache/local language
A2: PROBLEMLÖSUNGSBLATT | B2: PROBLEM SOLVING SHEET | C2: HÁROK NA RIEŠENIE PROBLÉMOV
A3: PSS No. | B3: PSS No. | C3: PSS č.
A4: Seite 1: D0-D1-D2-D3 | B4: Page 1: D0-D1-D2-D3 | C4: Strana 1: D0-D1-D2-D3
A5: Sprache | B5: Language | C5: Jazyk
A6: Fehlerart | B6: Fault type | C6: Typ chyby
A7: Grunddaten-Team-Problembeschreibung -Sofortige Maßnahme(n) | B7: Basic Data-Team-Problem Description-Immediate Action(s) | C7: Základné údaje-Tím-Popis problému– okamžitá(é) opatrenie(a)
A8: Kroschu Werk | B8: Kroschu plant | C8: Závod Kroschu
A9: Start Datum | B9: Opening date | C9: Dátum začiatku
A10: Kunde | B10: Customer | C10: Zákazník
A11: Projekt | B11: Project | C11: Projekt
A12: Kunden Reklamations Nr. | B12: Customer complaint No. | C12: Číslo reklamácie zákazníka
... A271: PSC/ FSM | B271: PSC/ FSM | C271: PSC/ FSM

Sheet УКРАЇНСьКА
A1: Deutsch | B1: English | C1: Landessprache/local language
A2: PROBLEMLÖSUNGSBLATT | B2: PROBLEM SOLVING SHEET
A3: PSS No. | B3: PSS No.
A4: Seite 1: D0-D1-D2-D3 | B4: Page 1: D0-D1-D2-D3
A5: Sprache | B5: Language
A6: Fehlerart | B6: Fault type
A7: Grunddaten-Team-Problembeschreibung -Sofortige Maßnahme(n) | B7: Basic Data-Team-Problem Description-Immediate Action(s)
A8: Kroschu Werk | B8: Kroschu plant
A9: Start Datum | B9: Opening date
A10: Kunde | B10: Customer
A11: Projekt | B11: Project
A12: Kunden Reklamations Nr. | B12: Customer complaint No.
A13: Basis Daten | B13: Basic Data
... A269: Technische Betrachtungsfaktoren | B269: Technical consideration factors
A270: FuSi (Funktionale Sicherheit) | B270: FuSi (Functional safety) | C270: FuSi (Functional safety)
A271: PSC/ FSM | B271: PSC/ FSM | C271: PSC/ FSM

Sheet 中文
A1: Deutsch | B1: English | C1: Landessprache/local language
A2: PROBLEMLÖSUNGSBLATT | B2: PROBLEM SOLVING SHEET
A3: PSS No. | B3: PSS No.
A4: Seite 1: D0-D1-D2-D3 | B4: Page 1: D0-D1-D2-D3
A5: Sprache | B5: Language
A6: Fehlerart | B6: Fault type
A7: Grunddaten-Team-Problembeschreibung -Sofortige Maßnahme(n) | B7: Basic Data-Team-Problem Description-Immediate Action(s)
A8: Kroschu Werk | B8: Kroschu plant
A9: Start Datum | B9: Opening date
A10: Kunde | B10: Customer
A11: Projekt | B11: Project
A12: Kunden Reklamations Nr. | B12: Customer complaint No.
A13: Basis Daten | B13: Basic Data
... A269: Technische Betrachtungsfaktoren | B269: Technical consideration factors
A270: FuSi (Funktionale Sicherheit) | B270: FuSi (Functional safety) | C270: FuSi (Functional safety)
A271: PSC/ FSM | B271: PSC/ FSM | C271: PSC/ FSM
